Workbook

Sheet v1.0-MVP
A1: 任务ID | B1: 任务名称 | C1: TDD阶段 | D1: 所属模块 | E1: 优先级 | F1: 负责角色 | G1: 预估工时 | H1: 开始周 | I1: 结束周 | J1: 前置依赖 | K1: 状态 | L1: 详细任务提示词 | M1: 验收标准 | N1: 备注
A2: MVP-CLI-001 | B2: 克隆VS Code OSS仓库，配置开发环境 | C2: 基础设施 | D2: 客户端基础 | E2: P0 | F2: 全栈 | G2: 2 | H2: 2026-W14 | I2: 2026-W14 | K2: 未开始 | L2: 【目标】搭建织梦笔客户端开发环境，基于VS Code OSS Fork 【技术选型】VS Code OSS (microsoft/vscode), Node.js 20+, Yarn 1.22+ 【具体步骤】 1. 克隆仓库：git clone https://github.com/microsoft/vscode.git --depth 1 2. 安装Node.js 20+：确认node -v >= 20.0.0, npm -v >= 10.0.0 3. 安装Yarn：corepack enable && corepack prepare yarn@1.22.22 --activate 4. 安装依赖：cd vscode && yarn install 5. 编译验证：yarn watch（等待编译完成，确认无错误） 6. 运行验证：yarn electron（启动Electron应用，确认VS Code正常打开） 7. 配置开发环境： - 创建.vscode/settings.json，配置TypeScript strict模式 - 配置ESLint：.eslintrc.json继承VS Code规则 - 配置Prettier：.prettierrc统一代码风格 - 配置launch.json用于F5调试 【配置内容】 { "typescript.tsdk": "node_modules/typescript/lib", "typescript.enablePromptUseWorkspaceTsdk": true, "editor.formatOnSave": true, "editor.defaultFormatter": "esbenp.prettier-vscode" } 【验证命令】yarn watch && yarn electron 【预期结果】VS Code OSS成功编译并启动，无任何错误或警告 | M2: VS Code OSS成功编译启动，F5可调试，ESLint/Prettier配置生效
A3: MVP-CLI-002 | B3: 修改product.json品牌化 | C3: Green实现 | D3: 客户端基础 | E3: P0 | F3: 前端 | G3: 1 | H3: 2026-W14 | I3: 2026-W14 | J3: MVP-CLI-001 | K3: 未开始 | L3: 【目标】将VS Code OSS品牌化为「织梦笔」 【源文件路径】product.json 【实现步骤】 1. 修改product.json中的品牌字段： - nameShort: "织梦笔" - nameLong: "织梦笔 - AI驱动的小说创作工具" - applicationName: "dreamweaver-pen" - dataFolderName: "DreamweaverPen" - reportIssueUrl: "https://github.com/dreamweaver-pen/issues" - licenseUrl: "https://github.com/dreamweaver-pen/license" 2. 替换extensionsGallery端点为自建： - 将"extensionsGallery.serviceUrl"替换为自建扩展市场地址 - 或设为空字符串禁用默认扩展市场 3. 禁用遥测： - 将"enableTelemetry"设为false - 将"aiServices"相关配置清空或禁用 4. 修改quality参数为"oss" 5. 验证yarn watch编译通过 6. 启动应用验证标题栏显示"织梦笔" 【关键代码结构】 - product.json: { nameShort, nameLong, applicationName, dataFolderName, extensionsGallery, enableTelemetry } 【运行命令】yarn watch && yarn electron 【预期结果】应用标题显示"织梦笔"，数据存储在DreamweaverPen目录 | M3: 应用标题显示「织梦笔」，数据目录为DreamweaverPen，遥测已禁用，编译无错误
A4: MVP-CLI-003 | B4: 替换图标和资源文件 | C4: Green实现 | D4: 客户端基础 | E4: P0 | F4: 前端 | G4: 1 | H4: 2026-W14 | I4: 2026-W14 | J4: MVP-CLI-002 | K4: 未开始 | L4: 【目标】替换VS Code OSS默认图标为织梦笔品牌图标 【源文件路径】resources/目录 【实现步骤】 1. 准备织梦笔Logo设计稿（由设计师提供，路径：assets/brand/logo/） 2. 替换各平台图标文件： - macOS: resources/darwin/code.icns → 替换为织梦笔.icns（需要iconutil工具转换） - Windows: resources/win32/code_150x150.png, code_70x70.png, code.ico → 替换为织梦笔图标 - Linux: resources/linux/code.png → 替换为织梦笔.png 3. 替换窗口图标： - resources/code-icon.svg → 替换为织梦笔SVG 4. 生成各尺寸PNG（使用sharp或ImageMagick）： - 16x16, 32x32, 48x48, 64x64, 128x128, 256x256, 512x512 5. 生成macOS .icns文件：iconutil -c icns icon.iconset 6. 生成Windows .ico文件：使用ImageMagick或在线工具 7. 验证各平台图标显示正确 【配置内容】 - macOS图标尺寸：16/32/128/256/512/1024 - Windows图标尺寸：16/32/48/64/128/256 - Linux图标尺寸：64/128/256/512 【验证命令】yarn watch && yarn electron（各平台分别验证） 【预期结果】各平台任务栏、窗口标题、桌面快捷方式均显示织梦笔图标 | M4: macOS/Windows/Linux各平台图标均正确显示织梦笔Logo，无残留VS Code图标
A5: MVP-CLI-004 | B5: 移除不需要的内置功能 | C5: Green实现 | D5: 客户端基础 | E5: P1 | F5: 前端 | G5: 2 | H5: 2026-W14 | I5: 2026-W15 | J5: MVP-CLI-002 | K5: 未开始 | L5: 【目标】移除VS Code中与小说创作无关的内置功能，精简编辑器 【源文件路径】extensions/, src/vs/workbench/contrib/ 【实现步骤】 1. 从extensions/目录移除以下内置扩展： - extensions/debugger-auto-launch/ → 调试器自动启动 - extensions/git/ → Git集成 - extensions/git-base/ → Git基础 - extensions/merge-conflict/ → 合并冲突 - extensions/npm/ → NPM支持 - extensions/debugger-core/ → 调试器核心 - extensions/typescript-language-features/ → 保留但精简 2. 从src/vs/workbench/contrib/移除对应贡献点： - contrib/debug/ → 调试视图 - contrib/scm/ → 源代码管理 - contrib/terminal/ → 终端（可选保留） - contrib/testing/ → 测试面板 - contrib/remote/ → 远程开发 3. 修改默认布局配置： - 隐藏Debug视图 - 隐藏Source Control视图 - 隐藏Extensions视图（或替换为织梦笔扩展市场） 4. 清理package.json中的扩展依赖 5. 验证编译通过：yarn watch 6. 验证移除的面板不再显示 【关键代码结构】 - extensions/ → 删除不需要的扩展目录 - src/vs/workbench/contrib/ → 删除不需要的贡献点 - src/vs/workbench/browser/workbench.contribution.ts → 移除注册 【运行命令】yarn watch（编译验证） 【预期结果】编译通过，移除的面板不再显示，保留核心编辑功能 | M5: 移除的功能面板不再显示，编译无错误，核心编辑功能正常
A6: MVP-CLI-005 | B6: 修改默认Workbench布局 | C6: Green实现 | D6: 客户端基础 | E6: P1 | F6: 前端 | G6: 2 | H6: 2026-W15 | I6: 2026-W15 | J6: MVP-CLI-004 | K6: 未开始 | L6: 【目标】将VS Code默认布局改造为织梦笔小说创作工作台布局 【源文件路径】src/vs/workbench/browser/, src/vs/workbench/contrib/activitybar/ 【实现步骤】 1. 修改Activity Bar默认图标和顺序： - 大纲（📖）→ Story Explorer / 大纲视图 - 分支（🌿）→ Branch Manager / 分支管理 - 知识库（📚）→ Story Bible / 知识库 - AI（🤖）→ AI Assistant / AI助手 - 统计（📊）→ Analytics / 数据统计 - 设置（⚙️）→ Settings / 设置 2. 修改默认侧边栏： - 默认展开"大纲"视图 - 隐藏Explorer文件树（或替换为Story Explorer） 3. 修改底部面板： - 默认面板：AI日志 / 一致性报告 / 版本历史 - 移除Terminal/Problems/Output面板 4. 修改状态栏： - 左侧：显示当前章节名 / 字数统计 - 中间：显示当前AI模型 / Token用量 - 右侧：显示一致性状态 / 保存状态 5. 修改欢迎页： - 替换为织梦笔欢迎页，显示最近作品和快速操作 【关键代码结构】 - src/vs/workbench/browser/parts/activitybar/activitybarActions.ts → 修改Activity Bar项 - src/vs/workbench/browser/parts/statusbar/statusbarPart.ts → 修改状态栏 - src/vs/workbench/contrib/welcome/gettingStarted/ → 修改欢迎页 【运行命令】yarn watch && yarn electron 【预期结果】启动后显示织梦笔定制布局，Activity Bar图标和顺序正确 | M6: Activity Bar显示6个定制图标，侧边栏默认展开大纲，状态栏显示字数/模型/一致性
A7: MVP-CLI-006 | B7: 配置测试框架 | C7: 基础设施 | D7: 客户端基础 | E7: P0 | F7: 全栈 | G7: 1 | H7: 2026-W14 | I7: 2026-W14 | J7: MVP-CLI-001 | K7: 未开始 | L7: 【目标】配置VS Code Extension的单元测试和集成测试框架 【技术选型】Vitest + @vscode/test-electron 【配置文件路径】vitest.config.ts, src/vscode.d.ts 【具体步骤】 1. 安装测试依赖： npm install -D vitest @vitest/coverage-v8 @vscode/test-electron 2. 创建vitest.config.ts： - 配置test.include: ["extensions/**/*.test.ts", "src/**/*.test.ts"] - 配置coverage.provider: "v8" - 配置coverage.reporter: ["text", "html", "lcov"] - 配置test.environment: "node" 3. 创建测试示例文件extensions/dw-ai-assistant/__tests__/sample.test.ts： - describe("Sample Test Suite", () => { it("should pass", () => { expect(1+1).toBe(2); }); }) 4. 配置package.json scripts： - "test": "vitest run" - "test:watch": "vitest" - "test:coverage": "vitest run --coverage" - "test:e2e": "vscode-test" 5. 配置CI集成（为GitHub Actions准备） 6. 运行测试验证框架可用 【配置内容】 // vitest.config.ts import { defineConfig } from 'vitest/config'; export default defineConfig({ test: { include: ['extensions/**/*.test.ts'], coverage: { provider: 'v8', reporter: ['text', 'html'] }, }, }); 【验证命令】npm test 【预期结果】测试框架正确运行，示例测试通过，coverage报告生成 | M7: Vitest测试框架配置完成，示例测试通过，coverage报告可生成
A8: MVP-CLI-007 | B8: 配置GitHub Actions CI | C8: 基础设施 | D8: 客户端基础 | E8: P1 | F8: 全栈 | G8: 1 | H8: 2026-W15 | I8: 2026-W15 | J8: MVP-CLI-006 | K8: 未开始 | L8: 【目标】配置GitHub Actions持续集成流水线 【技术选型】GitHub Actions 【配置文件路径】.github/workflows/ci.yml 【具体步骤】 1. 创建.github/workflows/ci.yml 2. 配置触发条件： - push: branches: [main, develop] - pull_request: branches: [main] 3. 配置lint job： - runs-on: ubuntu-latest - steps: checkout → setup Node.js 20 → yarn install → yarn lint 4. 配置test job： - runs-on: ubuntu-latest - steps: checkout → setup Node.js 20 → yarn install → yarn test - 上传coverage报告为artifact 5. 配置build job： - runs-on: ubuntu-latest - steps: checkout → setup Node.js 20 → yarn install → yarn compile 6. 配置缓存加速： - actions/cache@v4 缓存 node_modules - 缓存 .yarn/cache 7. 配置矩阵测试（可选）：Node.js 20/21 【配置内容】 name: CI on: { push: { branches: [main, develop] }, pull_request: { branches: [main] } } jobs: lint: { runs-on: ubuntu-latest, steps: [checkout, setup-node@20, yarn install, yarn lint] } test: { runs-on: ubuntu-latest, steps: [checkout, setup-node@20, yarn install, yarn test, upload-coverage] } build: { runs-on: ubuntu-latest, steps: [checkout, setup-node@20, yarn install, yarn compile] } 【验证命令】推送代码到GitHub，查看Actions页面 【预期结果】CI流水线lint/test/build三个job全部通过 | M8: GitHub Actions CI配置完成，push/PR触发lint/test/build三个job，全部通过
A9: MVP-SRV-001 | B9: 初始化Go微服务项目 | C9: 基础设施 | D9: 服务端基础 | E9: P0 | F9: 后端 | G9: 2 | H9: 2026-W14 | I9: 2026-W14 | K9: 未开始 | L9: 【目标】搭建织梦笔后端Go微服务项目基础架构 【技术选型】Go 1.22+, Gin, golangci-lint 【配置文件路径】go.mod, Makefile, cmd/, internal/, pkg/ 【具体步骤】 1. 创建项目根目录server/ 2. 初始化Go Module：go mod init github.com/dreamweaver-pen/server 3. 创建monorepo目录结构： server/ ├── cmd/ │ ├── user-service/main.go │ ├── work-service/main.go │ ├── chapter-service/main.go │ ├── branch-service/main.go │ └── bible-service/main.go ├── internal/ │ ├── config/ # 配置管理 │ ├── middleware/ # 中间件 │ ├── models/ # 数据模型 │ └── repository/ # 数据访问层 ├── pkg/ │ ├── response/ # 统一响应 │ ├── logger/ # 日志 │ └── utils/ # 工具函数 ├── go.mod ├── go.sum ├── Makefile └── .golangci.yml 4. 配置Makefile： - make build: 编译所有服务 - make test: 运行测试 - make lint: 代码检查 - make run SERVICE=user: 运行指定服务 5. 配置golangci-lint：.golangci.yml 6. 创建健康检查端点：GET /health → {"status": "ok", "service": "user-service"} 7. 验证编译和运行 【配置内容】 # Makefile .PHONY: build test lint run build: go build -o bin/ ./cmd/... test: go test -v -cover ./... lint: golangci-lint run run: go run ./cmd/$(SERVICE) 【验证命令】make build && make test && make run SERVICE=user-service 【预期结果】所有服务编译成功，健康检查端点返回200 | M9: Go项目结构创建完成，所有服务编译通过，健康检查返回200
A10: MVP-SRV-002 | B10: 初始化Python AI服务项目 | C10: 基础设施 | D10: 服务端基础 | E10: P0 | F10: AI工程师 | G10: 2 | H10: 2026-W14 | I10: 2026-W14 | K10: 未开始 | L10: 【目标】搭建织梦笔AI引擎Python服务基础架构 【技术选型】Python 3.12+, FastAPI, uvicorn, pytest, ruff 【配置文件路径】ai-service/pyproject.toml, ai-service/app/ 【具体步骤】 1. 创建ai-service/目录 2. 初始化项目：创建pyproject.toml 3. 创建目录结构： ai-service/ ├── app/ │ ├── __init__.py │ ├── main.py # FastAPI应用入口 │ ├── api/ │ │ ├── __init__.py │ │ ├── routes/ │ │ │ ├── ai.py # AI生成端点 │ │ │ ├── rag.py # RAG端点 │ │ │ └── consistency.py # 一致性检查端点 │ │ └── deps.py # 依赖注入 │ ├── services/ │ │ ├── __init__.py │ │ ├── ai_service.py # AI服务核心 │ │ ├── rag_service.py # RAG服务 │ │ ├── consistency/ # 一致性检查 │ │ └── entity_extractor.py # 实体提取 │ ├── adapters/ │ │ ├── __init__.py │ │ ├── base.py # 适配器基类 │ │ ├── claude.py # Claude适配器 │ │ ├── deepseek.py # DeepSeek适配器 │ │ └── qwen.py # 通义千问适配器 │ ├── models/ │ │ ├── __init__.py │ │ └── schemas.py # Pydantic模型 │ └── config.py # 配置管理 ├── tests/ │ ├── conftest.py │ ├── test_ai.py │ └── test_rag.py ├── pyproject.toml └── ruff.toml 4. 配置pyproject.toml： - 依赖：fastapi, uvicorn, anthropic, openai, pymilvus, redis, elasticsearch - 开发依赖：pytest, pytest-asyncio, httpx, ruff, mypy 5. 配置ruff.toml：lint规则 6. 创建健康检查端点：GET /health 7. 验证uvicorn运行 【配置内容】 # pyproject.toml (关键部分) [project] name = "dreamweaver-ai" requires-python = ">=3.12" dependencies = ["fastapi>=0.110", "uvicorn>=0.27", "anthropic>=0.18", "openai>=1.12"] [tool.pytest.ini_options] asyncio_mode = "auto" 【验证命令】cd ai-service && uvicorn app.main:app --reload 【预期结果】FastAPI服务启动，/health返回200，Swagger文档可访问 | M10: Python AI服务结构创建完成，FastAPI启动成功，/health返回200，Swagger可访问
A11: MVP-SRV-003 | B11: 搭建PostgreSQL + Schema迁移 | C11: 基础设施 | D11: 服务端基础 | E11: P0 | F11: 后端 | G11: 1 | H11: 2026-W14 | I11: 2026-W14 | K11: 未开始 | L11: 【目标】搭建PostgreSQL数据库并创建全部数据表 【技术选型】PostgreSQL 16, golang-migrate 【配置文件路径】docker-compose.yml, migrations/001_init_schema.sql 【具体步骤】 1. 在docker-compose.yml中添加PostgreSQL 16服务： - image: postgres:16-alpine - ports: 5432:5432 - environment: POSTGRES_DB=dreamweaver, POSTGRES_USER=dw, POSTGRES_PASSWORD=dw_secret - volumes: pgdata:/var/lib/postgresql/data 2. 创建migrations/001_init_schema.sql，包含以下12张表： a. users: id, email, password_hash, nickname, avatar_url, created_at, updated_at b. user_settings: id, user_id, default_model, writing_style, auto_save_interval c. user_model_configs: id, user_id, model_id, api_key_encrypted, is_active d. works: id, user_id, title, genre, description, status, word_count, created_at, updated_at e. chapters: id, work_id, volume_number, chapter_number, title, content, status, word_count, branch_id, created_at, updated_at f. chapter_versions: id, chapter_id, version_number, content, word_count, commit_message, created_at g. branches: id, work_id, parent_id, name, branch_type, fork_point_chapter_id, fork_point_version_id, is_active, created_at h. story_bible_entries: id, work_id, entry_type, name, description, attributes_json, tags, created_at, updated_at i. story_bible_relations: id, work_id, source_entry_id, target_entry_id, relation_type, description j. ai_generation_logs: id, user_id, work_id, chapter_id, model_id, prompt_tokens, completion_tokens, latency_ms, created_at k. consistency_reports: id, work_id, chapter_id, warnings_json, score, created_at l. foreshadowing: id, work_id, chapter_id, description, status, resolved_chapter_id, created_at, updated_at 3. 配置golang-migrate工具 4. 执行迁移验证 【配置内容】 # docker-compose.yml (PostgreSQL部分) postgres: image: postgres:16-alpine ports: ["5432:5432"] environment: POSTGRES_DB: dreamweaver POSTGRES_USER: dw POSTGRES_PASSWORD: dw_secret volumes: [pgdata:/var/lib/postgresql/data] 【验证命令】docker-compose up postgres && migrate -path migrations -database "postgres://dw:dw_secret@localhost:5432/dreamweaver?sslmode=disable" up 【预期结果】PostgreSQL启动成功，12张表创建成功，外键关系正确 | M11: PostgreSQL启动成功，12张表全部创建，外键关系正确，迁移可重复执行
A12: MVP-SRV-004 | B12: 搭建Redis缓存 | C12: 基础设施 | D12: 服务端基础 | E12: P1 | F12: 后端 | G12: 1 | H12: 2026-W14 | I12: 2026-W14 | K12: 未开始 | L12: 【目标】搭建Redis缓存服务，用于会话管理、Token缓存、限流计数 【技术选型】Redis 7, go-redis/v9 (Go), redis-py (Python) 【配置文件路径】docker-compose.yml, pkg/cache/redis.go, app/config.py 【具体步骤】 1. docker-compose.yml添加Redis 7服务： - image: redis:7-alpine - ports: 6379:6379 - command: redis-server --maxmemory 256mb --maxmemory-policy allkeys-lru - volumes: redisdata:/data 2. Go集成go-redis/v9： - pkg/cache/redis.go → NewRedisClient(addr, password) → Get/Set/Del/Expire - 配置连接池：PoolSize=10, MinIdleConns=2 3. Python集成redis-py： - app/config.py → REDIS_URL配置 - app/services/cache.py → get_redis_client() → get/set/delete 4. 编写缓存工具函数： - cache_get(key) → Optional[bytes] - cache_set(key, value, ttl) → bool - cache_delete(key) → bool - cache_incr(key) → int（用于限流计数） 5. 验证读写正常 【配置内容】 # Go连接配置 redis.NewClient(&redis.Options{ Addr: "localhost:6379", Password: "", PoolSize: 10, MinIdleConns: 2, }) 【验证命令】docker-compose up redis && redis-cli ping → PONG 【预期结果】Redis启动成功，Go和Python客户端均可正常读写 | M12: Redis启动成功，Go/Python客户端读写正常，连接池配置生效
A13: MVP-SRV-005 | B13: 搭建RabbitMQ消息队列 | C13: 基础设施 | D13: 服务端基础 | E13: P1 | F13: 后端 | G13: 1 | H13: 2026-W15 | I13: 2026-W15 | K13: 未开始 | L13: 【目标】搭建RabbitMQ消息队列，用于异步任务（AI生成、实体提取、一致性检查） 【技术选型】RabbitMQ 3.13, amqp091-go (Go), pika (Python) 【配置文件路径】docker-compose.yml, pkg/mq/rabbitmq.go, app/services/mq.py 【具体步骤】 1. docker-compose.yml添加RabbitMQ 3.13服务： - image: rabbitmq:3.13-management-alpine - ports: 5672:5672 (AMQP), 15672:15672 (管理界面) - environment: RABBITMQ_DEFAULT_USER=dw, RABBITMQ_DEFAULT_PASS=dw_secret 2. 定义Exchange和Queue： - Exchange: dw.direct (direct类型) - Queue: dw.chapter.saved → 章节保存后触发实体提取+一致性检查 - Queue: dw.ai.generation.request → AI生成请求 - Queue: dw.ai.generation.result → AI生成结果 - Queue: dw.consistency.check.request → 一致性检查请求 - Queue: dw.consistency.check.result → 一致性检查结果 3. Go集成amqp091-go： - pkg/mq/rabbitmq.go → NewRabbitMQClient() → Publish/Consume - 定义消息格式：JSON { task_type, payload, created_at } 4. Python集成pika： - app/services/mq.py → get_mq_connection() → publish/consume 5. 验证消息发布和消费 【配置内容】 # Queue绑定 dw.chapter.saved → routing_key: chapter.saved dw.ai.generation.request → routing_key: ai.generation.request dw.consistency.check.request → routing_key: consistency.check.request 【验证命令】docker-compose up rabbitmq → 访问 http://localhost:15672 管理界面 【预期结果】RabbitMQ启动成功，Exchange和Queue创建成功，消息发布消费正常 | M13: RabbitMQ启动成功，管理界面可访问，消息发布消费正常
A14: MVP-SRV-006 | B14: 搭建Milvus向量数据库 | C14: 基础设施 | D14: 服务端基础 | E14: P0 | F14: AI工程师 | G14: 1 | H14: 2026-W15 | I14: 2026-W15 | K14: 未开始 | L14: 【目标】搭建Milvus向量数据库，用于RAG语义检索 【技术选型】Milvus 2.4, pymilvus (Python) 【配置文件路径】docker-compose.yml, app/services/vector_store.py 【具体步骤】 1. docker-compose.yml添加Milvus 2.4服务： - image: milvusdb/milvus:v2.4.0 - ports: 19530:19530 (gRPC), 9091:9091 (metrics) - environment: ETCD_ENDPOINTS=etcd:2379 - 依赖：etcd + minio 2. Python集成pymilvus： - app/services/vector_store.py → VectorStore类 3. 创建Collection（dw_chapter_segments）： - id: INT64 (PK) - work_id: INT64 - chapter_id: INT64 - segment_index: INT64 - content: VARCHAR(8192) - embedding: FLOAT_VECTOR(1536) # text-embedding-3-large维度 - Index: IVF_FLAT, nlist=1024 4. 创建Collection（dw_bible_entities）： - id: INT64 (PK) - work_id: INT64 - entry_id: INT64 - entry_type: VARCHAR(32) - name: VARCHAR(256) - description: VARCHAR(4096) - embedding: FLOAT_VECTOR(1536) - Index: IVF_FLAT, nlist=512 5. 编写向量CRUD工具函数： - insert_vectors(collection, data) → ids - search_vectors(collection, vector, top_k, filter) → results - delete_vectors(collection, ids) 6. 验证插入和检索 【配置内容】 # Collection Schema dw_chapter_segments: { id, work_id, chapter_id, segment_index, content, embedding(1536) } dw_bible_entities: { id, work_id, entry_id, entry_type, name, description, embedding(1536) } 【验证命令】python -c "from pymilvus import connections; connections.connect(); print('OK')" 【预期结果】Milvus启动成功，两个Collection创建成功，向量插入和检索正常 | M14: Milvus启动成功，两个Collection创建，向量插入和语义检索正常
A15: MVP-SRV-007 | B15: 搭建Elasticsearch | C15: 基础设施 | D15: 服务端基础 | E15: P1 | F15: 后端 | G15: 1 | H15: 2026-W15 | I15: 2026-W15 | K15: 未开始 | L15: 【目标】搭建Elasticsearch全文搜索引擎，用于知识库和章节内容搜索 【技术选型】Elasticsearch 8.x, olivere/elastic (Go), elasticsearch-py (Python) 【配置文件路径】docker-compose.yml, pkg/search/es.go, app/services/search.py 【具体步骤】 1. docker-compose.yml添加ES 8.x服务： - image: elasticsearch:8.12.0 - ports: 9200:9200 (HTTP), 9300:9300 (Transport) - environment: discovery.type=single-node, xpack.security.enabled=false, ES_JAVA_OPTS=-Xms512m -Xmx512m - volumes: esdata:/usr/share/elasticsearch/data 2. Go集成olivere/elastic： - pkg/search/es.go → NewESClient(url) → Index/Search/Delete 3. Python集成elasticsearch-py： - app/services/search.py → get_es_client() → index/search 4. 创建索引模板： - dw_chapters: { work_id, chapter_id, title, content, chapter_number, updated_at } → content字段使用ik_max_word分词器 - dw_bible: { work_id, entry_id, entry_type, name, description, tags } → name和description使用ik_max_word分词器 5. 验证索引和搜索 【配置内容】 # dw_chapters索引映射 { "mappings": { "properties": { "work_id": { "type": "long" }, "content": { "type": "text", "analyzer": "ik_max_word" } } } } 【验证命令】curl http://localhost:9200/_cluster/health?pretty 【预期结果】ES启动成功，索引创建成功，中文分词和搜索正常 | M15: Elasticsearch启动成功，索引创建成功，中文分词和全文搜索正常
A16: MVP-SRV-008 | B16: 搭建Kong API网关 | C16: 基础设施 | D16: 服务端基础 | E16: P1 | F16: 后端 | G16: 2 | H16: 2026-W15 | I16: 2026-W15 | J16: MVP-SRV-001 | K16: 未开始 | L16: 【目标】搭建Kong API网关，统一管理所有微服务API路由 【技术选型】Kong 3.6, PostgreSQL (Kong数据存储) 【配置文件路径】docker-compose.yml, kong/ 【具体步骤】 1. docker-compose.yml添加Kong服务： - image: kong:3.6 - ports: 8000:8000 (Proxy), 8443:8443 (Proxy SSL), 8001:8001 (Admin API) - environment: KONG_DATABASE=postgres, KONG_PG_HOST=kong-db - 依赖：kong-db (PostgreSQL) 2. 配置Service和Route： - Service: user-service → upstream: http://user-service:8001 Route: /api/v1/auth/*, /api/v1/users/* - Service: work-service → upstream: http://work-service:8002 Route: /api/v1/works/* - Service: chapter-service → upstream: http://chapter-service:8003 Route: /api/v1/chapters/* - Service: branch-service → upstream: http://branch-service:8004 Route: /api/v1/branches/* - Service: bible-service → upstream: http://bible-service:8005 Route: /api/v1/bible/* - Service: ai-service → upstream: http://ai-service:8006 Route: /api/v1/ai/* 3. 配置JWT认证Plugin： - 全局JWT Plugin - 配置issuer和secret 4. 配置限流Plugin： - rate-limiting: 100 req/min per consumer 5. 配置CORS： - 允许Origin: vscode-webview, localhost:3000 - 允许Methods: GET, POST, PUT, DELETE 6. 验证API路由和认证 【配置内容】 # Kong配置（通过Admin API或declarative config） services: - name: user-service, url: http://user-service:8001 - name: ai-service, url: http://ai-service:8006 routes: - name: auth-route, service: user-service, paths: ["/api/v1/auth"] - name: ai-route, service: ai-service, paths: ["/api/v1/ai"] plugins: - name: jwt, config: { claims_to_verify: ["exp"] } - name: rate-limiting, config: { minute: 100, policy: "local" } - name: cors, config: { origins: ["*"], methods: ["GET","POST","PUT","DELETE"] } 【验证命令】curl -I http://localhost:8000/api/v1/auth/health 【预期结果】Kong启动成功，API路由正确转发，JWT认证生效，限流生效 | M16: Kong启动成功，所有微服务API路由正确，JWT认证和限流生效
A17: MVP-SRV-009 | B17: 配置Docker Compose开发环境 | C17: 基础设施 | D17: 服务端基础 | E17: P0 | F17: 全栈 | G17: 1 | H17: 2026-W15 | I17: 2026-W15 | J17: MVP-SRV-003,MVP-SRV-004,MVP-SRV-005 | K17: 未开始 | L17: 【目标】整合所有服务到Docker Compose开发环境，实现一键启动 【技术选型】Docker Compose v2 【配置文件路径】docker-compose.dev.yml, .env.example, Makefile 【具体步骤】 1. 创建docker-compose.dev.yml，整合所有服务： - postgres (PostgreSQL 16) - redis (Redis 7) - rabbitmq (RabbitMQ 3.13 + management) - milvus (Milvus 2.4 + etcd + minio) - elasticsearch (Elasticsearch 8.x) - kong (Kong 3.6 + kong-db) - user-service (Go, build from Dockerfile) - ai-service (Python, build from Dockerfile) 2. 配置网络： - dw-network: 所有服务共用 3. 配置卷： - pgdata, redisdata, esdata, milvus-data 4. 配置环境变量.env.example： - DATABASE_URL=postgres://dw:dw_secret@localhost:5432/dreamweaver - REDIS_URL=redis://localhost:6379 - RABBITMQ_URL=amqp://dw:dw_secret@localhost:5672 - MILVUS_HOST=localhost, MILVUS_PORT=19530 - ELASTICSEARCH_URL=http://localhost:9200 - ANTHROPIC_API_KEY=sk-ant-xxx - DEEPSEEK_API_KEY=sk-xxx - JWT_SECRET=your-jwt-secret-change-in-production 5. 配置健康检查： - 每个服务配置healthcheck 6. 编写Makefile快捷命令： - make dev: docker-compose -f docker-compose.dev.yml up - make test: 运行所有测试 - make migrate: 执行数据库迁移 - make down: 停止所有服务 - make logs: 查看日志 7. 验证一键启动 【配置内容】 # Makefile dev: docker-compose -f docker-compose.dev.yml up --build test: cd server && go test ./... && cd ../ai-service && pytest migrate: migrate -path migrations -database "$(DATABASE_URL)" up down: docker-compose -f docker-compose.dev.yml down logs: docker-compose -f docker-compose.dev.yml logs -f 【验证命令】cp .env.example .env && make dev 【预期结果】docker-compose up一键启动所有服务，所有健康检查通过 | M17: Docker Compose一键启动所有服务，健康检查全部通过，Makefile命令可用
A18: MVP-SRV-010 | B18: 配置Kubernetes部署清单 | C18: 基础设施 | D18: 服务端基础 | E18: P2 | F18: 后端 | G18: 2 | H18: 2026-W15 | I18: 2026-W15 | J18: MVP-SRV-009 | K18: 未开始 | L18: 【目标】创建Kubernetes部署清单，用于生产环境部署 【技术选型】Kubernetes 1.29+, Helm (可选) 【配置文件路径】k8s/ 【具体步骤】 1. 创建k8s/namespace.yaml： - name: dreamweaver 2. 创建各服务的Deployment+Service+HPA YAML： - k8s/user-service/deployment.yaml, service.yaml, hpa.yaml - k8s/ai-service/deployment.yaml, service.yaml, hpa.yaml - k8s/work-service/deployment.yaml, service.yaml, hpa.yaml - k8s/chapter-service/deployment.yaml, service.yaml, hpa.yaml - k8s/branch-service/deployment.yaml, service.yaml, hpa.yaml - k8s/bible-service/deployment.yaml, service.yaml, hpa.yaml 3. 每个Deployment配置： - replicas: 2 - resources: requests { cpu: 100m, memory: 128Mi }, limits { cpu: 500m, memory: 512Mi } - livenessProbe: /health - readinessProbe: /health - envFrom: ConfigMap + Secret 4. 创建ConfigMap和Secret： - k8s/configmap.yaml: 非敏感配置 - k8s/secret.yaml: 敏感配置（API Keys, JWT Secret） 5. 创建Ingress： - k8s/ingress.yaml: 域名路由配置 - TLS配置 6. 编写Helm Chart（可选）： - k8s/helm/Chart.yaml, values.yaml, templates/ 7. 验证kubectl apply成功 【配置内容】 # Deployment示例 apiVersion: apps/v1 kind: Deployment metadata: { name: user-service, namespace: dreamweaver } spec: replicas: 2 template: spec: containers: - name: user-service image: dreamweaver/user-service:latest ports: [{ containerPort: 8001 }] resources: { requests: { cpu: 100m, memory: 128Mi }, limits: { cpu: 500m, memory: 512Mi } } livenessProbe: { httpGet: { path: /health, port: 8001 } } 【验证命令】kubectl apply -f k8s/ && kubectl get pods -n dreamweaver 【预期结果】所有Pod正常运行，Service可访问，HPA自动扩缩容 | M18: K8s清单创建完成，kubectl apply成功，所有Pod正常运行
A19: MVP-AUTH-001 | B19: 用户注册API - 测试 | C19: Red测试 | D19: 用户系统 | E19: P0 | F19: 后端 | G19: 1 | H19: 2026-W14 | I19: 2026-W14 | J19: MVP-SRV-003 | K19: 未开始 | L19: 【目标】编写用户注册API的完整单元测试和集成测试 【测试框架】pytest + httpx 【测试文件路径】ai-service/tests/auth/test_register.py 【测试用例清单】 1. test_register_success：正常注册（邮箱+密码+昵称）→ 期望返回201 + JWT Token + 用户信息 - 请求：POST /api/v1/auth/register {"email":"test@example.com","password":"Test@12345","nickname":"测试用户"} - 断言：status_code==201, response["access_token"]存在, response["user"]["email"]=="test@example.com" 2. test_register_duplicate_email：重复邮箱注册 → 期望返回409 Conflict - 先注册一个用户，再用相同邮箱注册 - 断言：status_code==409, response["detail"]=="邮箱已注册" 3. test_register_weak_password：弱密码注册 → 期望返回422 - 密码不足8位 → 断言：status_code==422 - 密码无大写字母 → 断言：status_code==422 - 密码无特殊字符 → 断言：status_code==422 4. test_register_invalid_email：无效邮箱格式 → 期望返回422 - 请求：{"email":"invalid","password":"Test@12345","nickname":"测试"} - 断言：status_code==422 5. test_register_empty_fields：空字段 → 期望返回422 - 缺少email/password/nickname各测试一次 6. test_register_password_hashed：验证密码已哈希存储 - 注册后查询数据库，确认password_hash不是明文 - 断言：password_hash != "Test@12345", password_hash.startswith("$2b$") 7. test_register_token_structure：验证JWT Token结构 - 解码access_token，验证payload包含user_id, exp, iat - 验证access_token过期时间为24h - 验证refresh_token过期时间为7d 【Mock依赖】 - Mock PostgreSQL数据库（使用pytest fixture创建测试数据库） - Mock邮件发送服务（注册确认邮件） 【断言要点】 - 状态码正确（201/409/422） - JWT Token格式正确（三段式base64） - 密码使用bcrypt哈希（$2b$开头） - 用户信息返回正确（email, nickname, id） - 错误信息不泄露敏感信息 【运行命令】cd ai-service && pytest tests/auth/test_register.py -v 【预期结果】所有7个测试用例通过 | M19: 7个测试用例全部通过，覆盖正常注册、重复邮箱、弱密码、无效邮箱、空字段、密码哈希、Token结构
A20: MVP-AUTH-002 | B20: 用户注册API - 实现 | C20: Green实现 | D20: 用户系统 | E20: P0 | F20: 后端 | G20: 2 | H20: 2026-W14 | I20: 2026-W14 | J20: MVP-AUTH-001 | K20: 未开始 | L20: 【目标】实现用户注册API，使MVP-AUTH-001中所有测试通过 【源文件路径】ai-service/app/api/routes/auth.py, ai-service/app/services/auth_service.py 【API端点】POST /api/v1/auth/register 【数据模型】 - 请求体：RegisterRequest { email: EmailStr, password: str, nickname: str } - 响应体：RegisterResponse { access_token: str, refresh_token: str, token_type: str, user: UserInfo } - 数据库表：users { id, email, password_hash, nickname, avatar_url, created_at, updated_at } 【实现步骤】 1. 创建Pydantic模型（app/models/schemas.py）： - RegisterRequest: email(EmailStr), password(min_length=8, regex), nickname(min_length=1, max_length=32) - UserInfo: id, email, nickname, avatar_url, created_at - TokenResponse: access_token, refresh_token, token_type="bearer" 2. 实现密码验证逻辑： - 至少8位字符 - 包含大写字母、小写字母、数字、特殊字符 - 正则：^(?=.*[a-z])(?=.*[A-Z])(?=.*\d)(?=.*[@$!%*?&])[A-Za-z\d@$!%*?&]{8,}$ 3. 实现auth_service.py： - async register_user(db, email, password, nickname) → User - bcrypt.hashpw(password, bcrypt.gensalt(rounds=12)) - INSERT INTO users (email, password_hash, nickname) VALUES (...) - 检查邮箱唯一性（UNIQUE约束 + 显式查询） 4. 实现JWT生成： - generate_access_token(user_id) → JWT(exp=24h) - generate_refresh_token(user_id) → JWT(exp=7d) - 使用PyJWT库，HS256算法 5. 实现路由（app/api/routes/auth.py）： - @router.post("/register", status_code=201, response_model=TokenResponse) - 错误处理：409邮箱已存在, 422参数验证失败 6. 注册路由到FastAPI app 【关键代码结构】 - 入口函数签名：async def register(request: RegisterRequest, db: AsyncSession) → TokenResponse - 核心逻辑：验证参数 → 检查邮箱唯一 → 哈希密码 → 插入用户 → 生成Token → 返回 - 错误处理：HTTPException(409, "邮箱已注册") / HTTPException(422, detail=validation_errors) 【依赖注入】 - 数据库Session（通过FastAPI Depends） - JWT_SECRET配置（环境变量） 【运行命令】pytest tests/auth/test_register.py -v（验证所有测试通过） 【预期结果】所有7个测试用例通过 | M20: 用户注册API实现完成，所有测试通过，密码bcrypt哈希，JWT Token正确生成
A21: MVP-AUTH-003 | B21: 用户注册API - 验收 | C21: Acceptance验收 | D21: 用户系统 | E21: P0 | F21: 后端 | G21: 1 | H21: 2026-W14 | I21: 2026-W14 | J21: MVP-AUTH-002 | K21: 未开始 | L21: 【目标】用户注册API的端到端验收测试 【测试范围】从HTTP请求到数据库写入的完整链路 【测试场景】 1. 正常流程：用户提交注册 → 系统返回Token → 验证Token可用 → 验证数据库有记录 - POST /api/v1/auth/register → 201 → 解码Token → 查询数据库确认用户存在 2. 异常流程：重复邮箱注册 → 系统返回409 → 验证错误信息不泄露已有用户信息 - 注册两次相同邮箱 → 第二次返回409 → 错误信息为"邮箱已注册" 3. 边界流程：密码刚好8位+满足所有规则 → 注册成功 - 密码"Abc123!@" → 201成功 4. 安全流程：SQL注入测试 → 注册邮箱包含SQL注入字符串 → 系统正确处理 - email: "test'; DROP TABLE users;--@example.com" → 422（邮箱格式无效） 5. 性能流程：注册响应时间 ≤ 200ms - 使用time测量API响应时间 【测试工具】httpx.AsyncClient + pytest-asyncio 【验收检查项】 □ 功能正确性：正常注册返回201+Token+用户信息 □ 错误处理：重复邮箱409，弱密码422，无效邮箱422 □ 安全：密码bcrypt哈希存储，JWT签名正确，错误信息不泄露敏感数据 □ 性能：注册API响应时间 ≤ 200ms（P95） □ 数据完整性：数据库记录与返回信息一致 【代码审查要点】 □ 代码风格符合ruff规则（ruff check通过） □ 无硬编码的密钥/URL（JWT_SECRET从环境变量读取） □ 有适当的日志记录（注册成功/失败日志） □ 有适当的错误处理（所有异常路径有处理） □ SQL使用参数化查询（防SQL注入） □ 密码哈希使用bcrypt rounds=12 【运行命令】pytest tests/auth/test_register.py -v --tb=short 【预期结果】所有验收项通过，代码审查无问题 | M21: 端到端验收通过，安全测试通过，性能≤200ms，代码审查无问题
A22: MVP-AUTH-004 | B22: 用户登录API - 测试 | C22: Red测试 | D22: 用户系统 | E22: P0 | F22: 后端 | G22: 1 | H22: 2026-W14 | I22: 2026-W14 | J22: MVP-AUTH-003 | K22: 未开始 | L22: 【目标】编写用户登录API的完整测试 【测试框架】pytest + httpx 【测试文件路径】ai-service/tests/auth/test_login.py 【测试用例清单】 1. test_login_success：正常登录 → 期望返回200 + JWT Token - 先注册用户，再POST /api/v1/auth/login {"email":"test@example.com","password":"Test@12345"} - 断言：status_code==200, access_token存在, refresh_token存在 2. test_login_wrong_password：密码错误 → 期望返回401 - 断言：status_code==401, detail=="邮箱或密码错误" 3. test_login_user_not_found：用户不存在 → 期望返回401 - 断言：status_code==401（不区分用户不存在和密码错误，防止枚举攻击） 4. test_login_empty_fields：空字段 → 期望返回422 5. test_login_rate_limit：多次失败后锁定 → 期望返回429 - 连续5次密码错误 → 第6次返回429 "账户已锁定，请15分钟后重试" 6. test_refresh_token：使用refresh_token刷新 → 期望返回新的access_token - POST /api/v1/auth/refresh {"refresh_token": "xxx"} - 断言：status_code==200, 新access_token与旧的不同 7. test_refresh_token_expired：过期refresh_token → 期望返回401 【Mock依赖】Mock PostgreSQL, Mock Redis（失败计数） 【断言要点】状态码正确，Token结构正确，失败计数正确，锁定机制生效 【运行命令】pytest tests/auth/test_login.py -v | M22: 7个测试用例通过，覆盖正常登录、密码错误、用户不存在、锁定、Token刷新
A23: MVP-AUTH-005 | B23: 用户登录API - 实现 | C23: Green实现 | D23: 用户系统 | E23: P0 | F23: 后端 | G23: 2 | H23: 2026-W14 | I23: 2026-W14 | J23: MVP-AUTH-004 | K23: 未开始 | L23: 【目标】实现用户登录API和Token刷新API 【源文件路径】ai-service/app/api/routes/auth.py, ai-service/app/services/auth_service.py 【API端点】POST /api/v1/auth/login, POST /api/v1/auth/refresh 【数据模型】 - LoginRequest: { email: EmailStr, password: str } - RefreshRequest: { refresh_token: str } 【实现步骤】 1. 实现login逻辑： - 查询用户（SELECT * FROM users WHERE email = ?） - bcrypt.checkpw(password, stored_hash) - Redis记录失败次数（key: login_fail:{email}, TTL: 15min） - 失败≥5次 → 返回429 - 成功 → 清除失败计数 → 生成JWT → 返回Token 2. 实现refresh逻辑： - 解码refresh_token → 验证签名和过期时间 - 查询用户是否存在 - 生成新access_token → 返回 3. 错误处理： - 401: 邮箱或密码错误（统一错误信息，不区分用户不存在和密码错误） - 429: 账户锁定 - 401: refresh_token无效或过期 【关键代码结构】 async def login(request: LoginRequest, db: AsyncSession, redis: Redis) → TokenResponse async def refresh_token(request: RefreshRequest, db: AsyncSession) → TokenResponse 【运行命令】pytest tests/auth/test_login.py -v | M23: 登录API实现完成，失败锁定、Token刷新功能正常，所有测试通过
A24: MVP-AUTH-006 | B24: 用户登录API - 验收 | C24: Acceptance验收 | D24: 用户系统 | E24: P0 | F24: 后端 | G24: 1 | H24: 2026-W14 | I24: 2026-W14 | J24: MVP-AUTH-005 | K24: 未开始 | L24: 【目标】用户登录API端到端验收 【测试范围】完整登录→Token刷新→安全测试链路 【测试场景】 1. 正常流程：注册→登录→使用Token访问受保护API→刷新Token→使用新Token访问 2. 异常流程：密码错误5次→锁定→等待15分钟→解锁 3. 安全测试：SQL注入、XSS（邮箱字段）、Token伪造 4. 性能测试：登录响应≤200ms 【测试工具】httpx.AsyncClient + pytest-asyncio 【验收检查项】 □ 功能正确性：登录返回Token，Token可用于认证 □ 安全：密码错误不区分用户不存在，失败锁定生效，Token签名正确 □ 性能：登录≤200ms，Token刷新≤100ms □ 代码审查：无硬编码密钥，参数化查询，适当日志 【运行命令】pytest tests/auth/test_login.py -v | M24: 登录验收通过，安全测试通过，性能达标，代码审查无问题
A25: MVP-AUTH-007 | B25: OAuth第三方登录 - 测试 | C25: Red测试 | D25: 用户系统 | E25: P1 | F25: 后端 | G25: 1 | H25: 2026-W14 | I25: 2026-W14 | J25: MVP-AUTH-003 | K25: 未开始 | L25: 【目标】编写OAuth第三方登录测试 【测试框架】pytest + httpx + respx（Mock HTTP） 【测试文件路径】ai-service/tests/auth/test_oauth.py 【测试用例清单】 1. test_wechat_oauth_callback：微信OAuth回调处理 - Mock微信API返回access_token + userinfo - 断言：返回JWT Token，新用户创建成功 2. test_google_oauth_callback：Google OAuth回调 - Mock Google API返回userinfo - 断言：返回JWT Token 3. test_oauth_new_user_auto_create：新用户自动创建 - 首次OAuth登录 → 自动创建用户记录 - 断言：数据库有新用户，nickname从OAuth provider获取 4. test_oauth_existing_user_login：已有用户直接登录 - 已绑定的OAuth用户再次登录 → 直接返回Token - 断言：不创建重复用户 5. test_oauth_invalid_code：无效授权码 → 期望返回401 6. test_oauth_provider_not_supported：不支持的Provider → 期望返回400 【Mock依赖】Mock微信API、GoogleAPI（使用respx库） 【断言要点】Token返回正确，用户创建/查找正确，错误处理正确 【运行命令】pytest tests/auth/test_oauth.py -v | M25: 6个OAuth测试用例通过，覆盖微信/Google登录、新用户创建、已有用户登录
A26: MVP-AUTH-008 | B26: OAuth第三方登录 - 实现 | C26: Green实现 | D26: 用户系统 | E26: P1 | F26: 后端 | G26: 2 | H26: 2026-W14 | I26: 2026-W14 | J26: MVP-AUTH-007 | K26: 未开始 | L26: 【目标】实现微信和Google OAuth第三方登录 【源文件路径】ai-service/app/api/routes/auth.py, ai-service/app/services/oauth_service.py 【API端点】 - GET /api/v1/auth/oauth/{provider} → 重定向到OAuth Provider - GET /api/v1/auth/oauth/{provider}/callback → 处理回调 【实现步骤】 1. 创建OAuth配置： - WECHAT_APP_ID, WECHAT_APP_SECRET - GOOGLE_CLIENT_ID, GOOGLE_CLIENT_SECRET 2. 实现OAuthService： - get_authorization_url(provider) → str - handle_callback(provider, code) → TokenResponse 3. 微信OAuth流程： - 重定向到 https://open.weixin.qq.com/connect/qrconnect?appid=...&redirect_uri=...&response_type=code - 回调获取code → POST https://api.weixin.qq.com/sns/oauth2/access_token → 获取openid - POST https://api.weixin.qq.com/sns/userinfo → 获取昵称/头像 4. Google OAuth流程： - 重定向到 Google Authorization URL - 回调获取code → POST https://oauth2.googleapis.com/token → 获取access_token - GET https://www.googleapis.com/oauth2/v2/userinfo → 获取邮箱/昵称/头像 5. 用户关联逻辑： - 查找oauth_accounts表（provider_user_id + provider） - 不存在 → 创建新用户 + 创建oauth_account关联 - 已存在 → 直接登录 6. 生成JWT返回 【运行命令】pytest tests/auth/test_oauth.py -v | M26: 微信和Google OAuth登录实现完成，新用户自动创建，已有用户直接登录
A27: MVP-AUTH-009 | B27: OAuth第三方登录 - 验收 | C27: Acceptance验收 | D27: 用户系统 | E27: P1 | F27: 后端 | G27: 1 | H27: 2026-W14 | I27: 2026-W14 | J27: MVP-AUTH-008 | K27: 未开始 | L27: 【目标】OAuth第三方登录端到端验收 【测试范围】完整OAuth流程（重定向→授权→回调→登录） 【测试场景】 1. 微信OAuth完整流程（使用Mock Provider） 2. Google OAuth完整流程（使用Mock Provider） 3. 新用户自动创建验证 4. 已有用户直接登录验证 5. 用户拒绝授权 → 错误处理 【测试工具】httpx + respx 【验收检查项】 □ 功能正确性：OAuth流程完整，Token返回正确 □ 安全：state参数防CSRF，Token安全 □ 错误处理：授权失败/拒绝/超时 【运行命令】pytest tests/auth/test_oauth.py -v | M27: OAuth验收通过，微信/Google流程正常，安全措施到位
... A138: MVP-INT-006 | B138: 部署 | C138: Acceptance验收 | D138: 集成测试 | E138: P0 | F138: 全栈 | G138: 2 | H138: 2026-W25 | I138: 2026-W25 | J138: MVP-INT-004,MVP-SRV-010 | K138: 未开始 | L138: 【目标】生产环境部署 【实现步骤】 1. K8s apply全部manifest 2. 配置Ingress域名（api.dreamweaver-pen.com） 3. 配置TLS证书（Let's Encrypt） 4. 配置Prometheus监控 5. 配置Grafana面板（API延迟/错误率/资源使用） 6. 配置ELK日志（Elasticsearch+Logstash+Kibana） 7. 验证所有服务健康 【验收检查项】 □ 所有Pod Running □ Ingress可访问 □ TLS证书有效 □ Prometheus数据采集 □ Grafana面板可用 □ ELK日志可查 □ 所有API健康检查通过 【运行命令】kubectl get pods -n dreamweaver && kubectl apply -f k8s/ | M138: 生产环境部署成功，所有服务健康

Sheet v1.5-增强
A1: 任务ID | B1: 任务名称 | C1: TDD阶段 | D1: 所属模块 | E1: 优先级 | F1: 负责角色 | G1: 预估工时 | H1: 开始周 | I1: 结束周 | J1: 前置依赖 | K1: 状态 | L1: 详细任务提示词 | M1: 验收标准 | N1: 备注
A2: V15-COL-001 | B2: 投票模式 - 测试 | C2: Red测试 | D2: 多模型协作 | E2: P1 | F2: AI工程师 | G2: 1 | H2: 2026-W26 | I2: 2026-W26 | K2: 未开始 | L2: 【目标】编写多模型投票模式测试 【测试框架】pytest + pytest-asyncio 【测试文件路径】ai-service/tests/services/collaboration/test_voting.py 【测试用例清单】 1. test_voting_single_task：同一任务发给3个模型 → 返回3个结果 2. test_voting_user_select：用户选择最佳结果 → 记录选择 3. test_voting_statistics：投票统计 → 返回各模型得票数 4. test_voting_timeout：某个模型超时 → 跳过该模型 5. test_voting_all_fail：所有模型失败 → 返回错误 【Mock依赖】Mock多个ModelAdapter 【运行命令】pytest ai-service/tests/services/collaboration/test_voting.py -v | M2: 5个投票模式测试用例通过
A3: V15-COL-002 | B3: 投票模式 - 实现 | C3: Green实现 | D3: 多模型协作 | E3: P1 | F3: AI工程师 | G3: 2 | H3: 2026-W26 | I3: 2026-W26 | J3: V15-COL-001 | K3: 未开始 | L3: 【目标】实现多模型投票模式 【源文件路径】ai-service/app/services/collaboration/voting_mode.py 【实现步骤】 1. 创建VotingMode类 2. 实现execute(task, models, options)： - 并发调用N个模型（asyncio.gather） - 每个模型生成结果 - 收集所有结果 - 返回VotingResult(results, statistics) 3. 用户选择API： - POST /api/v1/ai/vote → 记录用户选择 4. 投票统计： - GET /api/v1/ai/vote/stats → 各模型得票率 5. 超时处理：单个模型超时30秒则跳过 【运行命令】pytest ai-service/tests/services/collaboration/test_voting.py -v | M3: 投票模式实现完成，多模型并发和投票统计正常
A4: V15-COL-003 | B4: 投票模式 - 验收 | C4: Acceptance验收 | D4: 多模型协作 | E4: P1 | F4: AI工程师 | G4: 1 | H4: 2026-W26 | I4: 2026-W26 | J4: V15-COL-002 | K4: 未开始 | L4: 【目标】投票模式端到端验收 【测试场景】 1. 同一任务发给3个模型 → 3个结果展示 2. 用户选择最佳 → 记录成功 3. 投票统计 → 数据正确 【验收检查项】 □ 多模型并发正常 □ 结果展示正确 □ 投票记录正确 □ 超时处理正常 【运行命令】pytest ai-service/tests/services/collaboration/test_voting.py -v | M4: 投票模式验收通过
A5: V15-COL-004 | B5: 接力模式 - 测试 | C5: Red测试 | D5: 多模型协作 | E5: P1 | F5: AI工程师 | G5: 1 | H5: 2026-W26 | I5: 2026-W26 | K5: 未开始 | L5: 【目标】编写接力模式测试 【测试文件路径】ai-service/tests/services/collaboration/test_relay.py 【测试用例清单】 1. test_relay_two_steps：模型A→模型B → 结果传递正确 2. test_relay_multi_steps：多步骤链 → 每步结果缓存 3. test_relay_step_failure：某步失败 → 返回已完成的步骤结果 4. test_relay_custom_chain：自定义步骤链 → 按配置执行 【运行命令】pytest ai-service/tests/services/collaboration/test_relay.py -v | M5: 4个接力模式测试用例通过
A6: V15-COL-005 | B6: 接力模式 - 实现 | C6: Green实现 | D6: 多模型协作 | E6: P1 | F6: AI工程师 | G6: 2 | H6: 2026-W26 | I6: 2026-W26 | J6: V15-COL-004 | K6: 未开始 | L6: 【目标】实现多模型接力模式 【源文件路径】ai-service/app/services/collaboration/relay_mode.py 【实现步骤】 1. 创建RelayMode类 2. 实现execute(task, chain)： - chain: [{model_id, prompt_template, options}, ...] - 按顺序执行每一步 - 上一步的输出作为下一步的输入 - 每步结果缓存到Redis 3. 支持任意步骤链（2-5步） 4. 每步可配置不同的prompt模板和参数 5. 失败处理：某步失败返回已完成步骤的结果 【运行命令】pytest ai-service/tests/services/collaboration/test_relay.py -v | M6: 接力模式实现完成，多步骤链正确执行
A7: V15-COL-006 | B7: 接力模式 - 验收 | C7: Acceptance验收 | D7: 多模型协作 | E7: P1 | F7: AI工程师 | G7: 1 | H7: 2026-W26 | I7: 2026-W26 | J7: V15-COL-005 | K7: 未开始 | L7: 【目标】接力模式端到端验收 【测试场景】 1. 模型A完成→结果传给模型B→模型B继续 2. 多步骤链正确执行 3. 每步结果缓存 【验收检查项】 □ 步骤链执行正确 □ 结果传递正确 □ 缓存生效 □ 失败处理正确 【运行命令】pytest ai-service/tests/services/collaboration/test_relay.py -v | M7: 接力模式验收通过
A8: V15-COL-007 | B8: 辩论模式 - 测试 | C8: Red测试 | D8: 多模型协作 | E8: P1 | F8: AI工程师 | G8: 1 | H8: 2026-W27 | I8: 2026-W27 | K8: 未开始 | L8: 【目标】编写辩论模式测试 【测试文件路径】ai-service/tests/services/collaboration/test_debate.py 【测试用例清单】 1. test_debate_two_models：两个模型提出不同方案 → 返回对比 2. test_debate_display：对比视图展示 → 格式正确 3. test_debate_user_verdict：用户裁决 → 记录选择 4. test_debate_followup：继续追问 → 多轮辩论 【运行命令】pytest ai-service/tests/services/collaboration/test_debate.py -v | M8: 4个辩论模式测试用例通过
A9: V15-COL-008 | B9: 辩论模式 - 实现 | C9: Green实现 | D9: 多模型协作 | E9: P1 | F9: AI工程师 | G9: 2 | H9: 2026-W27 | I9: 2026-W27 | J9: V15-COL-007 | K9: 未开始 | L9: 【目标】实现多模型辩论模式 【源文件路径】ai-service/app/services/collaboration/debate_mode.py 【实现步骤】 1. 创建DebateMode类 2. 实现execute(task, model_a, model_b, rounds=2)： - 模型A提出方案A - 模型B提出方案B - 模型A针对方案B提出反驳 - 模型B针对方案A提出反驳 - 返回DebateResult(proposal_a, proposal_b, rebuttals, summary) 3. 用户裁决API 4. 继续追问：基于用户选择的方向继续深入 【运行命令】pytest ai-service/tests/services/collaboration/test_debate.py -v | M9: 辩论模式实现完成
A10: V15-COL-009 | B10: 辩论模式 - 验收 | C10: Acceptance验收 | D10: 多模型协作 | E10: P1 | F10: AI工程师 | G10: 1 | H10: 2026-W27 | I10: 2026-W27 | J10: V15-COL-008 | K10: 未开始 | L10: 【目标】辩论模式端到端验收 【测试场景】 1. 两个模型提出不同方案 → 对比视图 2. 用户裁决 → 记录 3. 继续追问 → 多轮辩论 【验收检查项】 □ 辩论流程正确 □ 对比视图清晰 □ 裁决记录正确 □ 追问功能正常 【运行命令】pytest ai-service/tests/services/collaboration/test_debate.py -v | M10: 辩论模式验收通过
A11: V15-COL-010 | B11: 融合模式 - 测试 | C11: Red测试 | D11: 多模型协作 | E11: P1 | F11: AI工程师 | G11: 1 | H11: 2026-W27 | I11: 2026-W27 | K11: 未开始 | L11: 【目标】编写融合模式测试 【测试文件路径】ai-service/tests/services/collaboration/test_fusion.py 【测试用例清单】 1. test_fusion_multi_output：多模型输出 → AI融合 2. test_fusion_preserve_strengths：保留各模型优点 3. test_fusion_dedup：去重 4. test_fusion_style_unify：风格统一 【运行命令】pytest ai-service/tests/services/collaboration/test_fusion.py -v | M11: 4个融合模式测试用例通过
A12: V15-COL-011 | B12: 融合模式 - 实现 | C12: Green实现 | D12: 多模型协作 | E12: P1 | F12: AI工程师 | G12: 2 | H12: 2026-W27 | I12: 2026-W27 | J12: V15-COL-010 | K12: 未开始 | L12: 【目标】实现多模型融合模式 【源文件路径】ai-service/app/services/collaboration/fusion_mode.py 【实现步骤】 1. 创建FusionMode类 2. 实现execute(task, models)： - 并发调用多个模型 - 收集所有输出 - 使用AI（Claude/GPT）进行融合： - 分析各输出的优点 - 合并为一个最优结果 - 去重重复内容 - 统一写作风格 - 返回FusionResult(fused_text, source_analysis) 【运行命令】pytest ai-service/tests/services/collaboration/test_fusion.py -v | M12: 融合模式实现完成
A13: V15-COL-012 | B13: 融合模式 - 验收 | C13: Acceptance验收 | D13: 多模型协作 | E13: P1 | F13: AI工程师 | G13: 1 | H13: 2026-W27 | I13: 2026-W27 | J13: V15-COL-011 | K13: 未开始 | L13: 【目标】融合模式端到端验收 【测试场景】 1. 多模型输出 → AI融合 → 保留优点 2. 去重 → 无重复内容 3. 风格统一 → 风格一致 【验收检查项】 □ 融合结果质量高 □ 保留各模型优点 □ 去重正确 □ 风格统一 【运行命令】pytest ai-service/tests/services/collaboration/test_fusion.py -v | M13: 融合模式验收通过
A14: V15-COL-013 | B14: 评审模式 - 测试 | C14: Red测试 | D14: 多模型协作 | E14: P1 | F14: AI工程师 | G14: 1 | H14: 2026-W27 | I14: 2026-W27 | K14: 未开始 | L14: 【目标】编写评审模式测试 【测试文件路径】ai-service/tests/services/collaboration/test_review.py 【测试用例清单】 1. test_review_creation：模型A创作 → 返回文本 2. test_review_evaluation：模型B/C评审 → 返回评分和建议 3. test_review_report：评审报告 → 格式正确 【运行命令】pytest ai-service/tests/services/collaboration/test_review.py -v | M14: 3个评审模式测试用例通过
A15: V15-COL-014 | B15: 评审模式 - 实现 | C15: Green实现 | D15: 多模型协作 | E15: P1 | F15: AI工程师 | G15: 2 | H15: 2026-W27 | I15: 2026-W27 | J15: V15-COL-013 | K15: 未开始 | L15: 【目标】实现多模型评审模式 【源文件路径】ai-service/app/services/collaboration/review_mode.py 【实现步骤】 1. 创建ReviewMode类 2. 实现execute(task, creator_model, reviewer_models)： - creator_model创作文本 - reviewer_models分别评审 - 评审维度：情节合理性/人物一致性/文笔质量/创意性 - 每维度1-10分 - 返回ReviewResult(text, reviews, average_score, suggestions) 3. 评审报告生成 【运行命令】pytest ai-service/tests/services/collaboration/test_review.py -v | M15: 评审模式实现完成
A16: V15-COL-015 | B16: 评审模式 - 验收 | C16: Acceptance验收 | D16: 多模型协作 | E16: P1 | F16: AI工程师 | G16: 1 | H16: 2026-W27 | I16: 2026-W27 | J16: V15-COL-014 | K16: 未开始 | L16: 【目标】评审模式端到端验收 【测试场景】 1. 模型A创作 → 模型B/C评审 → 评分和建议 2. 评审报告展示 【验收检查项】 □ 创作质量合理 □ 评审维度全面 □ 评分合理 □ 建议具体有用 【运行命令】pytest ai-service/tests/services/collaboration/test_review.py -v | M16: 评审模式验收通过
A17: V15-MRG-001 | B17: 段落级Diff - 测试 | C17: Red测试 | D17: 分支合并 | E17: P1 | F17: 后端 | G17: 1 | H17: 2026-W28 | I17: 2026-W28 | J17: MVP-BRN-009 | K17: 未开始 | L17: 【目标】编写段落级Diff算法测试 【测试框架】pytest 【测试文件路径】server/service/branch-service/tests/test_diff.py 【测试用例清单】 1. test_three_way_merge：三方合并算法 → 正确合并 2. test_find_common_ancestor：找到共同祖先 → 正确 3. test_detect_conflicts：标记冲突区域 → 正确 4. test_no_conflict_merge：无冲突合并 → 直接合并 5. test_complex_conflict：复杂冲突 → 正确标记 【运行命令】pytest server/service/branch-service/tests/test_diff.py -v | M17: 5个Diff测试用例通过
A18: V15-MRG-002 | B18: 段落级Diff - 实现 | C18: Green实现 | D18: 分支合并 | E18: P1 | F18: 后端 | G18: 3 | H18: 2026-W28 | I18: 2026-W28 | J18: V15-MRG-001 | K18: 未开始 | L18: 【目标】实现段落级三方合并算法 【源文件路径】server/service/branch-service/internal/diff/ 【实现步骤】 1. 实现三方合并（Three-way Merge）： - 输入：base_text, branch_a_text, branch_b_text - 按段落切分（双换行符分隔） - 使用LCS（最长公共子序列）算法比较差异 - 找到共同祖先版本 - 对比分叉点后的差异 - 标记冲突区域 2. 冲突标记格式： <<<<<<< BRANCH_A 分支A的内容 ======= 分支B的内容 >>>>>>> BRANCH_B 3. 自动合并无冲突的部分 【运行命令】pytest server/service/branch-service/tests/test_diff.py -v | M18: 段落级Diff算法实现完成，三方合并正确
A19: V15-MRG-003 | B19: 段落级Diff - 验收 | C19: Acceptance验收 | D19: 分支合并 | E19: P1 | F19: 后端 | G19: 1 | H19: 2026-W28 | I19: 2026-W28 | J19: V15-MRG-002 | K19: 未开始 | L19: 【目标】段落级Diff验收 【测试场景】 1. 无冲突合并 → 直接合并成功 2. 有冲突合并 → 正确标记冲突区域 3. 复杂冲突 → 多处冲突正确标记 【验收检查项】 □ 三方合并正确 □ 冲突标记准确 □ 无冲突部分自动合并 【运行命令】pytest server/service/branch-service/tests/test_diff.py -v | M19: 段落级Diff验收通过
A20: V15-MRG-004 | B20: AI辅助合并 - 测试 | C20: Red测试 | D20: 分支合并 | E20: P1 | F20: AI工程师 | G20: 1 | H20: 2026-W28 | I20: 2026-W28 | J20: V15-MRG-002 | K20: 未开始 | L20: 【目标】编写AI辅助合并测试 【测试文件路径】ai-service/tests/services/test_merge_assistant.py 【测试用例清单】 1. test_analyze_diff：AI分析两个分支差异 → 返回分析 2. test_suggest_merge：建议最优合并方案 → 返回建议 3. test_resolve_conflict：冲突自动解决建议 → 返回解决建议 4. test_merge_preview：合并预览 → 返回预览文本 【运行命令】pytest ai-service/tests/services/test_merge_assistant.py -v | M20: 4个AI辅助合并测试用例通过
A21: V15-MRG-005 | B21: AI辅助合并 - 实现 | C21: Green实现 | D21: 分支合并 | E21: P1 | F21: AI工程师 | G21: 2 | H21: 2026-W28 | I21: 2026-W28 | J21: V15-MRG-004 | K21: 未开始 | L21: 【目标】实现AI辅助合并服务 【源文件路径】ai-service/app/services/merge_assistant.py 【实现步骤】 1. 创建MergeAssistant类 2. 实现analyze_diff(branch_a_content, branch_b_content)： - 使用AI分析两分支差异 - 识别关键差异点 - 评估每个差异的影响 3. 实现suggest_merge(diff_result)： - AI建议最优合并方案 - 对每个冲突区域给出建议 4. 实现resolve_conflict(conflict)： - AI自动解决冲突 - 保留两分支优点 【运行命令】pytest ai-service/tests/services/test_merge_assistant.py -v | M21: AI辅助合并实现完成
A22: V15-MRG-006 | B22: AI辅助合并 - 验收 | C22: Acceptance验收 | D22: 分支合并 | E22: P1 | F22: AI工程师 | G22: 1 | H22: 2026-W28 | I22: 2026-W28 | J22: V15-MRG-005 | K22: 未开始 | L22: 【目标】AI辅助合并验收 【测试场景】 1. AI分析差异 → 分析准确 2. 建议合并方案 → 方案合理 3. 冲突自动解决 → 解决质量高 【验收检查项】 □ 差异分析准确 □ 合并建议合理 □ 冲突解决质量高 【运行命令】pytest ai-service/tests/services/test_merge_assistant.py -v | M22: AI辅助合并验收通过
A23: V15-MRG-007 | B23: 合并UI - 测试 | C23: Red测试 | D23: 分支合并 | E23: P1 | F23: 前端 | G23: 1 | H23: 2026-W29 | I23: 2026-W29 | J23: V15-MRG-003 | K23: 未开始 | L23: 【目标】编写合并UI测试 【测试文件路径】extensions/dw-branch-manager/__tests__/MergeView.test.ts 【测试用例清单】 1. test_side_by_side_view：并排对比视图渲染 2. test_conflict_highlight：冲突高亮 3. test_conflict_resolution：逐个冲突选择 4. test_merge_preview：合并预览 5. test_undo_support：撤销支持 【运行命令】npx vitest run extensions/dw-branch-manager/__tests__/MergeView.test.ts | M23: 5个合并UI测试用例通过
A24: V15-MRG-008 | B24: 合并UI - 实现 | C24: Green实现 | D24: 分支合并 | E24: P1 | F24: 前端 | G24: 3 | H24: 2026-W29 | I24: 2026-W29 | J24: V15-MRG-007 | K24: 未开始 | L24: 【目标】实现分支合并UI 【源文件路径】extensions/dw-branch-manager/src/webview/MergeView.ts 【实现步骤】 1. 并排对比视图： - 左侧：分支A内容 - 右侧：分支B内容 - 中间：合并结果 2. 冲突高亮： - 冲突区域红色/蓝色高亮 - 非冲突部分绿色高亮（已自动合并） 3. 逐个冲突选择： - 上一个/下一个冲突导航 - 选择A/选择B/保留两者 4. 合并预览： - 实时显示合并结果 - AI建议按钮 5. 撤销支持： - 每次选择可撤销 - Ctrl+Z撤销 【运行命令】npx vitest run extensions/dw-branch-manager/__tests__/MergeView.test.ts | M24: 合并UI实现完成
A25: V15-MRG-009 | B25: 合并UI - 验收 | C25: Acceptance验收 | D25: 分支合并 | E25: P1 | F25: 前端 | G25: 1 | H25: 2026-W29 | I25: 2026-W29 | J25: V15-MRG-008 | K25: 未开始 | L25: 【目标】合并UI端到端验收 【测试场景】 1. 并排对比视图 → 显示正确 2. 冲突高亮 → 颜色正确 3. 逐个冲突选择 → 导航和选择正常 4. 合并预览 → 实时更新 5. 撤销 → Ctrl+Z正常 【验收检查项】 □ 并排对比正确 □ 冲突高亮清晰 □ 选择操作正常 □ 预览实时更新 □ 撤销可用 【运行命令】F5启动Extension Development Host | M25: 合并UI验收通过
A26: V15-DAI-001 | B26: AI文本检测 - 测试 | C26: Red测试 | D26: 去AI味引擎 | E26: P1 | F26: AI工程师 | G26: 1 | H26: 2026-W30 | I26: 2026-W30 | K26: 未开始 | L26: 【目标】编写AI文本检测测试 【测试文件路径】ai-service/tests/services/test_ai_detector.py 【测试用例清单】 1. test_detect_ai_text：检测AI生成文本 → 评分>70 2. test_detect_human_text：检测人类写作 → 评分<30 3. test_detect_common_patterns：识别常见AI句式 → 列出 4. test_detect_overly_neat：识别过度工整结构 → 标记 5. test_score_range：评分范围0-100 → 正确 【运行命令】pytest ai-service/tests/services/test_ai_detector.py -v | M26: 5个AI检测测试用例通过
A27: V15-DAI-002 | B27: AI文本检测 - 实现 | C27: Green实现 | D27: 去AI味引擎 | E27: P1 | F27: AI工程师 | G27: 2 | H27: 2026-W30 | I27: 2026-W30 | J27: V15-DAI-001 | K27: 未开始 | L27: 【目标】实现AI文本检测服务 【源文件路径】ai-service/app/services/ai_detector.py 【实现步骤】 1. 创建AIDetector类 2. 实现detect(text) → AIDetectionResult(score, patterns, suggestions) 3. 检测维度： - 常见AI句式（"值得注意的是"、"总而言之"等） - 过度工整的段落结构 - 缺乏个人风格的用词 - 重复的句式模式 4. 评分算法：综合各维度给出0-100分 5. 返回具体AI味标记位置和建议 【运行命令】pytest ai-service/tests/services/test_ai_detector.py -v | M27: AI文本检测实现完成
A28: V15-DAI-003 | B28: AI文本检测 - 验收 | C28: Acceptance验收 | D28: 去AI味引擎 | E28: P1 | F28: AI工程师 | G28: 1 | H28: 2026-W30 | I28: 2026-W30 | J28: V15-DAI-002 | K28: 未开始 | L28: 【目标】AI文本检测验收 【测试场景】 1. AI生成文本 → 评分>70 2. 人类写作 → 评分<30 3. 混合文本 → 评分合理 【验收检查项】 □ 检测准确率≥85% □ 评分合理 □ 标记位置准确 【运行命令】pytest ai-service/tests/services/test_ai_detector.py -v | M28: AI文本检测验收通过
A29: V15-DAI-004 | B29: 智能去AI味 - 测试 | C29: Red测试 | D29: 去AI味引擎 | E29: P1 | F29: AI工程师 | G29: 1 | H29: 2026-W30 | I29: 2026-W30 | J29: V15-DAI-003 | K29: 未开始 | L29: 【目标】编写智能去AI味测试 【测试文件路径】ai-service/tests/services/test_de_ai.py 【测试用例清单】 1. test_multi_model_rewrite：多模型交叉改写 → 降低检测率 2. test_polish_pipeline：改写→润色→人性化 → 流水线正确 3. test_detection_score_decrease：处理后检测评分降低 【运行命令】pytest ai-service/tests/services/test_de_ai.py -v | M29: 3个去AI味测试用例通过
A30: V15-DAI-005 | B30: 智能去AI味 - 实现 | C30: Green实现 | D30: 去AI味引擎 | E30: P1 | F30: AI工程师 | G30: 3 | H30: 2026-W30 | I30: 2026-W30 | J30: V15-DAI-004 | K30: 未开始 | L30: 【目标】实现智能去AI味服务 【源文件路径】ai-service/app/services/de_ai_service.py 【实现步骤】 1. 创建DeAIService类 2. 实现三阶段流水线： - 阶段1：模型A改写（打破AI句式） - 阶段2：模型B润色（提升文笔） - 阶段3：模型C人性化（注入个人风格） 3. 每阶段使用不同模型（避免单一模型偏见） 4. 处理后重新检测，验证评分降低 5. 如果评分仍>50，可再次处理 【运行命令】pytest ai-service/tests/services/test_de_ai.py -v | M30: 智能去AI味实现完成
A31: V15-DAI-006 | B31: 智能去AI味 - 验收 | C31: Acceptance验收 | D31: 去AI味引擎 | E31: P1 | F31: AI工程师 | G31: 1 | H31: 2026-W30 | I31: 2026-W30 | J31: V15-DAI-005 | K31: 未开始 | L31: 【目标】智能去AI味验收 【测试场景】 1. AI文本 → 去AI味处理 → 检测评分降低 2. 处理后文本质量 → 可读性不下降 3. 多次处理 → 评分持续降低 【验收检查项】 □ 检测评分降低≥30% □ 文本质量不下降 □ 处理时间合理（<30s/千字） 【运行命令】pytest ai-service/tests/services/test_de_ai.py -v | M31: 智能去AI味验收通过
A32: V15-DAI-007 | B32: 个性化风格学习 - 测试 | C32: Red测试 | D32: 去AI味引擎 | E32: P2 | F32: AI工程师 | G32: 1 | H32: 2026-W31 | I32: 2026-W31 | J32: V15-DAI-005 | K32: 未开始 | L32: 【目标】编写个性化风格学习测试 【测试文件路径】ai-service/tests/services/test_style_learner.py 【测试用例清单】 1. test_collect_style_features：收集写作风格特征 2. test_build_style_profile：构建风格Profile 3. test_inject_style：AI生成时注入风格 【运行命令】pytest ai-service/tests/services/test_style_learner.py -v | M32: 3个风格学习测试用例通过
A33: V15-DAI-008 | B33: 个性化风格学习 - 实现 | C33: Green实现 | D33: 去AI味引擎 | E33: P2 | F33: AI工程师 | G33: 3 | H33: 2026-W31 | I33: 2026-W31 | J33: V15-DAI-007 | K33: 未开始 | L33: 【目标】实现个性化风格学习 【源文件路径】ai-service/app/services/style_learner.py 【实现步骤】 1. 创建StyleLearner类 2. 收集用户历史文本 → 分析风格特征： - 常用词汇和表达 - 句式偏好（长短句比例） - 描写风格（细腻/简洁/华丽） - 对话风格 3. 构建风格Profile → 存储到数据库 4. AI生成时注入风格 → 修改system prompt 【运行命令】pytest ai-service/tests/services/test_style_learner.py -v | M33: 个性化风格学习实现完成
A34: V15-DAI-009 | B34: 个性化风格学习 - 验收 | C34: Acceptance验收 | D34: 去AI味引擎 | E34: P2 | F34: AI工程师 | G34: 1 | H34: 2026-W31 | I34: 2026-W31 | J34: V15-DAI-008 | K34: 未开始 | L34: 【目标】个性化风格学习验收 【测试场景】 1. 收集历史文本 → 风格特征提取 2. 构建Profile → 存储正确 3. 注入风格 → AI生成文本风格匹配 【验收检查项】 □ 风格特征提取合理 □ Profile存储正确 □ 风格注入有效 【运行命令】pytest ai-service/tests/services/test_style_learner.py -v | M34: 个性化风格学习验收通过
A35: V15-MDL-001 | B35: Gemini适配器 - 测试 | C35: Red测试 | D35: 模型扩展 | E35: P1 | F35: AI工程师 | G35: 1 | H35: 2026-W32 | I35: 2026-W32 | K35: 未开始 | L35: 【目标】编写Gemini适配器测试 【测试文件路径】ai-service/tests/adapters/test_gemini.py 【测试用例清单】 1. test_generate_success：Mock Gemini API → 返回正确 2. test_stream_success：SSE流正确 3. test_error_handling：错误处理 【运行命令】pytest ai-service/tests/adapters/test_gemini.py -v | M35: 3个Gemini测试用例通过
A36: V15-MDL-002 | B36: Gemini适配器 - 实现 | C36: Green实现 | D36: 模型扩展 | E36: P1 | F36: AI工程师 | G36: 2 | H36: 2026-W32 | I36: 2026-W32 | J36: V15-MDL-001 | K36: 未开始 | L36: 【目标】实现Gemini适配器 【源文件路径】ai-service/app/adapters/gemini_adapter.py 【实现步骤】 1. 继承BaseModelAdapter 2. 使用Google Generative AI SDK（google-generativeai） 3. 模型：gemini-2.0-flash / gemini-2.0-pro 4. 实现generate/stream/count_tokens/health_check 5. 注册到ModelAdapterFactory 【运行命令】pytest ai-service/tests/adapters/test_gemini.py -v | M36: Gemini适配器实现完成
A37: V15-MDL-003 | B37: Gemini适配器 - 验收 | C37: Acceptance验收 | D37: 模型扩展 | E37: P1 | F37: AI工程师 | G37: 1 | H37: 2026-W32 | I37: 2026-W32 | J37: V15-MDL-002 | K37: 未开始 | L37: 【目标】Gemini适配器验收 【验收检查项】 □ API调用正常 □ 流式响应正确 □ 错误处理完善 【运行命令】pytest ai-service/tests/adapters/test_gemini.py -v -m integration | M37: Gemini适配器验收通过
A38: V15-MDL-004 | B38: Llama适配器 - 测试 | C38: Red测试 | D38: 模型扩展 | E38: P2 | F38: AI工程师 | G38: 1 | H38: 2026-W32 | I38: 2026-W32 | K38: 未开始 | L38: 【目标】编写Llama适配器测试（本地部署） 【测试文件路径】ai-service/tests/adapters/test_llama.py 【测试用例清单】 1. test_generate_success：Mock Llama API（OpenAI兼容） 2. test_stream_success：SSE流 3. test_local_deployment：本地部署连接 【运行命令】pytest ai-service/tests/adapters/test_llama.py -v | M38: 3个Llama测试用例通过
A39: V15-MDL-005 | B39: Llama适配器 - 实现 | C39: Green实现 | D39: 模型扩展 | E39: P2 | F39: AI工程师 | G39: 2 | H39: 2026-W32 | I39: 2026-W32 | J39: V15-MDL-004 | K39: 未开始 | L39: 【目标】实现Llama适配器（支持本地部署） 【源文件路径】ai-service/app/adapters/llama_adapter.py 【实现步骤】 1. 使用OpenAI兼容API格式（vLLM/Ollama） 2. base_url可配置（本地或远程） 3. 模型：llama-3-70b / llama-3-8b 4. 实现generate/stream/count_tokens/health_check 5. 注册到ModelAdapterFactory 【运行命令】pytest ai-service/tests/adapters/test_llama.py -v | M39: Llama适配器实现完成
A40: V15-MDL-006 | B40: Llama适配器 - 验收 | C40: Acceptance验收 | D40: 模型扩展 | E40: P2 | F40: AI工程师 | G40: 1 | H40: 2026-W32 | I40: 2026-W32 | J40: V15-MDL-005 | K40: 未开始 | L40: 【目标】Llama适配器验收 【验收检查项】 □ 本地部署连接正常 □ API调用正常 □ 流式响应正确 【运行命令】pytest ai-service/tests/adapters/test_llama.py -v | M40: Llama适配器验收通过
A41: V15-MDL-007 | B41: GLM适配器 - 测试 | C41: Red测试 | D41: 模型扩展 | E41: P2 | F41: AI工程师 | G41: 1 | H41: 2026-W32 | I41: 2026-W32 | K41: 未开始 | L41: 【目标】编写GLM适配器测试 【测试文件路径】ai-service/tests/adapters/test_glm.py 【测试用例清单】 1. test_generate_success：Mock GLM API 2. test_stream_success：SSE流 3. test_chinese_quality：中文生成质量 【运行命令】pytest ai-service/tests/adapters/test_glm.py -v | M41: 3个GLM测试用例通过
A42: V15-MDL-008 | B42: GLM适配器 - 实现 | C42: Green实现 | D42: 模型扩展 | E42: P2 | F42: AI工程师 | G42: 2 | H42: 2026-W32 | I42: 2026-W32 | J42: V15-MDL-007 | K42: 未开始 | L42: 【目标】实现GLM（智谱AI）适配器 【源文件路径】ai-service/app/adapters/glm_adapter.py 【实现步骤】 1. 使用智谱AI OpenAI兼容API 2. base_url = "https://open.bigmodel.cn/api/paas/v4" 3. 模型：glm-4-plus / glm-4 4. 实现generate/stream/count_tokens/health_check 5. 注册到ModelAdapterFactory 【运行命令】pytest ai-service/tests/adapters/test_glm.py -v | M42: GLM适配器实现完成
A43: V15-MDL-009 | B43: GLM适配器 - 验收 | C43: Acceptance验收 | D43: 模型扩展 | E43: P2 | F43: AI工程师 | G43: 1 | H43: 2026-W32 | I43: 2026-W32 | J43: V15-MDL-008 | K43: 未开始 | L43: 【目标】GLM适配器验收 【验收检查项】 □ API调用正常 □ 中文生成质量 □ 流式响应正确 【运行命令】pytest ai-service/tests/adapters/test_glm.py -v | M43: GLM适配器验收通过
A44: V15-RAG-001 | B44: 查询改写+交叉编码器 - 测试 | C44: Red测试 | D44: 高级RAG | E44: P1 | F44: AI工程师 | G44: 1 | H44: 2026-W33 | I44: 2026-W33 | J44: MVP-RAG-006 | K44: 未开始 | L44: 【目标】编写查询改写和交叉编码器测试 【测试文件路径】ai-service/tests/services/test_advanced_rag.py 【测试用例清单】 1. test_query_rewrite：查询改写 → 生成多个查询变体 2. test_cross_encoder_rerank：交叉编码器重排序 → 相关性排序更准确 3. test_combined_retrieval：组合检索 → 效果优于基础RAG 【运行命令】pytest ai-service/tests/services/test_advanced_rag.py -v | M44: 3个高级RAG测试用例通过
A45: V15-RAG-002 | B45: 查询改写+交叉编码器 - 实现 | C45: Green实现 | D45: 高级RAG | E45: P1 | F45: AI工程师 | G45: 3 | H45: 2026-W33 | I45: 2026-W33 | J45: V15-RAG-001 | K45: 未开始 | L45: 【目标】实现查询改写和交叉编码器重排序 【源文件路径】ai-service/app/services/advanced_rag.py 【实现步骤】 1. 查询改写（Query Rewrite）： - 使用AI将用户查询改写为多个变体 - 例如："描写张三的外貌" → ["张三长什么样", "描述张三的相貌特征", "张三的外貌描写"] - 每个变体独立检索 2. 交叉编码器重排序（Cross-Encoder Rerank）： - 使用cohere-rerank或自训练模型 - 对初始检索结果进行精排 - 输入：query + document pair - 输出：相关性分数 3. 组合到RAGService中替换基础检索 【运行命令】pytest ai-service/tests/services/test_advanced_rag.py -v | M45: 查询改写和交叉编码器实现完成
A46: V15-RAG-003 | B46: 查询改写+交叉编码器 - 验收 | C46: Acceptance验收 | D46: 高级RAG | E46: P1 | F46: AI工程师 | G46: 1 | H46: 2026-W33 | I46: 2026-W33 | J46: V15-RAG-002 | K46: 未开始 | L46: 【目标】高级RAG验收 【测试场景】 1. 查询改写 → 多个变体合理 2. 交叉编码器 → 重排序更准确 3. 组合检索 → Top-5准确率提升≥10% 【验收检查项】 □ 查询改写合理 □ 重排序准确 □ 检索效果提升 【运行命令】pytest ai-service/tests/services/test_advanced_rag.py -v | M46: 高级RAG验收通过
A47: V15-RAG-004 | B47: 高级RAG上下文管理 - 测试 | C47: Red测试 | D47: 高级RAG | E47: P1 | F47: AI工程师 | G47: 1 | H47: 2026-W33 | I47: 2026-W33 | J47: V15-RAG-002 | K47: 未开始 | L47: 【目标】编写高级RAG上下文管理测试 【测试文件路径】ai-service/tests/services/test_rag_context.py 【测试用例清单】 1. test_context_compression：上下文压缩 → 保留关键信息 2. test_context_priority：上下文优先级管理 3. test_long_context_handling：长上下文处理（>100K tokens） 【运行命令】pytest ai-service/tests/services/test_rag_context.py -v | M47: 3个上下文管理测试用例通过
A48: V15-RAG-005 | B48: 高级RAG上下文管理 - 实现 | C48: Green实现 | D48: 高级RAG | E48: P1 | F48: AI工程师 | G48: 2 | H48: 2026-W33 | I48: 2026-W33 | J48: V15-RAG-004 | K48: 未开始 | L48: 【目标】实现高级RAG上下文管理 【源文件路径】ai-service/app/services/rag_context_manager.py 【实现步骤】 1. 上下文压缩：使用AI摘要压缩长文本 2. 优先级管理：动态调整各部分上下文权重 3. 长上下文处理：支持>100K tokens的上下文窗口 4. 滑动窗口：对超长作品使用滑动窗口策略 【运行命令】pytest ai-service/tests/services/test_rag_context.py -v | M48: 高级RAG上下文管理实现完成
A49: V15-RAG-006 | B49: 高级RAG上下文管理 - 验收 | C49: Acceptance验收 | D49: 高级RAG | E49: P1 | F49: AI工程师 | G49: 1 | H49: 2026-W33 | I49: 2026-W33 | J49: V15-RAG-005 | K49: 未开始 | L49: 【目标】高级RAG上下文管理验收 【验收检查项】 □ 上下文压缩保留关键信息 □ 优先级管理合理 □ 长上下文处理正常 【运行命令】pytest ai-service/tests/services/test_rag_context.py -v | M49: 高级RAG上下文管理验收通过
A50: V15-FRK-001 | B50: Activity Bar定制 - 测试 | C50: Red测试 | D50: 中度Fork | E50: P1 | F50: 前端 | G50: 1 | H50: 2026-W34 | I50: 2026-W34 | J50: MVP-CLI-005 | K50: 未开始 | L50: 【目标】编写Activity Bar定制测试 【测试文件路径】extensions/dw-core/__tests__/ActivityBar.test.ts 【测试用例清单】 1. test_custom_icons：自定义图标显示正确 2. test_writing_icons：写作场景特有图标 3. test_active_state_style：活跃状态样式 【运行命令】npx vitest run extensions/dw-core/__tests__/ActivityBar.test.ts | M50: 3个Activity Bar测试用例通过
A51: V15-FRK-002 | B51: Activity Bar定制 - 实现 | C51: Green实现 | D51: 中度Fork | E51: P1 | F51: 前端 | G51: 2 | H51: 2026-W34 | I51: 2026-W34 | J51: V15-FRK-001 | K51: 未开始 | L51: 【目标】定制Activity Bar布局和样式 【源文件路径】src/vs/workbench/contrib/activitybar/ 【实现步骤】 1. 修改Activity Bar布局： - 调整图标大小和间距 - 添加写作场景特有图标（大纲/分支/知识库/AI/统计） 2. 自定义图标： - 使用SVG图标替换默认图标 - 添加hover动画效果 3. 修改活跃状态样式： - 自定义高亮颜色 - 添加指示器样式 【运行命令】yarn watch && yarn electron | M51: Activity Bar定制完成
A52: V15-FRK-003 | B52: Activity Bar定制 - 验收 | C52: Acceptance验收 | D52: 中度Fork | E52: P1 | F52: 前端 | G52: 1 | H52: 2026-W34 | I52: 2026-W34 | J52: V15-FRK-002 | K52: 未开始 | L52: 【目标】Activity Bar定制验收 【验收检查项】 □ 自定义图标正确 □ 写作场景图标显示 □ 活跃状态样式正确 □ hover动画流畅 【运行命令】yarn watch && yarn electron | M52: Activity Bar定制验收通过
A53: V15-FRK-004 | B53: Monaco写作配置 - 测试 | C53: Red测试 | D53: 中度Fork | E53: P1 | F53: 前端 | G53: 1 | H53: 2026-W34 | I53: 2026-W34 | K53: 未开始 | L53: 【目标】编写Monaco编辑器写作配置测试 【测试文件路径】extensions/dw-core/__tests__/EditorConfig.test.ts 【测试用例清单】 1. test_default_font：默认字体Noto Serif SC 16px 2. test_line_height：行高1.8 3. test_max_line_width：最大行宽700px 4. test_auto_save_interval：自动保存间隔 【运行命令】npx vitest run extensions/dw-core/__tests__/EditorConfig.test.ts | M53: 4个编辑器配置测试用例通过
A54: V15-FRK-005 | B54: Monaco写作配置 - 实现 | C54: Green实现 | D54: 中度Fork | E54: P1 | F54: 前端 | G54: 2 | H54: 2026-W34 | I54: 2026-W34 | J54: V15-FRK-004 | K54: 未开始 | L54: 【目标】自定义Monaco编辑器写作配置 【源文件路径】extensions/dw-core/src/EditorConfig.ts 【实现步骤】 1. 默认编辑器配置： - 字体：Noto Serif SC, 16px - 行高：1.8 - 最大行宽：700px（居中显示） - 自动保存间隔：30秒 - 禁用自动换行（或软换行） - 隐藏行号（可选） - 隐藏minimap 2. 写作模式： - 专注模式（隐藏侧边栏和面板） - 打字机模式（光标始终居中） - 翻页模式（章节间翻页） 【运行命令】npx vitest run extensions/dw-core/__tests__/EditorConfig.test.ts | M54: Monaco写作配置实现完成
A55: V15-FRK-006 | B55: Monaco写作配置 - 验收 | C55: Acceptance验收 | D55: 中度Fork | E55: P1 | F55: 前端 | G55: 1 | H55: 2026-W34 | I55: 2026-W34 | J55: V15-FRK-005 | K55: 未开始 | L55: 【目标】Monaco写作配置验收 【验收检查项】 □ 字体和行高正确 □ 最大行宽700px居中 □ 自动保存30秒 □ 专注模式可用 □ 打字机模式可用 【运行命令】yarn watch && yarn electron | M55: Monaco写作配置验收通过
A56: V15-FRK-007 | B56: 写作专用Extension API - 测试 | C56: Red测试 | D56: 中度Fork | E56: P1 | F56: 前端 | G56: 1 | H56: 2026-W35 | I56: 2026-W35 | K56: 未开始 | L56: 【目标】编写写作专用Extension API测试 【测试文件路径】extensions/dw-core/__tests__/DreamweaverAPI.test.ts 【测试用例清单】 1. test_getAvailableModels：获取可用模型列表 2. test_continueWriting：续写API 3. test_checkConsistency：一致性检查API 4. test_getBranches：获取分支列表 【运行命令】npx vitest run extensions/dw-core/__tests__/DreamweaverAPI.test.ts | M56: 4个Extension API测试用例通过
A57: V15-FRK-008 | B57: 写作专用Extension API - 实现 | C57: Green实现 | D57: 中度Fork | E57: P1 | F57: 前端 | G57: 3 | H57: 2026-W35 | I57: 2026-W35 | J57: V15-FRK-007 | K57: 未开始 | L57: 【目标】实现写作专用Extension API 【源文件路径】src/vscode.proposed.dreamweaver.d.ts, extensions/dw-core/src/api/ 【实现步骤】 1. 在vscode.proposed.dreamweaver.d.ts中定义API： - vscode.dreamweaver.getAvailableModels(): Promise<ModelInfo[]> - vscode.dreamweaver.continueWriting(options): Promise<string> - vscode.dreamweaver.checkConsistency(workId): Promise<ConsistencyResult> - vscode.dreamweaver.getBranches(workId): Promise<Branch[]> - vscode.dreamweaver.getStoryBible(workId): Promise<BibleEntry[]> 2. 实现ExtHost侧（src/vs/workbench/api/） 3. 实现Main Thread侧（src/vs/workbench/services/） 4. 注册到Extension API 【运行命令】npx vitest run extensions/dw-core/__tests__/DreamweaverAPI.test.ts | M57: 写作专用Extension API实现完成
A58: V15-FRK-009 | B58: 写作专用Extension API - 验收 | C58: Acceptance验收 | D58: 中度Fork | E58: P1 | F58: 前端 | G58: 1 | H58: 2026-W35 | I58: 2026-W35 | J58: V15-FRK-008 | K58: 未开始 | L58: 【目标】写作专用Extension API验收 【测试场景】 1. Extension调用getAvailableModels → 返回模型列表 2. 调用continueWriting → 返回续写结果 3. 调用checkConsistency → 返回检查结果 【验收检查项】 □ API定义正确 □ ExtHost实现正确 □ Main Thread实现正确 □ Extension可正常调用 【运行命令】yarn watch && yarn electron | M58: 写作专用Extension API验收通过

Sheet v2.0-生态
A1: 任务ID | B1: 任务名称 | C1: TDD阶段 | D1: 所属模块 | E1: 优先级 | F1: 负责角色 | G1: 预估工时 | H1: 开始周 | I1: 结束周 | J1: 前置依赖 | K1: 状态 | L1: 详细任务提示词 | M1: 验收标准 | N1: 备注
A2: V20-TPL-001 | B2: 模板CRUD API - 测试 | C2: Red测试 | D2: 模板市场 | E2: P2 | F2: 后端 | G2: 1 | H2: 2026-W36 | I2: 2026-W36 | K2: 未开始 | L2: 【目标】编写模板CRUD API测试 【测试框架】pytest + httpx 【测试文件路径】server/service/template-service/tests/test_template_api.py 【测试用例清单】 1. test_create_template：创建模板 → 201 2. test_get_template：获取模板 → 200 3. test_update_template：更新模板 → 200 4. test_delete_template：删除模板 → 204 5. test_list_templates：模板列表 → 200 + 分页 6. test_template_categories：分类筛选 → 正确过滤 【运行命令】pytest server/service/template-service/tests/test_template_api.py -v | M2: 6个模板API测试用例通过
A3: V20-TPL-002 | B3: 模板CRUD API - 实现 | C3: Green实现 | D3: 模板市场 | E3: P2 | F3: 后端 | G3: 2 | H3: 2026-W36 | I3: 2026-W36 | J3: V20-TPL-001 | K3: 未开始 | L3: 【目标】实现模板CRUD API 【源文件路径】server/service/template-service/ 【API端点】 - POST /templates → 创建模板 - GET /templates → 列表（分页+分类筛选+排序） - GET /templates/:id → 获取详情 - PUT /templates/:id → 更新 - DELETE /templates/:id → 删除 - POST /templates/:id/clone → 克隆模板 【数据模型】 - templates: { id, author_id, name, description, category, genre, structure_json, settings_json, is_public, download_count, rating, created_at, updated_at } 【实现步骤】 1. CRUD操作 2. 分类筛选（玄幻/都市/科幻/言情/历史/悬疑/其他） 3. 排序（热门/最新/评分） 4. 克隆功能 【运行命令】pytest server/service/template-service/tests/test_template_api.py -v | M3: 模板CRUD API实现完成
A4: V20-TPL-003 | B4: 模板CRUD API - 验收 | C4: Acceptance验收 | D4: 模板市场 | E4: P2 | F4: 后端 | G4: 1 | H4: 2026-W36 | I4: 2026-W36 | J4: V20-TPL-002 | K4: 未开始 | L4: 【目标】模板CRUD API验收 【验收检查项】 □ CRUD完整 □ 分类筛选正确 □ 排序正确 □ 克隆功能正常 【运行命令】pytest server/service/template-service/tests/test_template_api.py -v | M4: 模板CRUD API验收通过
A5: V20-TPL-004 | B5: 模板浏览搜索 - 测试 | C5: Red测试 | D5: 模板市场 | E5: P2 | F5: 后端 | G5: 1 | H5: 2026-W36 | I5: 2026-W36 | J5: V20-TPL-002 | K5: 未开始 | L5: 【目标】编写模板搜索测试 【测试文件路径】server/service/template-service/tests/test_template_search.py 【测试用例清单】 1. test_fulltext_search：全文搜索 → 返回匹配 2. test_tag_search：标签搜索 → 正确过滤 3. test_genre_filter：类型筛选 → 正确 4. test_sort_by_rating：按评分排序 → 正确 【运行命令】pytest server/service/template-service/tests/test_template_search.py -v | M5: 4个模板搜索测试用例通过
A6: V20-TPL-005 | B6: 模板浏览搜索 - 实现 | C6: Green实现 | D6: 模板市场 | E6: P2 | F6: 后端 | G6: 2 | H6: 2026-W36 | I6: 2026-W36 | J6: V20-TPL-004 | K6: 未开始 | L6: 【目标】实现模板搜索功能 【源文件路径】server/service/template-service/internal/search.go 【实现步骤】 1. Elasticsearch全文搜索（名称+描述+标签） 2. 标签搜索 3. 类型筛选 4. 多维排序（热门/最新/评分/下载量） 5. 搜索建议（自动补全） 【运行命令】pytest server/service/template-service/tests/test_template_search.py -v | M6: 模板搜索实现完成
A7: V20-TPL-006 | B7: 模板浏览搜索 - 验收 | C7: Acceptance验收 | D7: 模板市场 | E7: P2 | F7: 后端 | G7: 1 | H7: 2026-W36 | I7: 2026-W36 | J7: V20-TPL-005 | K7: 未开始 | L7: 【目标】模板搜索验收 【验收检查项】 □ 全文搜索准确 □ 标签搜索正确 □ 排序正确 □ 搜索建议可用 【运行命令】pytest server/service/template-service/tests/test_template_search.py -v | M7: 模板搜索验收通过
A8: V20-TPL-007 | B8: 模板创建向导 - 测试 | C8: Red测试 | D8: 模板市场 | E8: P2 | F8: 前端 | G8: 1 | H8: 2026-W37 | I8: 2026-W37 | J8: V20-TPL-002 | K8: 未开始 | L8: 【目标】编写模板创建向导测试 【测试文件路径】extensions/dw-template-market/__tests__/TemplateWizard.test.ts 【测试用例清单】 1. test_wizard_steps：向导步骤正确 2. test_template_structure_editor：结构编辑器 3. test_preview：模板预览 【运行命令】npx vitest run extensions/dw-template-market/__tests__/TemplateWizard.test.ts | M8: 3个向导测试用例通过
A9: V20-TPL-008 | B9: 模板创建向导 - 实现 | C9: Green实现 | D9: 模板市场 | E9: P2 | F9: 前端 | G9: 3 | H9: 2026-W37 | I9: 2026-W37 | J9: V20-TPL-007 | K9: 未开始 | L9: 【目标】实现模板创建向导 【源文件路径】extensions/dw-template-market/src/webview/TemplateWizard.ts 【实现步骤】 1. 多步骤向导： - 步骤1：基本信息（名称/描述/分类/标签） - 步骤2：结构定义（卷/章/节大纲） - 步骤3：角色设定模板 - 步骤4：世界观设定模板 - 步骤5：AI配置（推荐模型/写作风格） 2. 可视化结构编辑器（拖拽排序） 3. 实时预览 4. 保存和发布 【运行命令】npx vitest run extensions/dw-template-market/__tests__/TemplateWizard.test.ts | M9: 模板创建向导实现完成
A10: V20-TPL-009 | B10: 模板创建向导 - 验收 | C10: Acceptance验收 | D10: 模板市场 | E10: P2 | F10: 前端 | G10: 1 | H10: 2026-W37 | I10: 2026-W37 | J10: V20-TPL-008 | K10: 未开始 | L10: 【目标】模板创建向导验收 【验收检查项】 □ 向导步骤流畅 □ 结构编辑器可用 □ 预览正确 □ 保存发布正常 【运行命令】F5启动Extension Development Host | M10: 模板创建向导验收通过
A11: V20-TPL-010 | B11: 模板版本管理 - 测试 | C11: Red测试 | D11: 模板市场 | E11: P2 | F11: 后端 | G11: 1 | H11: 2026-W37 | I11: 2026-W37 | J11: V20-TPL-002 | K11: 未开始 | L11: 【目标】编写模板版本管理测试 【测试文件路径】server/service/template-service/tests/test_template_version.py 【测试用例清单】 1. test_create_version：创建版本 → 201 2. test_list_versions：版本列表 → 正确 3. test_rollback：版本回滚 → 正确 【运行命令】pytest server/service/template-service/tests/test_template_version.py -v | M11: 3个版本管理测试用例通过
A12: V20-TPL-011 | B12: 模板版本管理 - 实现 | C12: Green实现 | D12: 模板市场 | E12: P2 | F12: 后端 | G12: 2 | H12: 2026-W37 | I12: 2026-W37 | J12: V20-TPL-010 | K12: 未开始 | L12: 【目标】实现模板版本管理 【源文件路径】server/service/template-service/internal/version.go 【实现步骤】 1. 版本快照：每次更新自动创建版本 2. 版本列表：GET /templates/:id/versions 3. 版本对比：GET /templates/:id/diff/:v1/:v2 4. 版本回滚：POST /templates/:id/rollback/:version 5. 更新日志 【运行命令】pytest server/service/template-service/tests/test_template_version.py -v | M12: 模板版本管理实现完成
A13: V20-TPL-012 | B13: 模板版本管理 - 验收 | C13: Acceptance验收 | D13: 模板市场 | E13: P2 | F13: 后端 | G13: 1 | H13: 2026-W37 | I13: 2026-W37 | J13: V20-TPL-011 | K13: 未开始 | L13: 【目标】模板版本管理验收 【验收检查项】 □ 版本快照正常 □ 版本对比正确 □ 回滚功能正常 【运行命令】pytest server/service/template-service/tests/test_template_version.py -v | M13: 模板版本管理验收通过
A14: V20-ANA-001 | B14: 数据采集服务 - 测试 | C14: Red测试 | D14: 数据统计 | E14: P2 | F14: 后端 | G14: 1 | H14: 2026-W38 | I14: 2026-W38 | K14: 未开始 | L14: 【目标】编写数据采集服务测试 【测试文件路径】server/service/analytics-service/tests/test_collector.py 【测试用例清单】 1. test_collect_word_count：采集字数数据 2. test_collect_ai_usage：采集AI使用数据 3. test_collect_session：采集写作会话数据 4. test_collect_interval：定时采集 【运行命令】pytest server/service/analytics-service/tests/test_collector.py -v | M14: 4个数据采集测试用例通过
A15: V20-ANA-002 | B15: 数据采集服务 - 实现 | C15: Green实现 | D15: 数据统计 | E15: P2 | F15: 后端 | G15: 2 | H15: 2026-W38 | I15: 2026-W38 | J15: V20-ANA-001 | K15: 未开始 | L15: 【目标】实现数据采集服务 【源文件路径】server/service/analytics-service/internal/collector.go 【实现步骤】 1. 采集维度： - 字数统计（日/周/月） - AI使用次数和Token消耗 - 写作会话时长 - 章节完成数 - 模型使用分布 2. 定时采集（每小时） 3. 数据聚合（日/周/月汇总） 4. 存储到PostgreSQL analytics表 【运行命令】pytest server/service/analytics-service/tests/test_collector.py -v | M15: 数据采集服务实现完成
A16: V20-ANA-003 | B16: 数据采集服务 - 验收 | C16: Acceptance验收 | D16: 数据统计 | E16: P2 | F16: 后端 | G16: 1 | H16: 2026-W38 | I16: 2026-W38 | J16: V20-ANA-002 | K16: 未开始 | L16: 【目标】数据采集服务验收 【验收检查项】 □ 采集数据准确 □ 定时采集正常 □ 数据聚合正确 【运行命令】pytest server/service/analytics-service/tests/test_collector.py -v | M16: 数据采集服务验收通过
A17: V20-ANA-004 | B17: 统计分析API - 测试 | C17: Red测试 | D17: 数据统计 | E17: P2 | F17: 后端 | G17: 1 | H17: 2026-W38 | I17: 2026-W38 | J17: V20-ANA-002 | K17: 未开始 | L17: 【目标】编写统计分析API测试 【测试文件路径】server/service/analytics-service/tests/test_stats_api.py 【测试用例清单】 1. test_get_daily_stats：日统计 → 正确 2. test_get_weekly_stats：周统计 → 正确 3. test_get_model_usage：模型使用分布 → 正确 4. test_get_writing_trends：写作趋势 → 正确 【运行命令】pytest server/service/analytics-service/tests/test_stats_api.py -v | M17: 4个统计分析测试用例通过
A18: V20-ANA-005 | B18: 统计分析API - 实现 | C18: Green实现 | D18: 数据统计 | E18: P2 | F18: 后端 | G18: 2 | H18: 2026-W38 | I18: 2026-W38 | J18: V20-ANA-004 | K18: 未开始 | L18: 【目标】实现统计分析API 【源文件路径】server/service/analytics-service/ 【API端点】 - GET /analytics/daily → 日统计 - GET /analytics/weekly → 周统计 - GET /analytics/monthly → 月统计 - GET /analytics/model-usage → 模型使用分布 - GET /analytics/writing-trends → 写作趋势 - GET /analytics/goals → 目标完成度 【实现步骤】 1. SQL聚合查询 2. 时间范围筛选 3. 数据可视化格式 【运行命令】pytest server/service/analytics-service/tests/test_stats_api.py -v | M18: 统计分析API实现完成
A19: V20-ANA-006 | B19: 统计分析API - 验收 | C19: Acceptance验收 | D19: 数据统计 | E19: P2 | F19: 后端 | G19: 1 | H19: 2026-W38 | I19: 2026-W38 | J19: V20-ANA-005 | K19: 未开始 | L19: 【目标】统计分析API验收 【验收检查项】 □ 日/周/月统计正确 □ 模型使用分布正确 □ 写作趋势数据正确 【运行命令】pytest server/service/analytics-service/tests/test_stats_api.py -v | M19: 统计分析API验收通过
A20: V20-ANA-007 | B20: 可视化面板Webview - 测试 | C20: Red测试 | D20: 数据统计 | E20: P2 | F20: 前端 | G20: 1 | H20: 2026-W39 | I20: 2026-W39 | J20: V20-ANA-005 | K20: 未开始 | L20: 【目标】编写可视化面板测试 【测试文件路径】extensions/dw-analytics/__tests__/AnalyticsPanel.test.ts 【测试用例清单】 1. test_render_charts：图表渲染正确 2. test_date_range_selector：日期范围选择 3. test_export_report：导出报告 【运行命令】npx vitest run extensions/dw-analytics/__tests__/AnalyticsPanel.test.ts | M20: 3个可视化面板测试用例通过
A21: V20-ANA-008 | B21: 可视化面板Webview - 实现 | C21: Green实现 | D21: 数据统计 | E21: P2 | F21: 前端 | G21: 3 | H21: 2026-W39 | I21: 2026-W39 | J21: V20-ANA-007 | K21: 未开始 | L21: 【目标】实现数据可视化面板 【源文件路径】extensions/dw-analytics/src/webview/AnalyticsPanel.ts 【实现步骤】 1. 使用Chart.js或ECharts渲染图表 2. 图表类型： - 字数趋势折线图（日/周/月） - AI模型使用饼图 - 写作时段热力图 - 目标完成进度条 3. 日期范围选择器 4. 数据导出（CSV/PNG） 5. 写作目标设置和追踪 【运行命令】npx vitest run extensions/dw-analytics/__tests__/AnalyticsPanel.test.ts | M21: 可视化面板实现完成
A22: V20-ANA-009 | B22: 可视化面板Webview - 验收 | C22: Acceptance验收 | D22: 数据统计 | E22: P2 | F22: 前端 | G22: 1 | H22: 2026-W39 | I22: 2026-W39 | J22: V20-ANA-008 | K22: 未开始 | L22: 【目标】可视化面板验收 【验收检查项】 □ 图表渲染正确 □ 日期选择正常 □ 数据导出可用 □ 目标追踪正常 【运行命令】F5启动Extension Development Host | M22: 可视化面板验收通过
A23: V20-COM-001 | B23: 作品发布API - 测试 | C23: Red测试 | D23: 社区分享 | E23: P2 | F23: 后端 | G23: 1 | H23: 2026-W40 | I23: 2026-W40 | K23: 未开始 | L23: 【目标】编写作品发布API测试 【测试文件路径】server/service/community-service/tests/test_publish_api.py 【测试用例清单】 1. test_publish_work：发布作品 → 201 2. test_unpublish_work：取消发布 → 200 3. test_get_published_works：获取已发布作品列表 → 200 4. test_work_visibility：作品可见性控制 【运行命令】pytest server/service/community-service/tests/test_publish_api.py -v | M23: 4个发布API测试用例通过
A24: V20-COM-002 | B24: 作品发布API - 实现 | C24: Green实现 | D24: 社区分享 | E24: P2 | F24: 后端 | G24: 2 | H24: 2026-W40 | I24: 2026-W40 | J24: V20-COM-001 | K24: 未开始 | L24: 【目标】实现作品发布API 【源文件路径】server/service/community-service/ 【API端点】 - POST /community/works/:id/publish → 发布作品 - POST /community/works/:id/unpublish → 取消发布 - GET /community/works → 社区作品列表 - GET /community/works/:id → 作品详情 - POST /community/works/:id/like → 点赞 - POST /community/works/:id/favorite → 收藏 【实现步骤】 1. 发布/取消发布 2. 可见性控制（公开/仅链接/私密） 3. 点赞和收藏 4. 浏览量统计 【运行命令】pytest server/service/community-service/tests/test_publish_api.py -v | M24: 作品发布API实现完成
A25: V20-COM-003 | B25: 作品发布API - 验收 | C25: Acceptance验收 | D25: 社区分享 | E25: P2 | F25: 后端 | G25: 1 | H25: 2026-W40 | I25: 2026-W40 | J25: V20-COM-002 | K25: 未开始 | L25: 【目标】作品发布API验收 【验收检查项】 □ 发布/取消发布正常 □ 可见性控制正确 □ 点赞收藏正常 【运行命令】pytest server/service/community-service/tests/test_publish_api.py -v | M25: 作品发布API验收通过
A26: V20-COM-004 | B26: 评论互动系统 - 测试 | C26: Red测试 | D26: 社区分享 | E26: P2 | F26: 后端 | G26: 1 | H26: 2026-W40 | I26: 2026-W40 | J26: V20-COM-002 | K26: 未开始 | L26: 【目标】编写评论系统测试 【测试文件路径】server/service/community-service/tests/test_comment_api.py 【测试用例清单】 1. test_create_comment：创建评论 → 201 2. test_reply_comment：回复评论 → 201 3. test_delete_comment：删除评论 → 204 4. test_like_comment：点赞评论 → 200 5. test_get_comments：获取评论列表 → 200 【运行命令】pytest server/service/community-service/tests/test_comment_api.py -v | M26: 5个评论系统测试用例通过
A27: V20-COM-005 | B27: 评论互动系统 - 实现 | C27: Green实现 | D27: 社区分享 | E27: P2 | F27: 后端 | G27: 2 | H27: 2026-W40 | I27: 2026-W40 | J27: V20-COM-004 | K27: 未开始 | L27: 【目标】实现评论互动系统 【源文件路径】server/service/community-service/internal/comment.go 【API端点】 - POST /community/works/:id/comments → 创建评论 - POST /community/comments/:id/reply → 回复评论 - DELETE /community/comments/:id → 删除评论 - POST /community/comments/:id/like → 点赞 - GET /community/works/:id/comments → 评论列表（分页+排序） 【实现步骤】 1. 评论CRUD 2. 嵌套回复（最多3层） 3. 点赞 4. 敏感词过滤 5. 分页查询 【运行命令】pytest server/service/community-service/tests/test_comment_api.py -v | M27: 评论互动系统实现完成
A28: V20-COM-006 | B28: 评论互动系统 - 验收 | C28: Acceptance验收 | D28: 社区分享 | E28: P2 | F28: 后端 | G28: 1 | H28: 2026-W40 | I28: 2026-W40 | J28: V20-COM-005 | K28: 未开始 | L28: 【目标】评论互动系统验收 【验收检查项】 □ 评论CRUD正常 □ 嵌套回复正确 □ 敏感词过滤生效 □ 分页查询正确 【运行命令】pytest server/service/community-service/tests/test_comment_api.py -v | M28: 评论互动系统验收通过
A29: V20-COM-007 | B29: 社区Webview - 测试 | C29: Red测试 | D29: 社区分享 | E29: P2 | F29: 前端 | G29: 1 | H29: 2026-W41 | I29: 2026-W41 | J29: V20-COM-003 | K29: 未开始 | L29: 【目标】编写社区Webview测试 【测试文件路径】extensions/dw-community/__tests__/CommunityPanel.test.ts 【测试用例清单】 1. test_render_work_list：作品列表渲染 2. test_render_comments：评论区渲染 3. test_post_comment：发表评论 【运行命令】npx vitest run extensions/dw-community/__tests__/CommunityPanel.test.ts | M29: 3个社区Webview测试用例通过
A30: V20-COM-008 | B30: 社区Webview - 实现 | C30: Green实现 | D30: 社区分享 | E30: P2 | F30: 前端 | G30: 3 | H30: 2026-W41 | I30: 2026-W41 | J30: V20-COM-007 | K30: 未开始 | L30: 【目标】实现社区Webview 【源文件路径】extensions/dw-community/src/webview/CommunityPanel.ts 【实现步骤】 1. 作品列表页（瀑布流布局） 2. 作品详情页（简介+章节列表+评论区） 3. 评论组件（发表/回复/点赞） 4. 搜索和筛选 5. 个人主页（我的作品/收藏/点赞） 【运行命令】npx vitest run extensions/dw-community/__tests__/CommunityPanel.test.ts | M30: 社区Webview实现完成
A31: V20-COM-009 | B31: 社区Webview - 验收 | C31: Acceptance验收 | D31: 社区分享 | E31: P2 | F31: 前端 | G31: 1 | H31: 2026-W41 | I31: 2026-W41 | J31: V20-COM-008 | K31: 未开始 | L31: 【目标】社区Webview验收 【验收检查项】 □ 作品列表显示正确 □ 评论功能正常 □ 搜索筛选可用 □ 个人主页正常 【运行命令】F5启动Extension Development Host | M31: 社区Webview验收通过
A32: V20-COL-001 | B32: CRDT实时协作引擎 - 测试 | C32: Red测试 | D32: 协作写作 | E32: P2 | F32: 后端 | G32: 1 | H32: 2026-W42 | I32: 2026-W42 | K32: 未开始 | L32: 【目标】编写CRDT协作引擎测试 【测试框架】pytest 【测试文件路径】server/service/collab-service/tests/test_crdt.py 【测试用例清单】 1. test_concurrent_insert：并发插入 → 无冲突 2. test_concurrent_delete：并发删除 → 无冲突 3. test_sync_state：状态同步 → 最终一致 4. test_conflict_resolution：冲突解决 → 正确 5. test_performance_100_users：100用户并发 → 延迟<100ms 【运行命令】pytest server/service/collab-service/tests/test_crdt.py -v | M32: 5个CRDT测试用例通过
A33: V20-COL-002 | B33: CRDT实时协作引擎 - 实现 | C33: Green实现 | D33: 协作写作 | E33: P2 | F33: 后端 | G33: 5 | H33: 2026-W42 | I33: 2026-W43 | J33: V20-COL-001 | K33: 未开始 | L33: 【目标】实现CRDT实时协作引擎 【源文件路径】server/service/collab-service/internal/crdt/ 【技术选型】Yjs (CRDT库) + WebSocket 【实现步骤】 1. 集成Yjs CRDT库 2. WebSocket服务： - /ws/collab/:work_id/:chapter_id - 二进制编码（高效传输） 3. 操作转换： - insert(position, text) - delete(position, length) - format(position, length, attrs) 4. 状态同步： - 新用户加入 → 发送完整文档状态 - 增量更新 → 只发送变更 5. 持久化：定期保存到PostgreSQL 6. 断线重连：自动同步 【运行命令】pytest server/service/collab-service/tests/test_crdt.py -v | M33: CRDT协作引擎实现完成
A34: V20-COL-003 | B34: CRDT实时协作引擎 - 验收 | C34: Acceptance验收 | D34: 协作写作 | E34: P2 | F34: 后端 | G34: 1 | H34: 2026-W43 | I34: 2026-W43 | J34: V20-COL-002 | K34: 未开始 | L34: 【目标】CRDT协作引擎验收 【测试场景】 1. 2人同时编辑 → 无冲突 2. 5人同时编辑 → 最终一致 3. 断线重连 → 自动同步 4. 100用户并发 → 延迟<100ms 【验收检查项】 □ 并发编辑无冲突 □ 最终一致性保证 □ 断线重连正常 □ 性能达标 【运行命令】pytest server/service/collab-service/tests/test_crdt.py -v | M34: CRDT协作引擎验收通过
A35: V20-COL-004 | B35: 协作权限管理 - 测试 | C35: Red测试 | D35: 协作写作 | E35: P2 | F35: 后端 | G35: 1 | H35: 2026-W43 | I35: 2026-W43 | K35: 未开始 | L35: 【目标】编写协作权限管理测试 【测试文件路径】server/service/collab-service/tests/test_permissions.py 【测试用例清单】 1. test_add_collaborator：添加协作者 2. test_role_permissions：角色权限（ owner/editor/viewer） 3. test_remove_collaborator：移除协作者 【运行命令】pytest server/service/collab-service/tests/test_permissions.py -v | M35: 3个权限管理测试用例通过
A36: V20-COL-005 | B36: 协作权限管理 - 实现 | C36: Green实现 | D36: 协作写作 | E36: P2 | F36: 后端 | G36: 2 | H36: 2026-W43 | I36: 2026-W43 | J36: V20-COL-004 | K36: 未开始 | L36: 【目标】实现协作权限管理 【源文件路径】server/service/collab-service/internal/permissions.go 【实现步骤】 1. 角色：owner/editor/viewer 2. 权限矩阵： - owner: 所有权限 - editor: 编辑+评论 - viewer: 只读+评论 3. 邀请协作者（邮箱/链接） 4. 移除协作者 5. 权限变更实时通知 【运行命令】pytest server/service/collab-service/tests/test_permissions.py -v | M36: 协作权限管理实现完成
A37: V20-COL-006 | B37: 协作权限管理 - 验收 | C37: Acceptance验收 | D37: 协作写作 | E37: P2 | F37: 后端 | G37: 1 | H37: 2026-W43 | I37: 2026-W43 | J37: V20-COL-005 | K37: 未开始 | L37: 【目标】协作权限管理验收 【验收检查项】 □ 角色权限正确 □ 邀请/移除正常 □ 权限变更实时通知 【运行命令】pytest server/service/collab-service/tests/test_permissions.py -v | M37: 协作权限管理验收通过
A38: V20-COL-007 | B38: 协作UI - 测试 | C38: Red测试 | D38: 协作写作 | E38: P2 | F38: 前端 | G38: 1 | H38: 2026-W44 | I38: 2026-W44 | J38: V20-COL-003 | K38: 未开始 | L38: 【目标】编写协作UI测试 【测试文件路径】extensions/dw-collab/__tests__/CollabUI.test.ts 【测试用例清单】 1. test_cursor_display：显示协作者光标 2. test_selection_display：显示协作者选区 3. test_avatar_display：显示协作者头像 【运行命令】npx vitest run extensions/dw-collab/__tests__/CollabUI.test.ts | M38: 3个协作UI测试用例通过
A39: V20-COL-008 | B39: 协作UI - 实现 | C39: Green实现 | D39: 协作写作 | E39: P2 | F39: 前端 | G39: 3 | H39: 2026-W44 | I39: 2026-W44 | J39: V20-COL-007 | K39: 未开始 | L39: 【目标】实现协作UI（光标/选区/头像） 【源文件路径】extensions/dw-collab/src/CollabEditor.ts 【实现步骤】 1. 协作者光标显示： - 不同颜色区分 - 显示用户名标签 - 实时更新位置 2. 协作者选区显示： - 半透明背景色 - 实时更新 3. 协作者头像： - 右上角显示在线用户头像列表 - 头像颜色与光标颜色一致 4. WebSocket连接管理： - 自动连接/断线重连 - 连接状态指示 【运行命令】npx vitest run extensions/dw-collab/__tests__/CollabUI.test.ts | M39: 协作UI实现完成
A40: V20-COL-009 | B40: 协作UI - 验收 | C40: Acceptance验收 | D40: 协作写作 | E40: P2 | F40: 前端 | G40: 1 | H40: 2026-W44 | I40: 2026-W44 | J40: V20-COL-008 | K40: 未开始 | L40: 【目标】协作UI验收 【测试场景】 1. 2人同时编辑 → 各自光标和选区正确显示 2. 在线用户列表 → 头像和名称正确 3. 断线重连 → UI状态恢复 【验收检查项】 □ 光标显示正确 □ 选区显示正确 □ 头像列表正确 □ 连接状态正确 【运行命令】F5启动Extension Development Host | M40: 协作UI验收通过
A41: V20-COV-001 | B41: AI图像生成集成 - 测试 | C41: Red测试 | D41: 封面生成 | E41: P2 | F41: AI工程师 | G41: 1 | H41: 2026-W44 | I41: 2026-W44 | K41: 未开始 | L41: 【目标】编写AI图像生成测试 【测试文件路径】ai-service/tests/services/test_image_gen.py 【测试用例清单】 1. test_generate_cover：生成封面图 → 返回图片URL 2. test_style_transfer：风格迁移 → 正确 3. test_text_overlay：文字叠加 → 正确 【运行命令】pytest ai-service/tests/services/test_image_gen.py -v | M41: 3个图像生成测试用例通过
A42: V20-COV-002 | B42: AI图像生成集成 - 实现 | C42: Green实现 | D42: 封面生成 | E42: P2 | F42: AI工程师 | G42: 3 | H42: 2026-W44 | I42: 2026-W44 | J42: V20-COV-001 | K42: 未开始 | L42: 【目标】实现AI图像生成集成 【源文件路径】ai-service/app/services/image_generator.py 【实现步骤】 1. 集成DALL-E 3 / Midjourney API / Stable Diffusion 2. 实现generate_cover(prompt, style, size)： - 根据作品类型生成封面 - 支持多种风格（写实/插画/水墨/动漫） 3. 风格迁移：将生成图片转为指定风格 4. 文字叠加：将作品标题叠加到封面 5. 图片存储到OSS/S3 【运行命令】pytest ai-service/tests/services/test_image_gen.py -v | M42: AI图像生成集成实现完成
A43: V20-COV-003 | B43: AI图像生成集成 - 验收 | C43: Acceptance验收 | D43: 封面生成 | E43: P2 | F43: AI工程师 | G43: 1 | H43: 2026-W44 | I43: 2026-W44 | J43: V20-COV-002 | K43: 未开始 | L43: 【目标】AI图像生成验收 【验收检查项】 □ 封面生成质量可接受 □ 风格迁移正确 □ 文字叠加正确 □ 生成时间<30s 【运行命令】pytest ai-service/tests/services/test_image_gen.py -v | M43: AI图像生成验收通过
A44: V20-COV-004 | B44: 封面编辑器 - 测试 | C44: Red测试 | D44: 封面生成 | E44: P2 | F44: 前端 | G44: 1 | H44: 2026-W45 | I44: 2026-W45 | J44: V20-COV-002 | K44: 未开始 | L44: 【目标】编写封面编辑器测试 【测试文件路径】extensions/dw-cover-editor/__tests__/CoverEditor.test.ts 【测试用例清单】 1. test_render_editor：编辑器渲染 2. test_text_edit：文字编辑 3. test_style_change：风格切换 【运行命令】npx vitest run extensions/dw-cover-editor/__tests__/CoverEditor.test.ts | M44: 3个封面编辑器测试用例通过
A45: V20-COV-005 | B45: 封面编辑器 - 实现 | C45: Green实现 | D45: 封面生成 | E45: P2 | F45: 前端 | G45: 3 | H45: 2026-W45 | I45: 2026-W45 | J45: V20-COV-004 | K45: 未开始 | L45: 【目标】实现封面编辑器 【源文件路径】extensions/dw-cover-editor/src/webview/CoverEditor.ts 【实现步骤】 1. Canvas画布编辑器 2. 功能： - 拖拽文字位置 - 调整字体/大小/颜色 - 背景图选择/上传 - 滤镜效果 - 图层管理 3. 预设模板 4. 导出为PNG/JPG 【运行命令】npx vitest run extensions/dw-cover-editor/__tests__/CoverEditor.test.ts | M45: 封面编辑器实现完成
A46: V20-COV-006 | B46: 封面编辑器 - 验收 | C46: Acceptance验收 | D46: 封面生成 | E46: P2 | F46: 前端 | G46: 1 | H46: 2026-W45 | I46: 2026-W45 | J46: V20-COV-005 | K46: 未开始 | L46: 【目标】封面编辑器验收 【验收检查项】 □ 编辑器渲染正确 □ 文字编辑可用 □ 风格切换正常 □ 导出功能正常 【运行命令】F5启动Extension Development Host | M46: 封面编辑器验收通过
A47: V20-FRK-001 | B47: 自定义TextModel - 测试 | C47: Red测试 | D47: 深度Fork | E47: P2 | F47: 前端 | G47: 1 | H47: 2026-W46 | I47: 2026-W46 | J47: V15-FRK-009 | K47: 未开始 | L47: 【目标】编写自定义TextModel测试 【测试文件路径】extensions/dw-core/__tests__/TextModel.test.ts 【测试用例清单】 1. test_chapter_model：章节模型正确 2. test_branch_switch：分支切换时模型更新 3. test_version_history：版本历史集成 【运行命令】npx vitest run extensions/dw-core/__tests__/TextModel.test.ts | M47: 3个TextModel测试用例通过
A48: V20-FRK-002 | B48: 自定义TextModel - 实现 | C48: Green实现 | D48: 深度Fork | E48: P2 | F48: 前端 | G48: 5 | H48: 2026-W46 | I48: 2026-W47 | J48: V20-FRK-001 | K48: 未开始 | L48: 【目标】实现自定义TextModel 【源文件路径】src/vs/editor/common/model/dreamweaverTextModel.ts 【实现步骤】 1. 继承vscode.TextModel 2. 添加小说创作特有功能： - 章节管理（章节边界标记） - 分支感知（知道当前属于哪个分支） - 版本快照集成 - 字数统计（中文字数精确计算） 3. 修改保存逻辑： - 保存时自动创建版本快照 - 保存时触发实体提取 - 保存时触发一致性检查 4. 自定义Undo/Redo栈 【运行命令】yarn watch | M48: 自定义TextModel实现完成
A49: V20-FRK-003 | B49: 自定义TextModel - 验收 | C49: Acceptance验收 | D49: 深度Fork | E49: P2 | F49: 前端 | G49: 1 | H49: 2026-W47 | I49: 2026-W47 | J49: V20-FRK-002 | K49: 未开始 | L49: 【目标】自定义TextModel验收 【验收检查项】 □ 章节管理正确 □ 分支切换更新 □ 版本快照集成 □ 字数统计准确 【运行命令】yarn watch && yarn electron | M49: 自定义TextModel验收通过
A50: V20-FRK-004 | B50: 编辑器装饰器 - 测试 | C50: Red测试 | D50: 深度Fork | E50: P2 | F50: 前端 | G50: 1 | H50: 2026-W47 | I50: 2026-W47 | J50: V20-FRK-002 | K50: 未开始 | L50: 【目标】编写编辑器装饰器测试 【测试文件路径】extensions/dw-core/__tests__/Decorations.test.ts 【测试用例清单】 1. test_ai_completion_marker：AI补全标记 2. test_consistency_marker：一致性标记 3. test_foreshadow_marker：伏笔标记 【运行命令】npx vitest run extensions/dw-core/__tests__/Decorations.test.ts | M50: 3个装饰器测试用例通过
A51: V20-FRK-005 | B51: 编辑器装饰器 - 实现 | C51: Green实现 | D51: 深度Fork | E51: P2 | F51: 前端 | G51: 3 | H51: 2026-W47 | I51: 2026-W47 | J51: V20-FRK-004 | K51: 未开始 | L51: 【目标】实现编辑器装饰器 【源文件路径】extensions/dw-core/src/decorations/ 【实现步骤】 1. AI补全标记：灰色虚线下划线标记AI生成的内容 2. 一致性标记： - Error: 红色波浪线 - Warning: 黄色波浪线 - Info: 蓝色虚线 3. 伏笔标记：绿色高亮标记伏笔位置 4. 角色名高亮：知识库角色名特殊颜色 5. 装饰器管理：统一注册和更新 【运行命令】npx vitest run extensions/dw-core/__tests__/Decorations.test.ts | M51: 编辑器装饰器实现完成
A52: V20-FRK-006 | B52: 编辑器装饰器 - 验收 | C52: Acceptance验收 | D52: 深度Fork | E52: P2 | F52: 前端 | G52: 1 | H52: 2026-W47 | I52: 2026-W47 | J52: V20-FRK-005 | K52: 未开始 | L52: 【目标】编辑器装饰器验收 【验收检查项】 □ AI补全标记正确 □ 一致性标记颜色正确 □ 伏笔标记正确 □ 角色名高亮正确 □ 性能不影响编辑 【运行命令】yarn watch && yarn electron | M52: 编辑器装饰器验收通过
A53: V20-FRK-007 | B53: 自定义Diff Provider - 测试 | C53: Red测试 | D53: 深度Fork | E53: P2 | F53: 前端 | G53: 1 | H53: 2026-W48 | I53: 2026-W48 | J53: V15-MRG-003 | K53: 未开始 | L53: 【目标】编写自定义Diff Provider测试 【测试文件路径】extensions/dw-core/__tests__/DiffProvider.test.ts 【测试用例清单】 1. test_branch_diff：分支对比 → 正确显示差异 2. test_version_diff：版本对比 → 正确 3. test_conflict_display：冲突显示 → 清晰 【运行命令】npx vitest run extensions/dw-core/__tests__/DiffProvider.test.ts | M53: 3个Diff Provider测试用例通过
... A55: V20-FRK-009 | B55: 自定义Diff Provider - 验收 | C55: Acceptance验收 | D55: 深度Fork | E55: P2 | F55: 前端 | G55: 1 | H55: 2026-W48 | I55: 2026-W48 | J55: V20-FRK-008 | K55: 未开始 | L55: 【目标】自定义Diff Provider验收 【验收检查项】 □ 分支对比正确 □ 版本对比正确 □ 冲突显示清晰 □ 性能可接受（100K字<2s） 【运行命令】yarn watch && yarn electron | M55: 自定义Diff Provider验收通过
A56: V20-PER-001 | B56: 大文件编辑优化 - 测试 | C56: Red测试 | D56: 性能优化 | E56: P2 | F56: 前端 | G56: 1 | H56: 2026-W49 | I56: 2026-W49 | K56: 未开始 | L56: 【目标】编写大文件编辑优化测试 【测试文件路径】extensions/dw-core/__tests__/LargeFileOptimization.test.ts 【测试用例清单】 1. test_virtual_rendering_100k：10万字虚拟渲染 → FPS≥30 2. test_lazy_loading：懒加载 → 内存占用<500MB 3. test_incremental_parsing：增量解析 → 响应<50ms 【运行命令】npx vitest run extensions/dw-core/__tests__/LargeFileOptimization.test.ts | M56: 3个大文件优化测试用例通过
A57: V20-PER-002 | B57: 大文件编辑优化 - 实现 | C57: Green实现 | D57: 性能优化 | E57: P2 | F57: 前端 | G57: 3 | H57: 2026-W49 | I57: 2026-W49 | J57: V20-PER-001 | K57: 未开始 | L57: 【目标】实现大文件编辑优化 【源文件路径】src/vs/editor/, extensions/dw-core/src/performance/ 【实现步骤】 1. 虚拟渲染：只渲染可视区域的行 2. 懒加载：非活跃章节延迟加载 3. 增量解析：语法高亮和一致性检查增量执行 4. 内存优化：大文件分块管理 5. Web Worker：将计算密集任务移到Worker线程 【运行命令】npx vitest run extensions/dw-core/__tests__/LargeFileOptimization.test.ts | M57: 大文件编辑优化实现完成
A58: V20-PER-003 | B58: 大文件编辑优化 - 验收 | C58: Acceptance验收 | D58: 性能优化 | E58: P2 | F58: 前端 | G58: 1 | H58: 2026-W49 | I58: 2026-W49 | J58: V20-PER-002 | K58: 未开始 | L58: 【目标】大文件编辑优化验收 【验收检查项】 □ 10万字文件FPS≥30 □ 内存占用<500MB □ 编辑响应<50ms □ 语法高亮不卡顿 【运行命令】yarn watch && yarn electron | M58: 大文件编辑优化验收通过
A59: V20-PER-004 | B59: AI响应缓存优化 - 测试 | C59: Red测试 | D59: 性能优化 | E59: P2 | F59: AI工程师 | G59: 1 | H59: 2026-W49 | I59: 2026-W49 | K59: 未开始 | L59: 【目标】编写AI响应缓存优化测试 【测试文件路径】ai-service/tests/services/test_ai_cache.py 【测试用例清单】 1. test_semantic_cache：语义缓存命中 2. test_cache_ttl：缓存过期 3. test_cache_invalidation：缓存失效 【运行命令】pytest ai-service/tests/services/test_ai_cache.py -v | M59: 3个AI缓存测试用例通过
A60: V20-PER-005 | B60: AI响应缓存优化 - 实现 | C60: Green实现 | D60: 性能优化 | E60: P2 | F60: AI工程师 | G60: 2 | H60: 2026-W49 | I60: 2026-W49 | J60: V20-PER-004 | K60: 未开始 | L60: 【目标】实现AI响应缓存优化 【源文件路径】ai-service/app/services/ai_cache.py 【实现步骤】 1. 语义缓存：相似Prompt（余弦相似度>0.95）命中缓存 2. Redis缓存：TTL=1h，LRU淘汰 3. 本地内存缓存：热点数据缓存 4. 缓存预热：常用Prompt预生成 5. 缓存统计：命中率/节省Token数 【运行命令】pytest ai-service/tests/services/test_ai_cache.py -v | M60: AI响应缓存优化实现完成
A61: V20-PER-006 | B61: AI响应缓存优化 - 验收 | C61: Acceptance验收 | D61: 性能优化 | E61: P2 | F61: AI工程师 | G61: 1 | H61: 2026-W49 | I61: 2026-W49 | J61: V20-PER-005 | K61: 未开始 | L61: 【目标】AI响应缓存优化验收 【验收检查项】 □ 语义缓存命中率≥30% □ 缓存命中时响应<100ms □ 缓存失效正确 □ 节省Token≥20% 【运行命令】pytest ai-service/tests/services/test_ai_cache.py -v | M61: AI响应缓存优化验收通过
A62: V20-MOB-001 | B62: 响应式布局 - 测试 | C62: Red测试 | D62: 移动端 | E62: P2 | F62: 前端 | G62: 1 | H62: 2026-W50 | I62: 2026-W50 | K62: 未开始 | L62: 【目标】编写响应式布局测试 【测试文件路径】extensions/dw-core/__tests__/ResponsiveLayout.test.ts 【测试用例清单】 1. test_desktop_layout：桌面布局（>1200px） 2. test_tablet_layout：平板布局（768-1200px） 3. test_mobile_layout：手机布局（<768px） 【运行命令】npx vitest run extensions/dw-core/__tests__/ResponsiveLayout.test.ts | M62: 3个响应式布局测试用例通过
A63: V20-MOB-002 | B63: 响应式布局 - 实现 | C63: Green实现 | D63: 移动端 | E63: P2 | F63: 前端 | G63: 3 | H63: 2026-W50 | I63: 2026-W50 | J63: V20-MOB-001 | K63: 未开始 | L63: 【目标】实现响应式布局 【源文件路径】extensions/dw-core/src/layout/ 【实现步骤】 1. CSS媒体查询： - 桌面（>1200px）：完整布局 - 平板（768-1200px）：侧边栏可折叠 - 手机（<768px）：单栏布局 2. Activity Bar响应式： - 桌面：左侧图标栏 - 平板：底部标签栏 - 手机：汉堡菜单 3. 编辑器响应式： - 自适应宽度 - 字体大小调整 4. Webview响应式： - AI面板自适应 - 知识库面板自适应 【运行命令】npx vitest run extensions/dw-core/__tests__/ResponsiveLayout.test.ts | M63: 响应式布局实现完成
A64: V20-MOB-003 | B64: 响应式布局 - 验收 | C64: Acceptance验收 | D64: 移动端 | E64: P2 | F64: 前端 | G64: 1 | H64: 2026-W50 | I64: 2026-W50 | J64: V20-MOB-002 | K64: 未开始 | L64: 【目标】响应式布局验收 【测试场景】 1. 桌面浏览器 → 完整布局 2. 平板 → 侧边栏折叠 3. 手机 → 单栏布局 【验收检查项】 □ 三种布局正确切换 □ 功能在所有尺寸可用 □ 触摸操作友好 【运行命令】yarn watch && yarn electron | M64: 响应式布局验收通过
A65: V20-MOB-004 | B65: 手势交互 - 测试 | C65: Red测试 | D65: 移动端 | E65: P2 | F65: 前端 | G65: 1 | H65: 2026-W50 | I65: 2026-W50 | J65: V20-MOB-002 | K65: 未开始 | L65: 【目标】编写手势交互测试 【测试文件路径】extensions/dw-core/__tests__/Gestures.test.ts 【测试用例清单】 1. test_swipe_navigation：滑动导航 2. test_pinch_zoom：捏合缩放 3. test_long_press：长按菜单 【运行命令】npx vitest run extensions/dw-core/__tests__/Gestures.test.ts | M65: 3个手势交互测试用例通过
A66: V20-MOB-005 | B66: 手势交互 - 实现 | C66: Green实现 | D66: 移动端 | E66: P2 | F66: 前端 | G66: 2 | H66: 2026-W50 | I66: 2026-W50 | J66: V20-MOB-004 | K66: 未开始 | L66: 【目标】实现手势交互 【源文件路径】extensions/dw-core/src/gestures/ 【实现步骤】 1. 滑动导航：左右滑动切换章节/面板 2. 捏合缩放：编辑器字体缩放 3. 长按菜单：长按显示上下文菜单 4. 下拉刷新：刷新AI面板/知识库 5. 使用Hammer.js或自研手势库 【运行命令】npx vitest run extensions/dw-core/__tests__/Gestures.test.ts | M66: 手势交互实现完成
A67: V20-MOB-006 | B67: 手势交互 - 验收 | C67: Acceptance验收 | D67: 移动端 | E67: P2 | F67: 前端 | G67: 1 | H67: 2026-W50 | I67: 2026-W50 | J67: V20-MOB-005 | K67: 未开始 | L67: 【目标】手势交互验收 【测试场景】 1. 左右滑动 → 切换章节 2. 捏合 → 字体缩放 3. 长按 → 上下文菜单 【验收检查项】 □ 滑动导航流畅 □ 缩放正确 □ 长按菜单正确 □ 手势不冲突 【运行命令】yarn watch && yarn electron | M67: 手势交互验收通过

Sheet 里程碑
A1: ID | B1: 名称 | C1: 版本 | D1: 时间 | E1: 交付物 | F1: 验收标准 | G1: 状态
A2: M1 | B2: 技术验证 | C2: v1.0 | D2: W14 | E2: 编辑器Demo+AI基础集成 | F2: 能在编辑器中调用AI生成文本 | G2: 未开始
A3: M2 | B3: Alpha内测 | C3: v1.0 | D3: W18 | E3: 完整MVP功能 | F3: 内部团队可完成一部短篇小说创作 | G3: 未开始
A4: M3 | B4: Beta公测 | C4: v1.0 | D4: W21 | E4: 公测版本+基础运营 | F4: 500名种子用户，7日留存>=30% | G4: 未开始
A5: M4 | B5: 正式上线 | C5: v1.0 | D5: W22 | E5: v1.0正式版 | F5: 注册用户>=5000，付费转化>=5% | G5: 未开始
A6: M5 | B6: 协作模式完成 | C6: v1.5 | D6: W26 | E6: 5种协作模式 | F6: 多模型协作流水线可用 | G6: 未开始
A7: M6 | B7: 分支合并完成 | C7: v1.5 | D7: W28 | E7: 分支合并功能 | F7: 段落级+AI辅助合并可用 | G7: 未开始
A8: M7 | B8: 去AI味上线 | C8: v1.5 | D8: W30 | E8: 去AI味引擎 | F8: AI检测+去AI味可用 | G8: 未开始
A9: M8 | B9: v1.5发布 | C9: v1.5 | D9: W32 | E9: v1.5增强版 | F9: 8-10个模型+高级RAG+去AI味 | G9: 未开始
A10: M9 | B10: 模板市场上线 | C10: v2.0 | D10: W36 | E10: 模板市场 | F10: 预设+社区模板可用 | G10: 未开始
A11: M10 | B11: 社区+协作 | C11: v2.0 | D11: W38 | E11: 社区分享+协作写作 | F11: 作品发布+评论+实时协作 | G11: 未开始
A12: M11 | B12: 深度Fork完成 | C12: v2.0 | D12: W40 | E12: 深度定制编辑器 | F12: 自定义TextModel+Diff+装饰器 | G12: 未开始
... A20: M19 | B20: 全球版验收 | C20: v2.3 | D20: W30 | E20: 全球版E2E测试报告 | F20: GDPR合规审计通过 | G20: 未开始

Sheet 任务总览
A1: 织梦笔项目任务总览
A3: 版本 | B3: 总任务数 | C3: 未开始 | D3: 进行中 | E3: 测试中 | F3: 已完成 | G3: 阻塞 | H3: 完成率
A4: v1.0-MVP | B4: =COUNTA('v1.0-MVP'!A2:A1000) | C4: =COUNTIF('v1.0-MVP'!K2:K1000,"未开始") | D4: =COUNTIF('v1.0-MVP'!K2:K1000,"进行中") | E4: =COUNTIF('v1.0-MVP'!K2:K1000,"测试中") | F4: =COUNTIF('v1.0-MVP'!K2:K1000,"已完成") | G4: =COUNTIF('v1.0-MVP'!K2:K1000,"阻塞") | H4: =IF(B4=0,"N/A",G4/B4)
A5: v1.5-增强 | B5: =COUNTA('v1.5-增强'!A2:A1000) | C5: =COUNTIF('v1.5-增强'!K2:K1000,"未开始") | D5: =COUNTIF('v1.5-增强'!K2:K1000,"进行中") | E5: =COUNTIF('v1.5-增强'!K2:K1000,"测试中") | F5: =COUNTIF('v1.5-增强'!K2:K1000,"已完成") | G5: =COUNTIF('v1.5-增强'!K2:K1000,"阻塞") | H5: =IF(B5=0,"N/A",G5/B5)
A6: v2.0-生态 | B6: =COUNTA('v2.0-生态'!A2:A1000) | C6: =COUNTIF('v2.0-生态'!K2:K1000,"未开始") | D6: =COUNTIF('v2.0-生态'!K2:K1000,"进行中") | E6: =COUNTIF('v2.0-生态'!K2:K1000,"测试中") | F6: =COUNTIF('v2.0-生态'!K2:K1000,"已完成") | G6: =COUNTIF('v2.0-生态'!K2:K1000,"阻塞") | H6: =IF(B6=0,"N/A",G6/B6)
A7: 合计 | B7: =SUM(B4:B6) | C7: =SUM(C4:C6) | D7: =SUM(D4:D6) | E7: =SUM(E4:E6) | F7: =SUM(F4:F6) | G7: =SUM(G4:G6) | H7: =IF(B7=0,"N/A",G7/B7)
A9: 优先级分布
A10: 版本 | B10: P0 | C10: P1 | D10: P2
A11: v1.0-MVP | B11: =COUNTIF('v1.0-MVP'!E2:E1000,"P0") | C11: =COUNTIF('v1.0-MVP'!E2:E1000,"P1") | D11: =COUNTIF('v1.0-MVP'!E2:E1000,"P2")
A12: v1.5-增强 | B12: =COUNTIF('v1.5-增强'!E2:E1000,"P0") | C12: =COUNTIF('v1.5-增强'!E2:E1000,"P1") | D12: =COUNTIF('v1.5-增强'!E2:E1000,"P2")
A13: v2.0-生态 | B13: =COUNTIF('v2.0-生态'!E2:E1000,"P0") | C13: =COUNTIF('v2.0-生态'!E2:E1000,"P1") | D13: =COUNTIF('v2.0-生态'!E2:E1000,"P2")
A15: 角色分布
A16: 版本 | B16: 前端 | C16: 后端 | D16: AI工程师 | E16: 设计师 | F16: 测试 | G16: 全栈
A17: v1.0-MVP | B17: =COUNTIF('v1.0-MVP'!F2:F1000,"前端") | C17: =COUNTIF('v1.0-MVP'!F2:F1000,"后端") | D17: =COUNTIF('v1.0-MVP'!F2:F1000,"AI工程师") | E17: =COUNTIF('v1.0-MVP'!F2:F1000,"设计师") | F17: =COUNTIF('v1.0-MVP'!F2:F1000,"测试") | G17: =COUNTIF('v1.0-MVP'!F2:F1000,"全栈")
A18: v1.5-增强 | B18: =COUNTIF('v1.5-增强'!F2:F1000,"前端") | C18: =COUNTIF('v1.5-增强'!F2:F1000,"后端") | D18: =COUNTIF('v1.5-增强'!F2:F1000,"AI工程师") | E18: =COUNTIF('v1.5-增强'!F2:F1000,"设计师") | F18: =COUNTIF('v1.5-增强'!F2:F1000,"测试") | G18: =COUNTIF('v1.5-增强'!F2:F1000,"全栈")
A19: v2.0-生态 | B19: =COUNTIF('v2.0-生态'!F2:F1000,"前端") | C19: =COUNTIF('v2.0-生态'!F2:F1000,"后端") | D19: =COUNTIF('v2.0-生态'!F2:F1000,"AI工程师") | E19: =COUNTIF('v2.0-生态'!F2:F1000,"设计师") | F19: =COUNTIF('v2.0-生态'!F2:F1000,"测试") | G19: =COUNTIF('v2.0-生态'!F2:F1000,"全栈")
A21: TDD阶段分布
A22: 版本 | B22: Red测试 | C22: Green实现 | D22: Refactor重构 | E22: Acceptance验收 | F22: 基础设施
A23: v1.0-MVP | B23: =COUNTIF('v1.0-MVP'!C2:C1000,"Red测试") | C23: =COUNTIF('v1.0-MVP'!C2:C1000,"Green实现") | D23: =COUNTIF('v1.0-MVP'!C2:C1000,"Refactor重构") | E23: =COUNTIF('v1.0-MVP'!C2:C1000,"Acceptance验收") | F23: =COUNTIF('v1.0-MVP'!C2:C1000,"基础设施")
A24: v1.5-增强 | B24: =COUNTIF('v1.5-增强'!C2:C1000,"Red测试") | C24: =COUNTIF('v1.5-增强'!C2:C1000,"Green实现") | D24: =COUNTIF('v1.5-增强'!C2:C1000,"Refactor重构") | E24: =COUNTIF('v1.5-增强'!C2:C1000,"Acceptance验收") | F24: =COUNTIF('v1.5-增强'!C2:C1000,"基础设施")
A25: v2.0-生态 | B25: =COUNTIF('v2.0-生态'!C2:C1000,"Red测试") | C25: =COUNTIF('v2.0-生态'!C2:C1000,"Green实现") | D25: =COUNTIF('v2.0-生态'!C2:C1000,"Refactor重构") | E25: =COUNTIF('v2.0-生态'!C2:C1000,"Acceptance验收") | F25: =COUNTIF('v2.0-生态'!C2:C1000,"基础设施")
A27: v2.5-Harness | B27: 127 | C27: 127 | D27: 0 | E27: 0 | F27: 0 | G27: 0 | H27: 0%
A28: v2.3-Global | B28: 93 | C28: 93 | D28: 0 | E28: 0 | F28: 0 | G28: 0 | H28: 0%

Sheet v2.5-Harness
A1: 任务ID | B1: 任务名称 | C1: TDD阶段 | D1: 所属模块 | E1: 优先级 | F1: 负责角色 | G1: 预估工时 | H1: 开始周 | I1: 结束周 | J1: 前置依赖 | K1: 状态 | L1: 详细任务提示词 | M1: 验收标准 | N1: 备注
A2: V25-PCH-001 | B2: 静态/动态边界分割 - 测试 | C2: Red测试 | D2: Prompt Cache Harness | E2: P0 | F2: AI工程师 | G2: 3 | H2: 2026-W27 | I2: 2026-W28 | K2: 未开始 | L2: 【目标】测试promptBuilder.ts能正确识别静态段（平台指令、写作风格、题材模板）和动态段（章节上下文、角色状态、活跃伏笔），验证DYNAMIC_BOUNDARY标记插入位置正确，静态段约3000 tokens使用global scope缓存。 【运行命令】npm test -- --grep 'PromptBuilder' 【测试文件路径】src/harness/prompt-cache/__tests__/promptBuilder.test.ts 【测试用例清单】1. 静态段包含平台指令+写作风格+题材模板 2. 动态段包含章节上下文+角色状态+伏笔 3. DYNAMIC_BOUNDARY标记位于静态段和动态段之间 4. 静态段token数约3000 5. 动态段每turn重新计算 | M2: 所有测试用例通过，静态段正确识别并缓存 | N2: 借鉴Claude Code PR#24490 Blake2b哈希碎片化修复
A3: V25-PCH-002 | B3: 静态/动态边界分割 - 实现 | C3: Green实现 | D3: Prompt Cache Harness | E3: P0 | F3: AI工程师 | G3: 5 | H3: 2026-W27 | I3: 2026-W28 | J3: V25-PCH-001 | K3: 未开始 | L3: 【目标】实现三文件联动协议：promptBuilder.ts产出DYNAMIC_BOUNDARY标记→cacheSplitter.ts消费标记分割为3-4个block→apiRequestBuilder.ts映射为API cache_control blocks。静态段使用global scope缓存，动态段每turn重新计算。 【运行命令】npm test -- --grep 'PromptBuilder' 【实现步骤】1. 创建src/harness/prompt-cache/promptBuilder.ts，实现静态/动态段识别逻辑 2. 创建cacheSplitter.ts，实现三文件联动协议 3. 创建apiRequestBuilder.ts，映射cache_control blocks 4. 集成到REPL循环中 【源文件路径】src/harness/prompt-cache/promptBuilder.ts 【测试文件路径】src/harness/prompt-cache/__tests__/promptBuilder.test.ts | M3: 三文件联动协议正确工作，静态段global scope缓存命中
A4: V25-PCH-003 | B4: 静态/动态边界分割 - 重构 | C4: Refactor重构 | D4: Prompt Cache Harness | E4: P0 | F4: AI工程师 | G4: 2 | H4: 2026-W28 | I4: 2026-W29 | J4: V25-PCH-002 | K4: 未开始 | L4: 【目标】重构promptBuilder.ts的静态/动态段识别逻辑，提取公共方法，优化性能，添加TypeScript类型定义。 【运行命令】npm test -- --grep 'PromptBuilder' && npm run lint 【源文件路径】src/harness/prompt-cache/promptBuilder.ts | M4: 代码通过lint检查，测试全部通过，性能无回退
A5: V25-PCH-004 | B5: 静态/动态边界分割 - 验收 | C5: Acceptance验收 | D5: Prompt Cache Harness | E5: P0 | F5: AI工程师 | G5: 2 | H5: 2026-W28 | I5: 2026-W29 | J5: V25-PCH-003 | K5: 未开始 | L5: 【目标】验收静态/动态边界分割功能的完整实现，确认缓存命中率符合预期。 【运行命令】npm test -- --grep 'PromptBuilder' && node scripts/verify-cache-boundary.ts 【验收检查项】1. 静态段正确识别，约3000 tokens 2. DYNAMIC_BOUNDARY标记位置正确 3. 三文件联动协议正常工作 4. global scope缓存命中率>60% | M5: 验收通过，静态段缓存命中率达标
A6: V25-PCH-005 | B6: 三种缓存模式 - 测试 | C6: Red测试 | D6: Prompt Cache Harness | E6: P0 | F6: AI工程师 | G6: 3 | H6: 2026-W27 | I6: 2026-W28 | K6: 未开始 | L6: 【目标】测试Global Cache（有boundary+无外部工具，4 blocks）、Org Cache（有外部工具如MCP，3 blocks）、Default（boundary缺失降级，3 blocks）三种模式的自动选择逻辑，验证Attribution header永远不缓存（包含用户fingerprint，每请求不同）。 【运行命令】npm test -- --grep 'CacheMode' 【测试文件路径】src/harness/prompt-cache/__tests__/cacheMode.test.ts 【测试用例清单】1. 有boundary+无外部工具→Global Cache 4 blocks 2. 有MCP工具→Org Cache 3 blocks 3. boundary缺失→Default 3 blocks 4. Attribution header永远不缓存 5. static段使用global scope | M6: 三种缓存模式自动选择逻辑正确
A7: V25-PCH-006 | B7: 三种缓存模式 - 实现 | C7: Green实现 | D7: Prompt Cache Harness | E7: P0 | F7: AI工程师 | G7: 5 | H7: 2026-W27 | I7: 2026-W28 | J7: V25-PCH-005 | K7: 未开始 | L7: 【目标】实现三种缓存模式的自动选择逻辑：Global Cache模式使用4 blocks（attribution+prefix+static+dynamic），Org Cache模式使用3 blocks（attribution+prefix+rest），Default模式使用3 blocks。Attribution header永远不缓存。 【运行命令】npm test -- --grep 'CacheMode' 【实现步骤】1. 创建src/harness/prompt-cache/cacheMode.ts 2. 实现selectCacheMode()函数 3. 实现buildCacheBlocks()函数 4. 集成到cacheSplitter.ts 【源文件路径】src/harness/prompt-cache/cacheMode.ts 【测试文件路径】src/harness/prompt-cache/__tests__/cacheMode.test.ts | M7: 三种缓存模式正确实现并自动选择
A8: V25-PCH-007 | B8: 三种缓存模式 - 重构 | C8: Refactor重构 | D8: Prompt Cache Harness | E8: P0 | F8: AI工程师 | G8: 2 | H8: 2026-W28 | I8: 2026-W29 | J8: V25-PCH-006 | K8: 未开始 | L8: 【目标】重构缓存模式选择逻辑，优化条件判断，提取公共block构建方法。 【运行命令】npm test -- --grep 'CacheMode' && npm run lint 【源文件路径】src/harness/prompt-cache/cacheMode.ts | M8: 代码通过lint，测试通过，模式选择逻辑清晰
A9: V25-PCH-008 | B9: 三种缓存模式 - 验收 | C9: Acceptance验收 | D9: Prompt Cache Harness | E9: P0 | F9: AI工程师 | G9: 2 | H9: 2026-W28 | I9: 2026-W29 | J9: V25-PCH-007 | K9: 未开始 | L9: 【目标】验收三种缓存模式的完整实现，确认模式切换逻辑正确。 【运行命令】npm test -- --grep 'CacheMode' 【验收检查项】1. Global Cache 4 blocks正确 2. Org Cache 3 blocks正确 3. Default 3 blocks正确 4. Attribution不缓存 5. 模式切换无缓存泄漏 | M9: 三种缓存模式验收通过
A10: V25-PCH-009 | B10: 工具Schema两层缓存 - 测试 | C10: Red测试 | D10: Prompt Cache Harness | E10: P0 | F10: AI工程师 | G10: 3 | H10: 2026-W28 | I10: 2026-W29 | K10: 未开始 | L10: 【目标】测试cacheKey格式为`${tool.name}:${jsonStringify(tool.inputSchema)}`，会话级TTL=1h，每请求覆盖层处理defer_loading/cache_control。验证同名工具不同schema不会返回错误schema（借鉴Claude Code PR#25424的51%错误率修复）。 【运行命令】npm test -- --grep 'SchemaCache' 【测试文件路径】src/harness/prompt-cache/__tests__/schemaCache.test.ts 【测试用例清单】1. cacheKey包含tool.name和inputSchema 2. 同名工具不同schema返回不同缓存 3. 会话级TTL=1h过期 4. 每请求覆盖层正确处理defer_loading 5. Schema变化时缓存自动失效 | M10: Schema两层缓存逻辑正确，无错误schema返回 | N10: 借鉴PR#25424：错误率5.4%→51%
A11: V25-PCH-010 | B11: 工具Schema两层缓存 - 实现 | C11: Green实现 | D11: Prompt Cache Harness | E11: P0 | F11: AI工程师 | G11: 4 | H11: 2026-W28 | I11: 2026-W29 | J11: V25-PCH-009 | K11: 未开始 | L11: 【目标】实现工具Schema两层缓存：会话级缓存基础schema（name, description, input_schema, strict），每请求覆盖层处理defer_loading和cache_control。cacheKey使用tool.name+jsonStringify(tool.inputSchema)确保唯一性。 【运行命令】npm test -- --grep 'SchemaCache' 【实现步骤】1. 创建src/harness/prompt-cache/schemaCache.ts 2. 实现SessionSchemaCache类 3. 实现getSchema()和invalidateSchema()方法 4. 集成到apiRequestBuilder.ts 【源文件路径】src/harness/prompt-cache/schemaCache.ts 【测试文件路径】src/harness/prompt-cache/__tests__/schemaCache.test.ts | M11: Schema两层缓存正确实现，TTL过期机制工作
A12: V25-PCH-011 | B12: 工具Schema两层缓存 - 重构 | C12: Refactor重构 | D12: Prompt Cache Harness | E12: P0 | F12: AI工程师 | G12: 2 | H12: 2026-W29 | I12: 2026-W30 | J12: V25-PCH-010 | K12: 未开始 | L12: 【目标】重构Schema缓存实现，优化缓存键计算性能，添加缓存统计。 【运行命令】npm test -- --grep 'SchemaCache' && npm run lint 【源文件路径】src/harness/prompt-cache/schemaCache.ts | M12: 重构完成，测试通过，lint通过
A13: V25-PCH-012 | B13: 工具Schema两层缓存 - 验收 | C13: Acceptance验收 | D13: Prompt Cache Harness | E13: P0 | F13: AI工程师 | G13: 2 | H13: 2026-W29 | I13: 2026-W30 | J13: V25-PCH-011 | K13: 未开始 | L13: 【目标】验收Schema两层缓存，确认同名不同schema工具不会混淆。 【运行命令】npm test -- --grep 'SchemaCache' 【验收检查项】1. 同名工具不同schema正确区分 2. TTL过期自动清理 3. 覆盖层正确应用 4. 缓存命中率>80% | M13: Schema缓存验收通过
A14: V25-PCH-013 | B14: Sticky-on Latch + TTL锁存 - 测试 | C14: Red测试 | D14: Prompt Cache Harness | E14: P0 | F14: AI工程师 | G14: 3 | H14: 2026-W29 | I14: 2026-W30 | K14: 未开始 | L14: 【目标】测试已启用beta功能Set只增不减（Sticky-on Latch），1h TTL锁存首次评估后锁存到bootstrap state整个会话不再变化。验证mid-session flip不会导致缓存失效（每个flip约50-70K token bust成本）。 【运行命令】npm test -- --grep 'StickyLatch' 【测试文件路径】src/harness/prompt-cache/__tests__/stickyLatch.test.ts 【测试用例清单】1. beta功能启用后加入Set，不可移除 2. 1h TTL首次评估后锁存 3. mid-session flip不触发缓存失效 4. 会话结束清理所有latch状态 5. 多个beta功能独立latch | M14: Sticky Latch和TTL锁存逻辑正确 | N14: 借鉴Claude Code：~50-70K token/flip bust成本
A15: V25-PCH-014 | B15: Sticky-on Latch + TTL锁存 - 实现 | C15: Green实现 | D15: Prompt Cache Harness | E15: P0 | F15: AI工程师 | G15: 4 | H15: 2026-W29 | I15: 2026-W30 | J15: V25-PCH-013 | K15: 未开始 | L15: 【目标】实现Sticky-on Latch机制：使用Set<string>记录已启用beta功能，会话内只增不减。实现1h TTL锁存：用户配额资格首次评估后锁存到bootstrap state，TTL=3600000ms。 【运行命令】npm test -- --grep 'StickyLatch' 【实现步骤】1. 创建src/harness/prompt-cache/stickyLatch.ts 2. 实现StickyLatch类（add/has/clear方法） 3. 实现TTLLatch类（evaluate/lock/isLocked方法） 4. 集成到REPL循环 【源文件路径】src/harness/prompt-cache/stickyLatch.ts 【测试文件路径】src/harness/prompt-cache/__tests__/stickyLatch.test.ts | M15: Sticky Latch和TTL锁存正确实现
A16: V25-PCH-015 | B16: Sticky-on Latch + TTL锁存 - 重构 | C16: Refactor重构 | D16: Prompt Cache Harness | E16: P0 | F16: AI工程师 | G16: 2 | H16: 2026-W29 | I16: 2026-W30 | J16: V25-PCH-014 | K16: 未开始 | L16: 【目标】重构Latch实现，优化内存管理，添加latch状态监控。 【运行命令】npm test -- --grep 'StickyLatch' && npm run lint 【源文件路径】src/harness/prompt-cache/stickyLatch.ts | M16: 重构完成，测试和lint通过
A17: V25-PCH-016 | B17: Sticky-on Latch + TTL锁存 - 验收 | C17: Acceptance验收 | D17: Prompt Cache Harness | E17: P0 | F17: AI工程师 | G17: 2 | H17: 2026-W30 | I17: 2026-W31 | J17: V25-PCH-015 | K17: 未开始 | L17: 【目标】验收Sticky Latch和TTL锁存，确认mid-session不触发缓存失效。 【运行命令】npm test -- --grep 'StickyLatch' 【验收检查项】1. beta功能只增不减 2. TTL锁存正确工作 3. mid-session flip无缓存bust 4. 会话结束正确清理 | M17: Sticky Latch验收通过
A18: V25-PCH-017 | B18: cache_reference精确放置 - 测试 | C18: Red测试 | D18: Prompt Cache Harness | E18: P0 | F18: AI工程师 | G18: 2 | H18: 2026-W30 | I18: 2026-W31 | K18: 未开始 | L18: 【目标】测试每个请求只在最后一个消息放置cache_control marker，避免多marker导致KV缓存空间浪费（Mycroft的turn-to-turn驱逐策略会保护多余位置但永远不会恢复）。 【运行命令】npm test -- --grep 'CacheReference' 【测试文件路径】src/harness/prompt-cache/__tests__/cacheReference.test.ts 【测试用例清单】1. 只有最后一个消息有cache_control 2. 中间消息无cache_control marker 3. 单消息请求正确放置 4. 多消息请求只在最后放置 | M18: cache_reference精确放置逻辑正确
A19: V25-PCH-018 | B19: cache_reference精确放置 - 实现 | C19: Green实现 | D19: Prompt Cache Harness | E19: P0 | F19: AI工程师 | G19: 3 | H19: 2026-W30 | I19: 2026-W31 | J19: V25-PCH-017 | K19: 未开始 | L19: 【目标】实现cache_reference精确放置逻辑：在构建API请求时，遍历消息数组，只在最后一个消息添加cache_control: {type: 'ephemeral'} marker。 【运行命令】npm test -- --grep 'CacheReference' 【实现步骤】1. 创建src/harness/prompt-cache/cacheReference.ts 2. 实现placeCacheReference()函数 3. 集成到apiRequestBuilder.ts 【源文件路径】src/harness/prompt-cache/cacheReference.ts 【测试文件路径】src/harness/prompt-cache/__tests__/cacheReference.test.ts | M19: cache_reference只在最后消息放置
A20: V25-PCH-019 | B20: cache_reference精确放置 - 验收 | C20: Acceptance验收 | D20: Prompt Cache Harness | E20: P0 | F20: AI工程师 | G20: 2 | H20: 2026-W30 | I20: 2026-W31 | J20: V25-PCH-018 | K20: 未开始 | L20: 【目标】验收cache_reference精确放置功能。 【运行命令】npm test -- --grep 'CacheReference' 【验收检查项】1. 只在最后消息放置marker 2. KV缓存空间无浪费 3. 多轮对话缓存命中率正常 | M20: cache_reference验收通过
A21: V25-PCH-020 | B21: 缓存命中率监控 - 测试 | C21: Red测试 | D21: Prompt Cache Harness | E21: P0 | F21: 后端 | G21: 2 | H21: 2026-W30 | I21: 2026-W31 | K21: 未开始 | L21: 【目标】测试CacheMetrics接口：cacheCreationTokens、cacheReadTokens、hitRate、bustEvents。验证每次API请求后正确更新指标，hitRate计算准确。 【运行命令】npm test -- --grep 'CacheMetrics' 【测试文件路径】src/harness/prompt-cache/__tests__/cacheMetrics.test.ts 【测试用例清单】1. cacheCreationTokens正确累加 2. cacheReadTokens正确累加 3. hitRate=cacheReadTokens/(cacheCreationTokens+cacheReadTokens) 4. bustEvents正确记录 5. 指标可持久化到数据库 | M21: 缓存监控指标正确记录和计算
A22: V25-PCH-021 | B22: 缓存命中率监控 - 实现 | C22: Green实现 | D22: Prompt Cache Harness | E22: P0 | F22: 后端 | G22: 3 | H22: 2026-W30 | I22: 2026-W31 | J22: V25-PCH-020 | K22: 未开始 | L22: 【目标】实现CacheMetrics接口和监控服务：每次API请求后从响应头提取cache_creation和cache_read token数，计算hitRate，记录bustEvents。目标命中率>70%，单次bust<20K tokens。 【运行命令】npm test -- --grep 'CacheMetrics' 【实现步骤】1. 创建src/harness/prompt-cache/cacheMetrics.ts 2. 实现CacheMetricsCollector类 3. 实现指标持久化到prompt_cache_entries表 4. 添加Prometheus metrics暴露 【源文件路径】src/harness/prompt-cache/cacheMetrics.ts 【测试文件路径】src/harness/prompt-cache/__tests__/cacheMetrics.test.ts | M22: 缓存监控服务正确工作，指标可查询
A23: V25-PCH-022 | B23: 缓存命中率监控 - 验收 | C23: Acceptance验收 | D23: Prompt Cache Harness | E23: P0 | F23: 后端 | G23: 2 | H23: 2026-W30 | I23: 2026-W31 | J23: V25-PCH-021 | K23: 未开始 | L23: 【目标】验收缓存命中率监控，确认指标准确可查。 【运行命令】npm test -- --grep 'CacheMetrics' 【验收检查项】1. hitRate计算准确 2. bustEvents正确记录 3. 指标可查询和展示 4. Prometheus metrics正常暴露 | M23: 缓存监控验收通过，目标命中率>70%
A24: V25-PMH-001 | B24: Fail-closed一致性检查器 - 测试 | C24: Red测试 | D24: Permission Harness | E24: P0 | F24: AI工程师 | G24: 3 | H24: 2026-W27 | I24: 2026-W28 | K24: 未开始 | L24: 【目标】测试Fail-closed一致性检查器：所有异常情况默认shouldBlock:true。异常矩阵包括：分类器解析失败、API错误、用户中断、Transcript太长、工具参数异常。验证误报代价远低于漏报——用户可手动批准被阻止的操作。 【运行命令】npm test -- --grep 'FailClosedClassifier' 【测试文件路径】src/harness/permission/__tests__/failClosedClassifier.test.ts 【测试用例清单】1. 解析失败→shouldBlock:true 2. API错误→shouldBlock:true 3. 用户中断→shouldBlock:true 4. Transcript太长→shouldBlock:true 5. 工具参数异常→shouldBlock:true 6. 正常操作→shouldBlock:false | M24: 所有异常情况默认阻止，正常操作正确放行
A25: V25-PMH-002 | B25: Fail-closed一致性检查器 - 实现 | C25: Green实现 | D25: Permission Harness | E25: P0 | F25: AI工程师 | G25: 5 | H25: 2026-W27 | I25: 2026-W28 | J25: V25-PMH-001 | K25: 未开始 | L25: 【目标】实现Fail-closed一致性检查器：创建ConsistencyClassifier类，所有异常处理路径返回{shouldBlock:true, reason}。定义操作风险等级矩阵：批量删除章节/覆盖核心设定=高危需确认；自动续写/一致性检查/创建分支=低危自动放行。 【运行命令】npm test -- --grep 'FailClosedClassifier' 【实现步骤】1. 创建src/harness/permission/failClosedClassifier.ts 2. 实现classify()方法及异常处理矩阵 3. 定义操作风险等级 4. 集成到REPL循环的Permission预检点 【源文件路径】src/harness/permission/failClosedClassifier.ts 【测试文件路径】src/harness/permission/__tests__/failClosedClassifier.test.ts | M25: Fail-closed检查器正确实现
A26: V25-PMH-003 | B26: Fail-closed一致性检查器 - 重构 | C26: Refactor重构 | D26: Permission Harness | E26: P0 | F26: AI工程师 | G26: 2 | H26: 2026-W28 | I26: 2026-W29 | J26: V25-PMH-002 | K26: 未开始 | L26: 【目标】重构一致性检查器，优化异常处理路径，提取风险等级配置为独立模块。 【运行命令】npm test -- --grep 'FailClosedClassifier' && npm run lint 【源文件路径】src/harness/permission/failClosedClassifier.ts | M26: 重构完成，测试和lint通过
A27: V25-PMH-004 | B27: Fail-closed一致性检查器 - 验收 | C27: Acceptance验收 | D27: Permission Harness | E27: P0 | F27: AI工程师 | G27: 2 | H27: 2026-W28 | I27: 2026-W29 | J27: V25-PMH-003 | K27: 未开始 | L27: 【目标】验收Fail-closed一致性检查器，确认安全默认行为。 【运行命令】npm test -- --grep 'FailClosedClassifier' 【验收检查项】1. 所有异常路径返回shouldBlock:true 2. 正常操作正确分类 3. 风险等级矩阵准确 4. 误报可通过手动批准解决 | M27: Fail-closed检查器验收通过
A28: V25-PMH-005 | B28: 两阶段XML分类器 - 测试 | C28: Red测试 | D28: Permission Harness | E28: P0 | F28: AI工程师 | G28: 4 | H28: 2026-W27 | I28: 2026-W28 | K28: 未开始 | L28: 【目标】测试两阶段XML分类器：Stage1（64 tokens，<500ms P99）快速分类输出<allow/>或<block/>；Stage2（4096 tokens，<3s P99）仅block时触发完整推理。两阶段共享系统提示词，受益于prompt caching。验证alwaysOnThinking模型增加2048 token headroom。 【运行命令】npm test -- --grep 'TwoStageClassifier' 【测试文件路径】src/harness/permission/__tests__/twoStageClassifier.test.ts 【测试用例清单】1. Stage1安全操作→<allow/> 2. Stage1危险操作→<block/> 3. Stage1 block后触发Stage2 4. Stage2 P99<3s 5. Stage1 P99<500ms 6. 两阶段共享系统提示词 | M28: 两阶段分类器正确工作，性能达标 | N28: 借鉴Claude Code：adaptive thinking消耗过多token导致空响应
A29: V25-PMH-006 | B29: 两阶段XML分类器 - 实现 | C29: Green实现 | D29: Permission Harness | E29: P0 | F29: AI工程师 | G29: 6 | H29: 2026-W28 | I29: 2026-W29 | J29: V25-PMH-005 | K29: 未开始 | L29: 【目标】实现两阶段XML分类器：Stage1使用小模型快速判断（64 tokens输出），Stage2使用大模型完整推理（4096 tokens输出）。两阶段共享系统提示词以利用prompt caching。对alwaysOnThinking模型增加2048 token headroom防止max_tokens截断。 【运行命令】npm test -- --grep 'TwoStageClassifier' 【实现步骤】1. 创建src/harness/permission/twoStageClassifier.ts 2. 实现Stage1Classifier（快速分类） 3. 实现Stage2Classifier（完整推理） 4. 实现分类器协调器 5. 添加headroom逻辑 6. 集成到Permission Harness 【源文件路径】src/harness/permission/twoStageClassifier.ts 【测试文件路径】src/harness/permission/__tests__/twoStageClassifier.test.ts | M29: 两阶段分类器正确实现，性能达标
A30: V25-PMH-007 | B30: 两阶段XML分类器 - 重构 | C30: Refactor重构 | D30: Permission Harness | E30: P0 | F30: AI工程师 | G30: 3 | H30: 2026-W29 | I30: 2026-W30 | J30: V25-PMH-006 | K30: 未开始 | L30: 【目标】重构两阶段分类器，优化prompt模板，添加分类结果缓存。 【运行命令】npm test -- --grep 'TwoStageClassifier' && npm run lint 【源文件路径】src/harness/permission/twoStageClassifier.ts | M30: 重构完成，分类准确率和性能达标
A31: V25-PMH-008 | B31: 两阶段XML分类器 - 验收 | C31: Acceptance验收 | D31: Permission Harness | E31: P0 | F31: AI工程师 | G31: 2 | H31: 2026-W29 | I31: 2026-W30 | J31: V25-PMH-007 | K31: 未开始 | L31: 【目标】验收两阶段XML分类器，确认分类准确率和性能。 【运行命令】npm test -- --grep 'TwoStageClassifier' 【验收检查项】1. Stage1 P99<500ms 2. Stage2 P99<3s 3. 分类准确率>95% 4. 两阶段共享prompt cache 5. headroom机制正常工作 | M31: 两阶段分类器验收通过
A32: V25-PMH-009 | B32: 权限拒绝→tool_result反馈 - 测试 | C32: Red测试 | D32: Permission Harness | E32: P0 | F32: AI工程师 | G32: 3 | H32: 2026-W28 | I32: 2026-W29 | K32: 未开始 | L32: 【目标】测试权限拒绝→tool_result反馈完整链路：classifier.shouldBlock→reason→cancelAndAbort→tool_result content_block→模型收到反馈→自动调整写作策略。示例：AI尝试让角色使用尚未觉醒的能力→检测时间线冲突→反馈给AI→AI改用其他描写方式。 【运行命令】npm test -- --grep 'PermissionFeedback' 【测试文件路径】src/harness/permission/__tests__/permissionFeedback.test.ts 【测试用例清单】1. shouldBlock:true生成tool_result 2. tool_result包含拒绝原因 3. 模型收到反馈后调整策略 4. 反馈内容格式正确 5. 连续拒绝不会导致无限循环 | M32: 权限拒绝反馈链路正确工作
A33: V25-PMH-010 | B33: 权限拒绝→tool_result反馈 - 实现 | C33: Green实现 | D33: Permission Harness | E33: P0 | F33: AI工程师 | G33: 5 | H33: 2026-W29 | I33: 2026-W30 | J33: V25-PMH-009 | K33: 未开始 | L33: 【目标】实现权限拒绝→tool_result反馈机制：当classifier返回shouldBlock:true时，调用cancelAndAbort(feedback, undefined, contentBlocks)生成tool_result content_block，作为user message的一部分发回模型，让模型看到拒绝原因后自动调整行为。 【运行命令】npm test -- --grep 'PermissionFeedback' 【实现步骤】1. 创建src/harness/permission/permissionFeedback.ts 2. 实现buildToolResultFeedback()函数 3. 实现cancelAndAbort()函数 4. 集成到REPL query loop 5. 添加最大重试次数限制 【源文件路径】src/harness/permission/permissionFeedback.ts 【测试文件路径】src/harness/permission/__tests__/permissionFeedback.test.ts | M33: 权限拒绝反馈机制正确实现
A34: V25-PMH-011 | B34: 权限拒绝→tool_result反馈 - 重构 | C34: Refactor重构 | D34: Permission Harness | E34: P0 | F34: AI工程师 | G34: 2 | H34: 2026-W29 | I34: 2026-W30 | J34: V25-PMH-010 | K34: 未开始 | L34: 【目标】重构权限反馈机制，优化反馈内容格式，添加反馈历史记录。 【运行命令】npm test -- --grep 'PermissionFeedback' && npm run lint 【源文件路径】src/harness/permission/permissionFeedback.ts | M34: 重构完成，反馈格式清晰
A35: V25-PMH-012 | B35: 权限拒绝→tool_result反馈 - 验收 | C35: Acceptance验收 | D35: Permission Harness | E35: P0 | F35: AI工程师 | G35: 2 | H35: 2026-W30 | I35: 2026-W31 | J35: V25-PMH-011 | K35: 未开始 | L35: 【目标】验收权限拒绝反馈机制，确认AI能根据反馈自动调整。 【运行命令】npm test -- --grep 'PermissionFeedback' 【验收检查项】1. 拒绝反馈正确生成 2. 模型能理解反馈内容 3. AI自动调整策略 4. 无无限循环 5. 反馈记录可审计 | M35: 权限反馈机制验收通过
A36: V25-PMH-013 | B36: 多竞态者模式 - 测试 | C36: Red测试 | D36: Permission Harness | E36: P0 | F36: AI工程师 | G36: 3 | H36: 2026-W29 | I36: 2026-W30 | K36: 未开始 | L36: 【目标】测试多竞态者模式：最多5个竞态者解决同一权限请求（用户交互、Web响应、Channel中继、权限hooks、一致性分类器）。第一个claim()成功的胜出，所有竞态者超时则deny。验证竞态安全和超时处理。 【运行命令】npm test -- --grep 'MultiRacer' 【测试文件路径】src/harness/permission/__tests__/multiRacer.test.ts 【测试用例清单】1. 第一个claim()成功胜出 2. 其他竞态者收到rejected通知 3. 所有竞态者超时→deny 4. 并发claim()无竞态条件 5. 竞态者可动态注册/注销 | M36: 多竞态者模式正确工作，无竞态条件
A37: V25-PMH-014 | B37: 多竞态者模式 - 实现 | C37: Green实现 | D37: Permission Harness | E37: P0 | F37: AI工程师 | G37: 5 | H37: 2026-W30 | I37: 2026-W31 | J37: V25-PMH-013 | K37: 未开始 | L37: 【目标】实现多竞态者模式：创建PermissionRacer类，支持注册最多5个竞态者（UserInteractionRacer、WebResponseRacer、ChannelRelayRacer、HookRacer、ClassifierRacer）。使用Promise.race()实现第一个claim()胜出，超时后默认deny。 【运行命令】npm test -- --grep 'MultiRacer' 【实现步骤】1. 创建src/harness/permission/multiRacer.ts 2. 实现PermissionRacer类 3. 实现5个内置竞态者 4. 实现claim()/reject()/timeout逻辑 5. 集成到Permission Harness 【源文件路径】src/harness/permission/multiRacer.ts 【测试文件路径】src/harness/permission/__tests__/multiRacer.test.ts | M37: 多竞态者模式正确实现
A38: V25-PMH-015 | B38: 多竞态者模式 - 验收 | C38: Acceptance验收 | D38: Permission Harness | E38: P0 | F38: AI工程师 | G38: 2 | H38: 2026-W30 | I38: 2026-W31 | J38: V25-PMH-014 | K38: 未开始 | L38: 【目标】验收多竞态者模式，确认竞态安全和超时处理。 【运行命令】npm test -- --grep 'MultiRacer' 【验收检查项】1. 竞态安全无数据竞争 2. 超时正确处理 3. 5个竞态者可同时工作 4. 胜出者正确记录到审计日志 | M38: 多竞态者模式验收通过
A39: V25-PMH-016 | B39: 危险权限剥离与恢复 - 测试 | C39: Red测试 | D39: Permission Harness | E39: P0 | F39: AI工程师 | G39: 2 | H39: 2026-W30 | I39: 2026-W31 | K39: 未开始 | L39: 【目标】测试进入自动模式时剥离危险权限（batchDeleteChapters、overwriteCoreSettings、modifyPublishedContent等），退出自动模式时恢复原始权限。验证剥离和恢复的完整性。 【运行命令】npm test -- --grep 'DangerousPermission' 【测试文件路径】src/harness/permission/__tests__/dangerousPermission.test.ts 【测试用例清单】1. 进入自动模式→危险权限被剥离 2. 自动模式下尝试危险操作→被阻止 3. 退出自动模式→原始权限恢复 4. 剥离/恢复不影响非危险权限 5. 剥离状态可查询 | M39: 危险权限剥离与恢复正确工作
A40: V25-PMH-017 | B40: 危险权限剥离与恢复 - 实现 | C40: Green实现 | D40: Permission Harness | E40: P0 | F40: AI工程师 | G40: 3 | H40: 2026-W30 | I40: 2026-W31 | J40: V25-PMH-016 | K40: 未开始 | L40: 【目标】实现危险权限剥离与恢复机制：定义DANGEROUS_PERMISSIONS集合（batchDeleteChapters、overwriteCoreSettings、modifyPublishedContent等），进入自动模式时从权限列表中临时移除，退出时恢复。使用栈结构支持嵌套模式切换。 【运行命令】npm test -- --grep 'DangerousPermission' 【实现步骤】1. 创建src/harness/permission/dangerousPermission.ts 2. 定义DANGEROUS_PERMISSIONS集合 3. 实现stripPermissions()/restorePermissions() 4. 集成到模式切换逻辑 【源文件路径】src/harness/permission/dangerousPermission.ts 【测试文件路径】src/harness/permission/__tests__/dangerousPermission.test.ts | M40: 危险权限剥离与恢复正确实现
A41: V25-PMH-018 | B41: 危险权限剥离与恢复 - 验收 | C41: Acceptance验收 | D41: Permission Harness | E41: P0 | F41: AI工程师 | G41: 2 | H41: 2026-W30 | I41: 2026-W31 | J41: V25-PMH-017 | K41: 未开始 | L41: 【目标】验收危险权限剥离与恢复功能。 【运行命令】npm test -- --grep 'DangerousPermission' 【验收检查项】1. 自动模式下危险操作被阻止 2. 退出后权限完整恢复 3. 嵌套模式切换正确处理 4. 不影响非危险权限 | M41: 危险权限剥离验收通过
A42: V25-PMH-019 | B42: Transcript JSONL格式安全 - 测试 | C42: Red测试 | D42: Permission Harness | E42: P0 | F42: 安全工程师 | G42: 2 | H42: 2026-W30 | I42: 2026-W31 | K42: 未开始 | L42: 【目标】测试Transcript使用JSONL格式（每行一个JSON对象），JSON转义确保换行符被转义为\n，防止prompt注入。操作历史格式：{"Write":{...}}、{"Edit":{...}}、{"ConsistencyCheck":{...}}。验证恶意构造的输入无法逃逸JSON字符串上下文。 【运行命令】npm test -- --grep 'TranscriptSecurity' 【测试文件路径】src/harness/permission/__tests__/transcriptSecurity.test.ts 【测试用例清单】1. 正常操作正确序列化为JSONL 2. 包含换行符的内容被正确转义 3. 恶意注入尝试被JSON转义阻止 4. 反序列化不会执行注入代码 5. 大量操作日志性能可接受 | M42: JSONL格式安全，无prompt注入风险 | N42: 借鉴Claude Code：防止伪造User:行操纵分类器
A43: V25-PMH-020 | B43: Transcript JSONL格式安全 - 实现 | C43: Green实现 | D43: Permission Harness | E43: P0 | F43: 安全工程师 | G43: 3 | H43: 2026-W30 | I43: 2026-W31 | J43: V25-PMH-019 | K43: 未开始 | L43: 【目标】实现Transcript JSONL格式安全：创建TranscriptLogger类，所有操作记录使用JSON.stringify序列化为JSONL格式。添加输入验证和输出转义，确保恶意内容无法逃逸JSON上下文。 【运行命令】npm test -- --grep 'TranscriptSecurity' 【实现步骤】1. 创建src/harness/permission/transcriptSecurity.ts 2. 实现TranscriptLogger类 3. 实现JSONL序列化/反序列化 4. 添加输入验证 5. 集成到Permission Harness 【源文件路径】src/harness/permission/transcriptSecurity.ts 【测试文件路径】src/harness/permission/__tests__/transcriptSecurity.test.ts | M43: JSONL Transcript安全实现完成
A44: V25-PMH-021 | B44: Transcript JSONL格式安全 - 验收 | C44: Acceptance验收 | D44: Permission Harness | E44: P0 | F44: 安全工程师 | G44: 2 | H44: 2026-W31 | I44: 2026-W32 | J44: V25-PMH-020 | K44: 未开始 | L44: 【目标】验收JSONL Transcript安全，进行安全渗透测试。 【运行命令】npm test -- --grep 'TranscriptSecurity' 【验收检查项】1. 所有注入尝试被阻止 2. JSONL格式正确 3. 性能满足要求 4. 安全审计通过 | M44: Transcript安全验收通过
A45: V25-PMH-022 | B45: 复合操作死规则清理 - 测试 | C45: Red测试 | D45: Permission Harness | E45: P0 | F45: AI工程师 | G45: 2 | H45: 2026-W31 | I45: 2026-W32 | K45: 未开始 | L45: 【目标】测试自动检测并清理永远不会再次匹配的过时权限规则：从未匹配且超过30天的规则自动清理，超过90天未匹配的规则自动清理。借鉴Claude Code GH#11380：用户累积150+死规则问题。 【运行命令】npm test -- --grep 'DeadRuleCleaner' 【测试文件路径】src/harness/permission/__tests__/deadRuleCleaner.test.ts 【测试用例清单】1. 从未匹配+30天→标记清理 2. 90天未匹配→标记清理 3. 最近匹配过的规则保留 4. 清理操作可撤销 5. 清理统计正确报告 | M45: 死规则清理逻辑正确 | N45: 借鉴GH#11380：150+死规则累积
A46: V25-PMH-023 | B46: 复合操作死规则清理 - 实现 | C46: Green实现 | D46: Permission Harness | E46: P0 | F46: AI工程师 | G46: 3 | H46: 2026-W31 | I46: 2026-W32 | J46: V25-PMH-022 | K46: 未开始 | L46: 【目标】实现死规则清理器：创建DeadRuleCleaner类，扫描权限规则表，识别从未匹配且超过30天或超过90天未匹配的规则，标记为待清理。提供手动确认和自动清理两种模式。 【运行命令】npm test -- --grep 'DeadRuleCleaner' 【实现步骤】1. 创建src/harness/permission/deadRuleCleaner.ts 2. 实现规则扫描和匹配统计 3. 实现清理策略 4. 添加定时清理任务 5. 集成到Permission Harness 【源文件路径】src/harness/permission/deadRuleCleaner.ts 【测试文件路径】src/harness/permission/__tests__/deadRuleCleaner.test.ts | M46: 死规则清理器正确实现
A47: V25-PMH-024 | B47: 复合操作死规则清理 - 验收 | C47: Acceptance验收 | D47: Permission Harness | E47: P0 | F47: AI工程师 | G47: 2 | H47: 2026-W31 | I47: 2026-W32 | J47: V25-PMH-023 | K47: 未开始 | L47: 【目标】验收死规则清理功能。 【运行命令】npm test -- --grep 'DeadRuleCleaner' 【验收检查项】1. 30天/90天规则正确识别 2. 清理操作安全可撤销 3. 清理统计准确 4. 不影响活跃规则 | M47: 死规则清理验收通过
A48: V25-CPH-001 | B48: 四级压缩决策引擎 - 测试 | C48: Red测试 | D48: Compaction Harness | E48: P1 | F48: AI工程师 | G48: 4 | H48: 2026-W30 | I48: 2026-W31 | K48: 未开始 | L48: 【目标】测试四级压缩决策引擎：L1 Cached Microcompact（工具结果数量超阈值，零成本cache_edits）、L2 Time-based（距上次AI交互>60min清空旧工具结果）、L3 Session Memory Compact（用会话记忆替换旧消息，无API调用）、L4 Full Compact（API调用生成摘要，高成本）。验证选择逻辑优先级。 【运行命令】npm test -- --grep 'CompactionEngine' 【测试文件路径】src/harness/compaction/__tests__/compactionEngine.test.ts 【测试用例清单】1. 工具结果超阈值→L1 2. >60min无交互→L2 3. autoCompact阈值+记忆非空→L3 4. L3不可用→L4 5. L2触发时重置L1状态 6. L4失败触发熔断器 | M48: 四级压缩选择逻辑正确
A49: V25-CPH-002 | B49: 四级压缩决策引擎 - 实现 | C49: Green实现 | D49: Compaction Harness | E49: P1 | F49: AI工程师 | G49: 8 | H49: 2026-W30 | I49: 2026-W31 | J49: V25-CPH-001 | K49: 未开始 | L49: 【目标】实现四级压缩决策引擎：创建CompactionEngine类，实现microcompactMessages()和autoCompactIfNeeded()方法。L1使用cache_edits零成本压缩，L2清空旧工具结果，L3使用会话记忆文件内容替换旧消息，L4调用LLM生成摘要。 【运行命令】npm test -- --grep 'CompactionEngine' 【实现步骤】1. 创建src/harness/compaction/compactionEngine.ts 2. 实现L1 CachedMicrocompact 3. 实现L2 TimeBasedMicrocompact 4. 实现L3 SessionMemoryCompact 5. 实现L4 FullCompact 6. 实现决策引擎协调器 【源文件路径】src/harness/compaction/compactionEngine.ts 【测试文件路径】src/harness/compaction/__tests__/compactionEngine.test.ts | M49: 四级压缩引擎正确实现
A50: V25-CPH-003 | B50: 四级压缩决策引擎 - 重构 | C50: Refactor重构 | D50: Compaction Harness | E50: P1 | F50: AI工程师 | G50: 3 | H50: 2026-W31 | I50: 2026-W32 | J50: V25-CPH-002 | K50: 未开始 | L50: 【目标】重构压缩引擎，优化L1-L4选择逻辑，提取公共压缩接口。 【运行命令】npm test -- --grep 'CompactionEngine' && npm run lint 【源文件路径】src/harness/compaction/compactionEngine.ts | M50: 重构完成，测试和lint通过
A51: V25-CPH-004 | B51: 四级压缩决策引擎 - 验收 | C51: Acceptance验收 | D51: Compaction Harness | E51: P1 | F51: AI工程师 | G51: 2 | H51: 2026-W31 | I51: 2026-W32 | J51: V25-CPH-003 | K51: 未开始 | L51: 【目标】验收四级压缩引擎，确认压缩效果和成本控制。 【运行命令】npm test -- --grep 'CompactionEngine' 【验收检查项】1. L1零API成本 2. L2低API成本 3. L3无API调用 4. L4高成本但最后手段 5. 选择逻辑优先级正确 | M51: 四级压缩引擎验收通过
A52: V25-CPH-005 | B52: analysis+summary双块结构 - 测试 | C52: Red测试 | D52: Compaction Harness | E52: P1 | F52: AI工程师 | G52: 3 | H52: 2026-W31 | I52: 2026-W32 | K52: 未开始 | L52: 【目标】测试<analysis>草稿本+<summary>最终输出双块结构。analysis块用于提高摘要质量，summary块是最终输出。formatCompactSummary()在注入上下文前剥离analysis块。织梦笔9段摘要结构：核心梗概、主角状态、核心关系、主线进展、活跃伏笔、世界观要点、近期事件、风格备注、待解决问题。 【运行命令】npm test -- --grep 'DualBlockSummary' 【测试文件路径】src/harness/compaction/__tests__/dualBlockSummary.test.ts 【测试用例清单】1. analysis块正确生成 2. summary块包含9段结构 3. formatCompactSummary剥离analysis 4. 注入上下文只包含summary 5. 9段结构内容完整 | M52: 双块结构正确工作
A53: V25-CPH-006 | B53: analysis+summary双块结构 - 实现 | C53: Green实现 | D53: Compaction Harness | E53: P1 | F53: AI工程师 | G53: 5 | H53: 2026-W32 | I53: 2026-W33 | J53: V25-CPH-005 | K53: 未开始 | L53: 【目标】实现双块结构摘要：创建DualBlockSummarizer类，生成<analysis>草稿本和<summary>最终输出。实现formatCompactSummary()剥离analysis块。定义织梦笔9段摘要模板。 【运行命令】npm test -- --grep 'DualBlockSummary' 【实现步骤】1. 创建src/harness/compaction/dualBlockSummary.ts 2. 实现9段摘要模板 3. 实现analysis块生成 4. 实现summary块生成 5. 实现formatCompactSummary() 【源文件路径】src/harness/compaction/dualBlockSummary.ts 【测试文件路径】src/harness/compaction/__tests__/dualBlockSummary.test.ts | M53: 双块摘要结构正确实现
A54: V25-CPH-007 | B54: analysis+summary双块结构 - 验收 | C54: Acceptance验收 | D54: Compaction Harness | E54: P1 | F54: AI工程师 | G54: 2 | H54: 2026-W32 | I54: 2026-W33 | J54: V25-CPH-006 | K54: 未开始 | L54: 【目标】验收双块摘要结构。 【运行命令】npm test -- --grep 'DualBlockSummary' 【验收检查项】1. analysis块提高摘要质量 2. summary块9段结构完整 3. formatCompactSummary正确剥离 4. 注入上下文无analysis残留 | M54: 双块摘要验收通过
A55: V25-CPH-008 | B55: 熔断器 - 测试 | C55: Red测试 | D55: Compaction Harness | E55: P1 | F55: AI工程师 | G55: 2 | H55: 2026-W32 | I55: 2026-W33 | K55: 未开始 | L55: 【目标】测试压缩熔断器：MAX_CONSECUTIVE_AUTOCOMPACT_FAILURES=3，连续3次压缩失败后停止自动压缩并降级到L2 time-based microcompact。借鉴BQ数据：1279个会话50+连续失败，每天浪费约250K API调用。 【运行命令】npm test -- --grep 'CompactionCircuitBreaker' 【测试文件路径】src/harness/compaction/__tests__/circuitBreaker.test.ts 【测试用例清单】1. 连续3次失败→触发熔断 2. 熔断后降级到L2 3. 成功一次→重置计数器 4. 熔断状态可查询 5. 熔断恢复后自动重试 | M55: 熔断器正确工作 | N55: 借鉴BQ：1279会话50+失败，250K API/天浪费
A56: V25-CPH-009 | B56: 熔断器 - 实现 | C56: Green实现 | D56: Compaction Harness | E56: P1 | F56: AI工程师 | G56: 3 | H56: 2026-W32 | I56: 2026-W33 | J56: V25-CPH-008 | K56: 未开始 | L56: 【目标】实现压缩熔断器：创建CompactionCircuitBreaker类，跟踪连续失败次数，达到阈值(3)后切换到L2降级模式。成功时重置计数器。 【运行命令】npm test -- --grep 'CompactionCircuitBreaker' 【实现步骤】1. 创建src/harness/compaction/circuitBreaker.ts 2. 实现CircuitBreaker类 3. 集成到CompactionEngine 4. 添加熔断状态监控 【源文件路径】src/harness/compaction/circuitBreaker.ts 【测试文件路径】src/harness/compaction/__tests__/circuitBreaker.test.ts | M56: 熔断器正确实现
A57: V25-CPH-010 | B57: 熔断器 - 验收 | C57: Acceptance验收 | D57: Compaction Harness | E57: P1 | F57: AI工程师 | G57: 2 | H57: 2026-W32 | I57: 2026-W33 | J57: V25-CPH-009 | K57: 未开始 | L57: 【目标】验收熔断器功能。 【运行命令】npm test -- --grep 'CompactionCircuitBreaker' 【验收检查项】1. 3次连续失败触发熔断 2. 降级到L2模式 3. 成功重置计数器 4. 熔断状态正确上报 | M57: 熔断器验收通过
A58: V25-CPH-011 | B58: 工具结果大小限制 - 测试 | C58: Red测试 | D58: Compaction Harness | E58: P1 | F58: AI工程师 | G58: 2 | H58: 2026-W32 | I58: 2026-W33 | K58: 未开始 | L58: 【目标】测试工具结果大小限制：单结果50,000字符(DEFAULT_MAX_RESULT_SIZE_CHARS)，单消息200,000字符(MAX_PER_MESSAGE_CHARS)。超出限制时持久化到磁盘，模型收到截断预览+文件路径。 【运行命令】npm test -- --grep 'ResultSizeLimit' 【测试文件路径】src/harness/compaction/__tests__/resultSizeLimit.test.ts 【测试用例清单】1. 单结果<50K→完整返回 2. 单结果>50K→截断+文件路径 3. 单消息>200K→聚合截断 4. 磁盘持久化正确 5. 截断预览包含上下文 | M58: 工具结果大小限制正确工作
A59: V25-CPH-012 | B59: 工具结果大小限制 - 实现 | C59: Green实现 | D59: Compaction Harness | E59: P1 | F59: AI工程师 | G59: 3 | H59: 2026-W33 | I59: 2026-W34 | J59: V25-CPH-011 | K59: 未开始 | L59: 【目标】实现工具结果大小限制：创建ResultSizeLimiter类，检查单个工具结果和单消息聚合大小。超出时将完整结果持久化到磁盘，返回截断预览（前2000字符+...+文件路径）。 【运行命令】npm test -- --grep 'ResultSizeLimit' 【实现步骤】1. 创建src/harness/compaction/resultSizeLimit.ts 2. 实现truncateResult()方法 3. 实现persistToDisk()方法 4. 集成到Tool System 【源文件路径】src/harness/compaction/resultSizeLimit.ts 【测试文件路径】src/harness/compaction/__tests__/resultSizeLimit.test.ts | M59: 工具结果大小限制正确实现
A60: V25-CPH-013 | B60: 工具结果大小限制 - 验收 | C60: Acceptance验收 | D60: Compaction Harness | E60: P1 | F60: AI工程师 | G60: 2 | H60: 2026-W33 | I60: 2026-W34 | J60: V25-CPH-012 | K60: 未开始 | L60: 【目标】验收工具结果大小限制。 【运行命令】npm test -- --grep 'ResultSizeLimit' 【验收检查项】1. 50K单结果限制正确 2. 200K单消息限制正确 3. 磁盘持久化可恢复 4. 截断预览有意义 | M60: 工具结果大小限制验收通过
A61: V25-CPH-014 | B61: Context Collapse可逆压缩 - 测试 | C61: Red测试 | D61: Compaction Harness | E61: P1 | F61: AI工程师 | G61: 3 | H61: 2026-W33 | I61: 2026-W34 | K61: 未开始 | L61: 【目标】测试Context Collapse可逆压缩：使用UUID边界追踪(first_archived_msg_id/last_archived_msg_id)记录压缩范围，完整摘要保留，有序提交链(commit B可引用commit A的摘要)。用户可撤销某次压缩恢复被压缩的章节上下文。 【运行命令】npm test -- --grep 'ContextCollapse' 【测试文件路径】src/harness/compaction/__tests__/contextCollapse.test.ts 【测试用例清单】1. 压缩记录包含UUID边界 2. 完整摘要保留 3. 有序提交链正确 4. 撤销操作恢复原始消息 5. 部分撤销不影响后续提交 | M61: Context Collapse可逆压缩正确工作
A62: V25-CPH-015 | B62: Context Collapse可逆压缩 - 实现 | C62: Green实现 | D62: Compaction Harness | E62: P1 | F62: AI工程师 | G62: 5 | H62: 2026-W33 | I62: 2026-W34 | J62: V25-CPH-014 | K62: 未开始 | L62: 【目标】实现Context Collapse可逆压缩：创建ContextCollapseManager类，每次压缩生成ContextCollapseCommitEntry记录（collapseId、summaryContent、firstArchivedUuid、lastArchivedUuid）。实现undo()方法恢复指定压缩。 【运行命令】npm test -- --grep 'ContextCollapse' 【实现步骤】1. 创建src/harness/compaction/contextCollapse.ts 2. 实现collapse()方法 3. 实现undo()方法 4. 实现有序提交链 5. 持久化到compaction_records表 【源文件路径】src/harness/compaction/contextCollapse.ts 【测试文件路径】src/harness/compaction/__tests__/contextCollapse.test.ts | M62: Context Collapse可逆压缩正确实现
A63: V25-CPH-016 | B63: Context Collapse可逆压缩 - 验收 | C63: Acceptance验收 | D63: Compaction Harness | E63: P1 | F63: AI工程师 | G63: 2 | H63: 2026-W34 | I63: 2026-W35 | J63: V25-CPH-015 | K63: 未开始 | L63: 【目标】验收Context Collapse可逆压缩。 【运行命令】npm test -- --grep 'ContextCollapse' 【验收检查项】1. 压缩记录完整 2. 撤销恢复原始消息 3. 有序提交链正确 4. 数据库记录可查询 | M63: Context Collapse验收通过
A64: V25-CPH-017 | B64: 压缩Fork的Cache共享 - 测试 | C64: Red测试 | D64: Compaction Harness | E64: P1 | F64: AI工程师 | G64: 2 | H64: 2026-W34 | I64: 2026-W35 | K64: 未开始 | L64: 【目标】测试压缩请求默认使用forked agent复用主对话的缓存前缀，避免压缩操作bust主对话的缓存。借鉴Claude Code：false路径98% cache miss，消耗0.76%全舰队cache_creation。 【运行命令】npm test -- --grep 'CompactionFork' 【测试文件路径】src/harness/compaction/__tests__/compactionFork.test.ts 【测试用例清单】1. 压缩请求使用forked agent 2. 复用主对话缓存前缀 3. 压缩不bust主对话缓存 4. false路径回退正确 | M64: 压缩Fork正确共享缓存 | N64: 借鉴Claude Code：false路径98% miss
A65: V25-CPH-018 | B65: 压缩Fork的Cache共享 - 实现 | C65: Green实现 | D65: Compaction Harness | E65: P1 | F65: AI工程师 | G65: 3 | H65: 2026-W34 | I65: 2026-W35 | J65: V25-CPH-017 | K65: 未开始 | L65: 【目标】实现压缩Fork的Cache共享：在L4 Full Compact中使用forked agent模式，复用主对话的prompt cache前缀。false路径（fork失败）回退到独立请求。 【运行命令】npm test -- --grep 'CompactionFork' 【实现步骤】1. 创建src/harness/compaction/compactionFork.ts 2. 实现createCompactionFork()方法 3. 实现缓存前缀复用逻辑 4. 实现false路径回退 【源文件路径】src/harness/compaction/compactionFork.ts 【测试文件路径】src/harness/compaction/__tests__/compactionFork.test.ts | M65: 压缩Fork Cache共享正确实现
A66: V25-CPH-019 | B66: 压缩Fork的Cache共享 - 验收 | C66: Acceptance验收 | D66: Compaction Harness | E66: P1 | F66: AI工程师 | G66: 2 | H66: 2026-W34 | I66: 2026-W35 | J66: V25-CPH-018 | K66: 未开始 | L66: 【目标】验收压缩Fork Cache共享。 【运行命令】npm test -- --grep 'CompactionFork' 【验收检查项】1. forked agent正确复用缓存 2. 主对话缓存不受影响 3. false路径回退正常 | M66: 压缩Fork Cache共享验收通过
A67: V25-MMH-001 | B67: NOVEL.md双重截断 - 测试 | C67: Red测试 | D67: Memory Harness | E67: P1 | F67: AI工程师 | G67: 2 | H67: 2026-W30 | I67: 2026-W31 | K67: 未开始 | L67: 【目标】测试NOVEL.md双重截断：行数上限200行+字节上限25000字节。防止极端长行（Claude Code p100观测到197KB单行）绕过行数限制。验证截断时保留最重要的内容。 【运行命令】npm test -- --grep 'NovelMdTruncation' 【测试文件路径】src/harness/memory/__tests__/novelMdTruncation.test.ts 【测试用例清单】1. 行数>200→截断到200行 2. 字节>25000→截断到25000字节 3. 极端长单行（>100KB）被正确截断 4. 截断保留高优先级内容 5. 截断位置不破坏Markdown格式 | M67: 双重截断正确工作 | N67: 借鉴Claude Code：p100观测197KB单行
A68: V25-MMH-002 | B68: NOVEL.md双重截断 - 实现 | C68: Green实现 | D68: Memory Harness | E68: P1 | F68: AI工程师 | G68: 3 | H68: 2026-W30 | I68: 2026-W31 | J68: V25-MMH-001 | K68: 未开始 | L68: 【目标】实现NOVEL.md双重截断：创建NovelMdManager类，写入时同时检查行数(200)和字节数(25000)上限。超限时按优先级截断低重要性内容。 【运行命令】npm test -- --grep 'NovelMdTruncation' 【实现步骤】1. 创建src/harness/memory/novelMdManager.ts 2. 实现双重截断逻辑 3. 实现优先级排序 4. 集成到Memory Harness 【源文件路径】src/harness/memory/novelMdManager.ts 【测试文件路径】src/harness/memory/__tests__/novelMdTruncation.test.ts | M68: NOVEL.md双重截断正确实现
A69: V25-MMH-003 | B69: NOVEL.md双重截断 - 验收 | C69: Acceptance验收 | D69: Memory Harness | E69: P1 | F69: AI工程师 | G69: 2 | H69: 2026-W31 | I69: 2026-W32 | J69: V25-MMH-002 | K69: 未开始 | L69: 【目标】验收NOVEL.md双重截断。 【运行命令】npm test -- --grep 'NovelMdTruncation' 【验收检查项】1. 行数限制正确 2. 字节限制正确 3. 极端长行被截断 4. Markdown格式完整 | M69: NOVEL.md双重截断验收通过
A70: V25-MMH-004 | B70: 记忆老化警告 - 测试 | C70: Red测试 | D70: Memory Harness | E70: P1 | F70: AI工程师 | G70: 2 | H70: 2026-W31 | I70: 2026-W32 | K70: 未开始 | L70: 【目标】测试记忆老化警告：>1天的记忆附加<system-reminder>过期警告标签。防止过期角色设定/情节信息被AI断言为事实（Claude Code事故：过期file:line引用反而让过期声明显得更权威）。 【运行命令】npm test -- --grep 'MemoryAging' 【测试文件路径】src/harness/memory/__tests__/memoryAging.test.ts 【测试用例清单】1. <1天记忆无警告 2. >1天记忆附加过期警告 3. >7天记忆附加强烈过期警告 4. 警告格式正确 5. AI能理解警告并降低信任 | M70: 记忆老化警告正确工作 | N70: 借鉴Claude Code：过期file:line引用被断言为事实
A71: V25-MMH-005 | B71: 记忆老化警告 - 实现 | C71: Green实现 | D71: Memory Harness | E71: P1 | F71: AI工程师 | G71: 3 | H71: 2026-W31 | I71: 2026-W32 | J71: V25-MMH-004 | K71: 未开始 | L71: 【目标】实现记忆老化警告：创建MemoryAgingManager类，检查每条记忆的创建时间，>1天附加<system-reminder>注意：以下记忆可能已变更</system-reminder>，>7天附加强烈警告。 【运行命令】npm test -- --grep 'MemoryAging' 【实现步骤】1. 创建src/harness/memory/memoryAgingManager.ts 2. 实现checkAging()方法 3. 实现警告标签生成 4. 集成到Memory检索流程 【源文件路径】src/harness/memory/memoryAgingManager.ts 【测试文件路径】src/harness/memory/__tests__/memoryAging.test.ts | M71: 记忆老化警告正确实现
A72: V25-MMH-006 | B72: 记忆老化警告 - 验收 | C72: Acceptance验收 | D72: Memory Harness | E72: P1 | F72: AI工程师 | G72: 2 | H72: 2026-W31 | I72: 2026-W32 | J72: V25-MMH-005 | K72: 未开始 | L72: 【目标】验收记忆老化警告。 【运行命令】npm test -- --grep 'MemoryAging' 【验收检查项】1. 1天阈值正确 2. 7天强烈警告正确 3. 警告格式正确 4. AI正确处理警告 | M72: 记忆老化警告验收通过
A73: V25-MMH-007 | B73: 自动记忆提取Forked Agent - 测试 | C73: Red测试 | D73: Memory Harness | E73: P1 | F73: AI工程师 | G73: 4 | H73: 2026-W32 | I73: 2026-W33 | K73: 未开始 | L73: 【目标】测试Forked Agent模式自动提取记忆：互斥写入（主agent已写入记忆文件时后台提取器跳过该回合）、重叠合并（正在提取时到达的请求暂存stash，当前提取完成后执行尾部提取）、最大5回合限制、工具沙箱（Read/Grep/Glob无限制，Bash仅只读，Edit/Write仅限记忆目录内）。 【运行命令】npm test -- --grep 'ForkedMemoryExtractor' 【测试文件路径】src/harness/memory/__tests__/forkedMemoryExtractor.test.ts 【测试用例清单】1. 主agent已写入→跳过 2. 提取中到达请求→stash 3. 最大5回合限制 4. 工具沙箱限制正确 5. 提取结果写入记忆文件 | M73: Forked Agent记忆提取正确工作
A74: V25-MMH-008 | B74: 自动记忆提取Forked Agent - 实现 | C74: Green实现 | D74: Memory Harness | E74: P1 | F74: AI工程师 | G74: 6 | H74: 2026-W32 | I74: 2026-W33 | J74: V25-MMH-007 | K74: 未开始 | L74: 【目标】实现Forked Agent自动记忆提取：创建ForkedMemoryExtractor类，使用runForkedAgent创建完美分叉共享父对话prompt cache。实现互斥写入检查、stash队列、5回合限制、工具沙箱。 【运行命令】npm test -- --grep 'ForkedMemoryExtractor' 【实现步骤】1. 创建src/harness/memory/forkedMemoryExtractor.ts 2. 实现runForkedAgent包装 3. 实现互斥写入检查 4. 实现stash队列和尾部提取 5. 实现5回合限制 6. 实现工具沙箱 【源文件路径】src/harness/memory/forkedMemoryExtractor.ts 【测试文件路径】src/harness/memory/__tests__/forkedMemoryExtractor.test.ts | M74: Forked Agent记忆提取正确实现
A75: V25-MMH-009 | B75: 自动记忆提取Forked Agent - 重构 | C75: Refactor重构 | D75: Memory Harness | E75: P1 | F75: AI工程师 | G75: 2 | H75: 2026-W33 | I75: 2026-W34 | J75: V25-MMH-008 | K75: 未开始 | L75: 【目标】重构Forked Agent记忆提取，优化stash队列性能，添加提取质量评估。 【运行命令】npm test -- --grep 'ForkedMemoryExtractor' && npm run lint 【源文件路径】src/harness/memory/forkedMemoryExtractor.ts | M75: 重构完成，测试和lint通过
A76: V25-MMH-010 | B76: 自动记忆提取Forked Agent - 验收 | C76: Acceptance验收 | D76: Memory Harness | E76: P1 | F76: AI工程师 | G76: 2 | H76: 2026-W33 | I76: 2026-W34 | J76: V25-MMH-009 | K76: 未开始 | L76: 【目标】验收Forked Agent记忆提取。 【运行命令】npm test -- --grep 'ForkedMemoryExtractor' 【验收检查项】1. 互斥写入正确 2. stash队列正常 3. 5回合限制有效 4. 工具沙箱安全 5. 提取质量可接受 | M76: Forked Agent记忆提取验收通过
A77: V25-MMH-011 | B77: 记忆路径安全 - 测试 | C77: Red测试 | D77: Memory Harness | E77: P1 | F77: 安全工程师 | G77: 2 | H77: 2026-W33 | I77: 2026-W34 | K77: 未开始 | L77: 【目标】测试记忆路径安全：排除项目设置目录（.dreamweaver/settings.json），防止恶意项目设置autoMemoryDirectory指向敏感目录（如~/.ssh）获得静默写入权限。借鉴Claude Code：projectSettings被故意排除。 【运行命令】npm test -- --grep 'MemoryPathSecurity' 【测试文件路径】src/harness/memory/__tests__/memoryPathSecurity.test.ts 【测试用例清单】1. 记忆目录在项目内→允许 2. 记忆目录指向~/.ssh→拒绝 3. 记忆目录指向/etc→拒绝 4. 路径遍历攻击被阻止 5. 符号链接攻击被阻止 | M77: 记忆路径安全验证通过 | N77: 借鉴Claude Code：防止恶意仓库获取敏感目录写入
A78: V25-MMH-012 | B78: 记忆路径安全 - 实现 | C78: Green实现 | D78: Memory Harness | E78: P1 | F78: 安全工程师 | G78: 2 | H78: 2026-W33 | I78: 2026-W34 | J78: V25-MMH-011 | K78: 未开始 | L78: 【目标】实现记忆路径安全检查：创建MemoryPathValidator类，验证记忆目录路径。排除项目设置目录，阻止路径遍历和符号链接攻击。 【运行命令】npm test -- --grep 'MemoryPathSecurity' 【实现步骤】1. 创建src/harness/memory/memoryPathSecurity.ts 2. 实现路径验证 3. 实现路径遍历检测 4. 集成到Memory Harness 【源文件路径】src/harness/memory/memoryPathSecurity.ts 【测试文件路径】src/harness/memory/__tests__/memoryPathSecurity.test.ts | M78: 记忆路径安全正确实现
A79: V25-MMH-013 | B79: 记忆路径安全 - 验收 | C79: Acceptance验收 | D79: Memory Harness | E79: P1 | F79: 安全工程师 | G79: 2 | H79: 2026-W34 | I79: 2026-W35 | J79: V25-MMH-012 | K79: 未开始 | L79: 【目标】验收记忆路径安全。 【运行命令】npm test -- --grep 'MemoryPathSecurity' 【验收检查项】1. 敏感目录被阻止 2. 路径遍历被阻止 3. 符号链接被阻止 4. 安全审计通过 | M79: 记忆路径安全验收通过
A80: V25-CLH-001 | B80: 协调器最小权限 - 测试 | C80: Red测试 | D80: Collaboration Harness | E80: P1 | F80: AI工程师 | G80: 3 | H80: 2026-W34 | I80: 2026-W35 | K80: 未开始 | L80: 【目标】测试协调器只保留4个工具（TeamCreate、TeamDelete、SendMessage、SyntheticOutput），不能直接执行文件操作（Read/Write/Edit/Bash被禁止）。验证协调器核心职责是任务分配和结果汇总。 【运行命令】npm test -- --grep 'CoordinatorPermission' 【测试文件路径】src/harness/collaboration/__tests__/coordinatorPermission.test.ts 【测试用例清单】1. 协调器可使用TeamCreate 2. 协调器可使用TeamDelete 3. 协调器可使用SendMessage 4. 协调器可使用SyntheticOutput 5. 协调器不能使用Read/Write/Edit/Bash | M80: 协调器最小权限正确
A81: V25-CLH-002 | B81: 协调器最小权限 - 实现 | C81: Green实现 | D81: Collaboration Harness | E81: P1 | F81: AI工程师 | G81: 4 | H81: 2026-W34 | I81: 2026-W35 | J81: V25-CLH-001 | K81: 未开始 | L81: 【目标】实现协调器最小权限：定义COORDINATOR_ALLOWED_TOOLS集合（TeamCreate、TeamDelete、SendMessage、SyntheticOutput），在协调器模式下过滤工具列表。 【运行命令】npm test -- --grep 'CoordinatorPermission' 【实现步骤】1. 创建src/harness/collaboration/coordinatorPermission.ts 2. 定义允许工具集合 3. 实现工具过滤逻辑 4. 集成到协调器模式 【源文件路径】src/harness/collaboration/coordinatorPermission.ts 【测试文件路径】src/harness/collaboration/__tests__/coordinatorPermission.test.ts | M81: 协调器最小权限正确实现
A82: V25-CLH-003 | B82: 协调器最小权限 - 验收 | C82: Acceptance验收 | D82: Collaboration Harness | E82: P1 | F82: AI工程师 | G82: 2 | H82: 2026-W34 | I82: 2026-W35 | J82: V25-CLH-002 | K82: 未开始 | L82: 【目标】验收协调器最小权限。 【运行命令】npm test -- --grep 'CoordinatorPermission' 【验收检查项】1. 只有4个工具可用 2. 文件操作工具被禁止 3. 权限过滤不影响普通代理 | M82: 协调器最小权限验收通过
A83: V25-CLH-004 | B83: 三层权限过滤 - 测试 | C83: Red测试 | D83: Collaboration Harness | E83: P1 | F83: AI工程师 | G83: 3 | H83: 2026-W34 | I83: 2026-W35 | K83: 未开始 | L83: 【目标】测试三层权限过滤：第一层ALL_AGENT_DISALLOWED_TOOLS（TaskOutput、ExitPlanMode、AskUserQuestion、TaskStop、AgentTool），第二层ASYNC_AGENT_ALLOWED_TOOLS白名单，第三层COORDINATOR_MODE_ALLOWED_TOOLS。Plan mode优先级高于bypass permissions。 【运行命令】npm test -- --grep 'ThreeLayerPermission' 【测试文件路径】src/harness/collaboration/__tests__/threeLayerPermission.test.ts 【测试用例清单】1. 所有代理禁止TaskOutput 2. 异步代理白名单正确 3. 协调器工具列表正确 4. Plan mode优先级高于bypass 5. 子代理不继承父会话的--dangerously-skip-permissions | M83: 三层权限过滤正确工作
A84: V25-CLH-005 | B84: 三层权限过滤 - 实现 | C84: Green实现 | D84: Collaboration Harness | E84: P1 | F84: AI工程师 | G84: 5 | H84: 2026-W35 | I84: 2026-W36 | J84: V25-CLH-004 | K84: 未开始 | L84: 【目标】实现三层权限过滤：创建ThreeLayerPermissionFilter类，按层级过滤工具列表。第一层全局禁止，第二层异步代理白名单，第三层协调器模式。 【运行命令】npm test -- --grep 'ThreeLayerPermission' 【实现步骤】1. 创建src/harness/collaboration/threeLayerPermission.ts 2. 定义三层过滤规则 3. 实现filterTools()方法 4. 集成到代理系统 【源文件路径】src/harness/collaboration/threeLayerPermission.ts 【测试文件路径】src/harness/collaboration/__tests__/threeLayerPermission.test.ts | M84: 三层权限过滤正确实现
A85: V25-CLH-006 | B85: 三层权限过滤 - 验收 | C85: Acceptance验收 | D85: Collaboration Harness | E85: P1 | F85: AI工程师 | G85: 2 | H85: 2026-W35 | I85: 2026-W36 | J85: V25-CLH-005 | K85: 未开始 | L85: 【目标】验收三层权限过滤。 【运行命令】npm test -- --grep 'ThreeLayerPermission' 【验收检查项】1. 三层过滤正确 2. Plan mode优先级正确 3. 权限隔离完整 | M85: 三层权限过滤验收通过
A86: V25-CLH-007 | B86: FlushGate消息顺序保证 - 测试 | C86: Red测试 | D86: Collaboration Harness | E86: P1 | F86: 后端 | G86: 3 | H86: 2026-W35 | I86: 2026-W36 | K86: 未开始 | L86: 【目标】测试FlushGate消息顺序保证：初始历史flush期间实时消息必须排队等待，确保服务器按[history..., live...]顺序接收。Transport重建期间也启动FlushGate防止消息在旧epoch上静默丢失。 【运行命令】npm test -- --grep 'FlushGate' 【测试文件路径】src/harness/collaboration/__tests__/flushGate.test.ts 【测试用例清单】1. flush期间新消息排队 2. flush完成后排队消息按序发送 3. Transport重建启动FlushGate 4. 多个flush不互相干扰 5. 超时后安全释放 | M86: FlushGate消息顺序保证正确
A87: V25-CLH-008 | B87: FlushGate消息顺序保证 - 实现 | C87: Green实现 | D87: Collaboration Harness | E87: P1 | F87: 后端 | G87: 4 | H87: 2026-W35 | I87: 2026-W36 | J87: V25-CLH-007 | K87: 未开始 | L87: 【目标】实现FlushGate：创建FlushGate类，提供acquire()/release()方法。acquire()期间所有消息进入等待队列，release()后按FIFO顺序发送。 【运行命令】npm test -- --grep 'FlushGate' 【实现步骤】1. 创建src/harness/collaboration/flushGate.ts 2. 实现FlushGate类 3. 实现消息排队和有序释放 4. 集成到WebSocket连接管理 【源文件路径】src/harness/collaboration/flushGate.ts 【测试文件路径】src/harness/collaboration/__tests__/flushGate.test.ts | M87: FlushGate正确实现
A88: V25-CLH-009 | B88: FlushGate消息顺序保证 - 验收 | C88: Acceptance验收 | D88: Collaboration Harness | E88: P1 | F88: 后端 | G88: 2 | H88: 2026-W36 | I88: 2026-W37 | J88: V25-CLH-008 | K88: 未开始 | L88: 【目标】验收FlushGate。 【运行命令】npm test -- --grep 'FlushGate' 【验收检查项】1. 消息顺序保证 2. flush期间无消息丢失 3. Transport重建安全 4. 性能可接受 | M88: FlushGate验收通过
A89: V25-CLH-010 | B89: QueryGuard串行执行 - 测试 | C89: Red测试 | D89: Collaboration Harness | E89: P1 | F89: 后端 | G89: 3 | H89: 2026-W36 | I89: 2026-W37 | K89: 未开始 | L89: 【目标】测试QueryGuard三态状态机：idle→dispatching→running。Generation计数器解决异步取消竞态——被取消查询的finally块中end()调用因generation不匹配而被忽略。reserve()→tryStart()→end()流程。 【运行命令】npm test -- --grep 'QueryGuard' 【测试文件路径】src/harness/collaboration/__tests__/queryGuard.test.ts 【测试用例清单】1. idle→dispatching→running状态转换 2. reserve()在非idle时返回false 3. tryStart()返回generation 4. end(generation)匹配时→idle 5. end(generation)不匹配时→忽略 6. 并发reserve()只有一个成功 | M89: QueryGuard串行执行正确 | N89: 借鉴Claude Code：异步取消竞态防护
A90: V25-CLH-011 | B90: QueryGuard串行执行 - 实现 | C90: Green实现 | D90: Collaboration Harness | E90: P1 | F90: 后端 | G90: 4 | H90: 2026-W36 | I90: 2026-W37 | J90: V25-CLH-010 | K90: 未开始 | L90: 【目标】实现QueryGuard：创建QueryGuard类，维护_status和_generation。reserve()从idle→dispatching，tryStart()从dispatching→running并返回generation，end(generation)从running→idle（generation不匹配则忽略）。 【运行命令】npm test -- --grep 'QueryGuard' 【实现步骤】1. 创建src/harness/collaboration/queryGuard.ts 2. 实现三态状态机 3. 实现Generation计数器 4. 集成到REPL循环 【源文件路径】src/harness/collaboration/queryGuard.ts 【测试文件路径】src/harness/collaboration/__tests__/queryGuard.test.ts | M90: QueryGuard正确实现
A91: V25-CLH-012 | B91: QueryGuard串行执行 - 验收 | C91: Acceptance验收 | D91: Collaboration Harness | E91: P1 | F91: 后端 | G91: 2 | H91: 2026-W36 | I91: 2026-W37 | J91: V25-CLH-011 | K91: 未开始 | L91: 【目标】验收QueryGuard。 【运行命令】npm test -- --grep 'QueryGuard' 【验收检查项】1. 状态机转换正确 2. Generation竞态安全 3. 串行执行保证 4. 取消操作安全 | M91: QueryGuard验收通过
A92: V25-CLH-013 | B92: 非对称持久化 - 测试 | C92: Red测试 | D92: Collaboration Harness | E92: P1 | F92: 后端 | G92: 2 | H92: 2026-W36 | I92: 2026-W37 | K92: 未开始 | L92: 【目标】测试非对称持久化：用户消息同步写入（await）确保可恢复，AI生成异步写入（fire-and-forget）不阻塞响应。借鉴Claude Code事故：进程在用户按回车和API响应之间被杀死导致会话丢失。 【运行命令】npm test -- --grep 'AsymmetricPersistence' 【测试文件路径】src/harness/collaboration/__tests__/asymmetricPersistence.test.ts 【测试用例清单】1. 用户消息同步写入完成后再返回 2. AI消息异步写入不阻塞 3. 进程崩溃后用户消息可恢复 4. AI消息丢失不影响核心功能 5. 异步写入失败有重试 | M92: 非对称持久化正确工作 | N92: 借鉴Claude Code：进程杀死丢失会话
A93: V25-CLH-014 | B93: 非对称持久化 - 实现 | C93: Green实现 | D93: Collaboration Harness | E93: P1 | F93: 后端 | G93: 3 | H93: 2026-W37 | I93: 2026-W38 | J93: V25-CLH-013 | K93: 未开始 | L93: 【目标】实现非对称持久化：创建AsymmetricPersistenceManager类，用户消息使用await write()同步持久化，AI消息使用fire-and-forget write()异步持久化。 【运行命令】npm test -- --grep 'AsymmetricPersistence' 【实现步骤】1. 创建src/harness/collaboration/asymmetricPersistence.ts 2. 实现syncWrite()方法 3. 实现asyncWrite()方法 4. 添加重试和错误处理 5. 集成到REPL循环 【源文件路径】src/harness/collaboration/asymmetricPersistence.ts 【测试文件路径】src/harness/collaboration/__tests__/asymmetricPersistence.test.ts | M93: 非对称持久化正确实现
A94: V25-CLH-015 | B94: 非对称持久化 - 验收 | C94: Acceptance验收 | D94: Collaboration Harness | E94: P1 | F94: 后端 | G94: 2 | H94: 2026-W37 | I94: 2026-W38 | J94: V25-CLH-014 | K94: 未开始 | L94: 【目标】验收非对称持久化。 【运行命令】npm test -- --grep 'AsymmetricPersistence' 【验收检查项】1. 用户消息同步持久化 2. AI消息异步持久化 3. 崩溃恢复用户消息 4. 性能无明显影响 | M94: 非对称持久化验收通过
A95: V25-BLH-001 | B95: 四层Feature Gate框架 - 测试 | C95: Red测试 | D95: Build Harness | E95: P1 | F95: 后端 | G95: 4 | H95: 2026-W37 | I95: 2026-W38 | K95: 未开始 | L95: 【目标】测试四层Feature Gate体系：L1编译时DCE（feature()函数+Bun打包器--define常量折叠）、L2运行时GrowthBook tengu_*特性开关（A/B测试灰度发布）、L3环境变量DISABLE_*覆盖（开发调试紧急禁用）、L4 API Beta Headers（模型能力协商按模型启用功能）。 【运行命令】npm test -- --grep 'FeatureGate' 【测试文件路径】src/harness/build/__tests__/featureGate.test.ts 【测试用例清单】1. L1 feature()返回boolean 2. L2 GrowthBook正确读取 3. L3 DISABLE_*覆盖L2 4. L4 Beta Header正确协商 5. 层级优先级正确(L3>L2>L1) | M95: 四层Feature Gate正确工作
A96: V25-BLH-002 | B96: 四层Feature Gate框架 - 实现 | C96: Green实现 | D96: Build Harness | E96: P1 | F96: 后端 | G96: 6 | H96: 2026-W37 | I96: 2026-W38 | J96: V25-BLH-001 | K96: 未开始 | L96: 【目标】实现四层Feature Gate框架：创建FeatureGateManager类，实现feature()函数（L1）、GrowthBook集成（L2）、环境变量读取（L3）、Beta Header协商（L4）。层级优先级：L3>L2>L1。 【运行命令】npm test -- --grep 'FeatureGate' 【实现步骤】1. 创建src/harness/build/featureGate.ts 2. 实现feature()函数 3. 集成GrowthBook SDK 4. 实现环境变量覆盖 5. 实现Beta Header协商 6. 创建Bun打包配置 【源文件路径】src/harness/build/featureGate.ts 【测试文件路径】src/harness/build/__tests__/featureGate.test.ts | M96: 四层Feature Gate正确实现
A97: V25-BLH-003 | B97: 四层Feature Gate框架 - 重构 | C97: Refactor重构 | D97: Build Harness | E97: P1 | F97: 后端 | G97: 2 | H97: 2026-W38 | I97: 2026-W39 | J97: V25-BLH-002 | K97: 未开始 | L97: 【目标】重构Feature Gate框架，优化层级查找性能，添加Gate状态监控。 【运行命令】npm test -- --grep 'FeatureGate' && npm run lint 【源文件路径】src/harness/build/featureGate.ts | M97: 重构完成，测试和lint通过
A98: V25-BLH-004 | B98: 四层Feature Gate框架 - 验收 | C98: Acceptance验收 | D98: Build Harness | E98: P1 | F98: 后端 | G98: 2 | H98: 2026-W38 | I98: 2026-W39 | J98: V25-BLH-003 | K98: 未开始 | L98: 【目标】验收四层Feature Gate框架。 【运行命令】npm test -- --grep 'FeatureGate' 【验收检查项】1. 四层层级正确 2. 优先级正确 3. DCE在构建时生效 4. 运行时开关可动态切换 | M98: Feature Gate框架验收通过
A99: V25-BLH-005 | B99: Ant-only DCE - 测试 | C99: Red测试 | D99: Build Harness | E99: P1 | F99: 后端 | G99: 2 | H99: 2026-W38 | I99: 2026-W39 | K99: 未开始 | L99: 【目标】测试Ant-only DCE：process.env.BUILD_VARIANT==='internal'必须在每个调用点内联，不能提取为const。验证打包器能常量折叠消除分支，防止内部调试信息泄露到外部构建。 【运行命令】npm test -- --grep 'AntOnlyDCE' 【测试文件路径】src/harness/build/__tests__/antOnlyDCE.test.ts 【测试用例清单】1. 内联表达式正确DCE 2. 提取为const时DCE失败 3. 外部构建不包含内部代码 4. Bun打包器常量折叠正确 | M99: Ant-only DCE正确工作
A100: V25-BLH-006 | B100: Ant-only DCE - 实现 | C100: Green实现 | D100: Build Harness | E100: P1 | F100: 后端 | G100: 3 | H100: 2026-W38 | I100: 2026-W39 | J100: V25-BLH-005 | K100: 未开始 | L100: 【目标】实现Ant-only DCE模式：在Bun打包配置中添加--define 'process.env.BUILD_VARIANT="external"'，确保内部功能标记在每个调用点内联。 【运行命令】npm test -- --grep 'AntOnlyDCE' 【实现步骤】1. 更新bun.build.ts配置 2. 添加BUILD_VARIANT define 3. 验证内部代码被DCE 4. 添加构建时检查脚本 【源文件路径】scripts/build.ts 【测试文件路径】src/harness/build/__tests__/antOnlyDCE.test.ts | M100: Ant-only DCE正确实现
...

Sheet v2.3-Global
A1: 任务ID | B1: 任务名称 | C1: TDD阶段 | D1: 所属模块 | E1: 优先级 | F1: 负责角色 | G1: 预估工时 | H1: 开始周 | I1: 结束周 | J1: 前置依赖 | K1: 状态 | L1: 详细任务提示词 | M1: 验收标准 | N1: 备注
A2: V23-I18-001 | B2: react-i18next框架集成 - 测试 | C2: Red测试 | D2: 国际化与本地化 | E2: P0 | F2: 前端 | G2: 2 | H2: 2026-W26 | I2: 2026-W27 | K2: 未开始 | L2: 【目标】编写react-i18next框架集成的单元测试，验证国际化基础设施正确性。 【运行命令】npm test -- --grep 'i18n initialization' 【测试文件路径】src/i18n/__tests__/i18nProvider.test.tsx 【测试用例清单】 1. test_i18n_provider_renders_without_error：渲染I18nProvider组件不抛出异常 2. test_default_language_is_zh_cn：验证默认语言设置为zh-CN 3. test_switch_language_to_en：调用changeLanguage('en')后语言成功切换 4. test_load_translation_namespace：加载editor命名空间后翻译key可用 5. test_missing_key_fallback_behavior：访问不存在的翻译key时返回fallback值 6. test_language_persistence_in_storage：刷新页面后语言设置从localStorage持久化恢复 | M2: 6个i18n初始化测试全部通过，覆盖默认语言、切换、命名空间加载、fallback和持久化
A3: V23-I18-002 | B3: react-i18next框架集成 - 实现 | C3: Green实现 | D3: 国际化与本地化 | E3: P0 | F3: 前端 | G3: 4 | H3: 2026-W26 | I3: 2026-W27 | J3: V23-I18-001 | K3: 未开始 | L3: 【目标】实现react-i18next框架集成，搭建完整的国际化基础设施。 【运行命令】npm test -- --grep 'i18n initialization' 【实现步骤】 1. 安装依赖：npm install i18next react-i18next i18next-http-backend i18next-browser-languagedetector 2. 创建src/i18n/config.ts，配置zh-CN和en-US两种语言，默认zh-CN 3. 创建locales/zh-CN/和locales/en-US/目录结构 4. 定义命名空间：common、editor、writing、settings 5. 创建I18nProvider.tsx包装组件 6. 在App.tsx中集成I18nProvider 【源文件路径】src/i18n/config.ts, src/i18n/I18nProvider.tsx 【测试文件路径】src/i18n/__tests__/i18nProvider.test.tsx | M3: i18n框架集成完成，所有测试通过，支持中英文切换和命名空间加载
A4: V23-I18-003 | B4: react-i18next框架集成 - 重构 | C4: Refactor重构 | D4: 国际化与本地化 | E4: P0 | F4: 前端 | G4: 2 | H4: 2026-W26 | I4: 2026-W27 | J4: V23-I18-002 | K4: 未开始 | L4: 【目标】重构i18n代码，提取自定义hooks，增强类型安全和代码复用性。 【运行命令】npm test -- --grep 'i18n' 【实现步骤】 1. 创建src/i18n/hooks/useLanguage.ts，封装语言切换逻辑 2. 创建src/i18n/hooks/useTranslation.ts，封装翻译函数 3. 添加zh-CN.d.ts类型声明文件，为翻译key提供类型提示 4. 集成i18next类型插件实现编译时key校验 5. 实现翻译资源lazy loading机制 6. 添加语言切换过渡动画 【源文件路径】src/i18n/hooks/useLanguage.ts, src/i18n/hooks/useTranslation.ts 【测试文件路径】src/i18n/__tests__/i18nProvider.test.tsx | M4: i18n代码重构完成，hooks提取完成，类型安全增强，lazy loading生效
A5: V23-I18-004 | B5: react-i18next框架集成 - 验收 | C5: Acceptance验收 | D5: 国际化与本地化 | E5: P0 | F5: 前端 | G5: 1 | H5: 2026-W26 | I5: 2026-W27 | J5: V23-I18-003 | K5: 未开始 | L5: 【目标】验收react-i18next框架集成的完整性和正确性。 【验收检查项】 1. 应用启动默认显示中文界面 2. 点击语言切换按钮后界面完整切换为英文 3. 刷新页面后语言设置保持不变 4. 检查所有页面无硬编码中文字符串 5. 浏览器控制台无i18n相关警告 6. TypeScript编译无类型错误 【运行命令】npm run build && npm run test:e2e -- --grep 'i18n' | M5: i18n框架集成验收通过，中英文切换流畅，无硬编码和类型错误
A6: V23-I18-005 | B6: 双语UI实现 - 测试 | C6: Red测试 | D6: 国际化与本地化 | E6: P0 | F6: 前端 | G6: 3 | H6: 2026-W26 | I6: 2026-W27 | K6: 未开始 | L6: 【目标】编写双语UI组件的单元测试，确保所有界面元素支持中英文显示。 【运行命令】npm test -- --grep 'bilingual UI' 【测试文件路径】src/i18n/__tests__/bilingualUI.test.tsx 【测试用例清单】 1. test_sidebar_displays_zh_text：侧边栏在中文模式下显示中文文本 2. test_sidebar_displays_en_text：侧边栏在英文模式下显示英文文本 3. test_toolbar_displays_zh_text：工具栏在中文模式下显示中文文本 4. test_settings_page_displays_zh_text：设置页面在中文模式下显示中文文本 5. test_modal_displays_translated_text：弹窗组件显示对应语言的文本 6. test_empty_state_displays_translated_text：空状态组件显示对应语言提示 7. test_no_hardcoded_chinese_strings：扫描所有组件无硬编码中文字符串 | M6: 7个双语UI测试全部通过，覆盖侧边栏、工具栏、设置页、弹窗和空状态
A7: V23-I18-006 | B7: 双语UI实现 - 实现 | C7: Green实现 | D7: 国际化与本地化 | E7: P0 | F7: 前端 | G7: 5 | H7: 2026-W26 | I7: 2026-W27 | J7: V23-I18-005 | K7: 未开始 | L7: 【目标】实现所有UI组件的双语支持，完成中英文翻译资源文件。 【运行命令】npm test -- --grep 'bilingual UI' 【实现步骤】 1. 编写zh-CN/common.json，包含侧边栏、工具栏、设置、弹窗等通用UI文本 2. 编写en-US/common.json，对应英文翻译 3. 逐个替换Sidebar、Toolbar、Settings、Modal、EmptyState组件中的硬编码文本 4. 处理复数形式和变量插值（如{{count}}个文件） 5. 实现日期、数字、货币的本地化格式化 【源文件路径】src/i18n/locales/zh-CN/common.json, src/i18n/locales/en-US/common.json 【测试文件路径】src/i18n/__tests__/bilingualUI.test.tsx | M7: 双语UI实现完成，所有组件支持中英文切换，翻译资源完整
A8: V23-I18-007 | B8: 双语UI实现 - 重构 | C8: Refactor重构 | D8: 国际化与本地化 | E8: P0 | F8: 前端 | G8: 2 | H8: 2026-W26 | I8: 2026-W27 | J8: V23-I18-006 | K8: 未开始 | L8: 【目标】重构双语UI实现，优化翻译资源管理和组件国际化模式。 【运行命令】npm test -- --grep 'bilingual UI' 【实现步骤】 1. 按功能模块拆分翻译资源文件（common/editor/writing/settings） 2. 创建TransComponent工厂函数，统一国际化组件创建模式 3. 添加翻译key命名规范ESLint规则 4. 实现翻译覆盖率检查脚本 5. 优化语言切换时的UI过渡效果 【源文件路径】src/i18n/utils/TransComponent.ts 【测试文件路径】src/i18n/__tests__/bilingualUI.test.tsx | M8: 双语UI重构完成，翻译资源按模块拆分，国际化模式统一
A9: V23-I18-008 | B9: 双语UI实现 - 验收 | C9: Acceptance验收 | D9: 国际化与本地化 | E9: P0 | F9: 前端 | G9: 1 | H9: 2026-W26 | I9: 2026-W27 | J9: V23-I18-007 | K9: 未开始 | L9: 【目标】验收双语UI实现的完整性和一致性。 【验收检查项】 1. 所有页面在中文模式下显示完整中文 2. 所有页面在英文模式下显示完整英文 3. 无遗漏的未翻译文本 4. 翻译文本长度适配UI布局 5. 特殊字符和标点正确处理 6. 语言切换响应时间小于100ms 【运行命令】npm run test:e2e -- --grep 'bilingual' && npm run check:i18n-coverage | M9: 双语UI验收通过，所有页面中英文显示完整，布局适配良好
A10: V23-I18-009 | B10: 双语写作引擎 - 测试 | C10: Red测试 | D10: 国际化与本地化 | E10: P0 | F10: AI工程师 | G10: 3 | H10: 2026-W26 | I10: 2026-W27 | K10: 未开始 | L10: 【目标】编写双语写作引擎的测试用例，验证AI生成内容支持中英文。 【运行命令】npm test -- --grep 'bilingual writing engine' 【测试文件路径】src/ai/__tests__/bilingualEngine.test.ts 【测试用例清单】 1. test_generate_chinese_content：AI生成中文写作内容 2. test_generate_english_content：AI生成英文写作内容 3. test_mixed_language_prompt：混合语言prompt正确处理 4. test_writing_style_preservation_zh：中文写作风格保持 5. test_writing_style_preservation_en：英文写作风格保持 6. test_language_detection_accuracy：语言检测准确率>95% | M10: 6个双语写作引擎测试通过，覆盖中英文生成、风格保持和语言检测
A11: V23-I18-010 | B11: 双语写作引擎 - 实现 | C11: Green实现 | D11: 国际化与本地化 | E11: P0 | F11: AI工程师 | G11: 6 | H11: 2026-W26 | I11: 2026-W27 | J11: V23-I18-009 | K11: 未开始 | L11: 【目标】实现双语写作引擎，支持中英文AI内容生成和语言自动检测。 【运行命令】npm test -- --grep 'bilingual writing engine' 【实现步骤】 1. 创建src/ai/BilingualEngine.ts核心类 2. 实现语言检测模块，基于fasttext或自研模型 3. 集成中英文写作prompt模板 4. 实现写作风格参数化（正式/口语/文学等） 5. 添加语言特定的后处理管道 6. 与现有AI写作接口对接 【源文件路径】src/ai/BilingualEngine.ts 【测试文件路径】src/ai/__tests__/bilingualEngine.test.ts | M11: 双语写作引擎实现完成，支持中英文内容生成和自动语言检测
A12: V23-I18-011 | B12: 双语写作引擎 - 重构 | C12: Refactor重构 | D12: 国际化与本地化 | E12: P0 | F12: AI工程师 | G12: 3 | H12: 2026-W26 | I12: 2026-W27 | J12: V23-I18-010 | K12: 未开始 | L12: 【目标】重构双语写作引擎，优化性能和可维护性。 【运行命令】npm test -- --grep 'bilingual writing engine' 【实现步骤】 1. 提取LanguageDetector为独立服务 2. 实现prompt模板的国际化配置管理 3. 添加写作引擎的性能监控埋点 4. 优化语言检测缓存策略 5. 统一中英文输出格式规范 【源文件路径】src/ai/services/LanguageDetector.ts 【测试文件路径】src/ai/__tests__/bilingualEngine.test.ts | M12: 双语写作引擎重构完成，性能优化，代码结构清晰
A13: V23-I18-012 | B13: 双语写作引擎 - 验收 | C13: Acceptance验收 | D13: 国际化与本地化 | E13: P0 | F13: AI工程师 | G13: 2 | H13: 2026-W26 | I13: 2026-W27 | J13: V23-I18-011 | K13: 未开始 | L13: 【目标】验收双语写作引擎的功能和性能。 【验收检查项】 1. 中文写作生成质量达标 2. 英文写作生成质量达标 3. 语言检测准确率>95% 4. 混合语言输入正确处理 5. 写作风格参数生效 6. 生成延迟小于3秒 【运行命令】npm run test:e2e -- --grep 'bilingual engine' | M13: 双语写作引擎验收通过，中英文生成质量达标，语言检测准确
A14: V23-I18-013 | B14: AI双语路由 - 测试 | C14: Red测试 | D14: 国际化与本地化 | E14: P0 | F14: AI工程师 | G14: 2 | H14: 2026-W26 | I14: 2026-W27 | K14: 未开始 | L14: 【目标】编写AI双语路由的测试用例，验证请求正确路由到对应语言模型。 【运行命令】npm test -- --grep 'AI language router' 【测试文件路径】src/ai/__tests__/languageRouter.test.ts 【测试用例清单】 1. test_route_chinese_to_chinese_model：中文请求路由到中文模型 2. test_route_english_to_english_model：英文请求路由到英文模型 3. test_route_mixed_to_primary_model：混合语言路由到主语言模型 4. test_fallback_on_model_unavailable：模型不可用时fallback处理 5. test_route_caching：相同语言请求命中缓存 | M14: 5个AI双语路由测试通过，覆盖中英文路由、fallback和缓存
A15: V23-I18-014 | B15: AI双语路由 - 实现 | C15: Green实现 | D15: 国际化与本地化 | E15: P0 | F15: AI工程师 | G15: 4 | H15: 2026-W26 | I15: 2026-W27 | J15: V23-I18-013 | K15: 未开始 | L15: 【目标】实现AI双语路由，根据用户语言偏好自动选择对应语言模型。 【运行命令】npm test -- --grep 'AI language router' 【实现步骤】 1. 创建src/ai/LanguageRouter.ts路由核心 2. 实现基于用户语言偏好的模型选择策略 3. 配置中英文模型endpoint映射 4. 实现模型不可用时的fallback链 5. 添加路由决策缓存 6. 集成到现有AI请求管道 【源文件路径】src/ai/LanguageRouter.ts 【测试文件路径】src/ai/__tests__/languageRouter.test.ts | M15: AI双语路由实现完成，中英文请求正确路由到对应模型
A16: V23-I18-015 | B16: AI双语路由 - 验收 | C16: Acceptance验收 | D16: 国际化与本地化 | E16: P0 | F16: AI工程师 | G16: 2 | H16: 2026-W26 | I16: 2026-W27 | J16: V23-I18-014 | K16: 未开始 | L16: 【目标】验收AI双语路由的正确性和可靠性。 【验收检查项】 1. 中文用户请求路由到中文模型 2. 英文用户请求路由到英文模型 3. 模型故障时自动fallback 4. 路由延迟小于50ms 5. 路由决策日志完整 【运行命令】npm run test:e2e -- --grep 'language router' | M16: AI双语路由验收通过，路由正确，fallback可靠
A17: V23-I18-016 | B17: 本地化格式 - 测试 | C17: Red测试 | D17: 国际化与本地化 | E17: P0 | F17: 前端 | G17: 2 | H17: 2026-W26 | I17: 2026-W27 | K17: 未开始 | L17: 【目标】编写本地化格式测试，验证日期、数字、货币格式化正确性。 【运行命令】npm test -- --grep 'locale format' 【测试文件路径】src/i18n/__tests__/localeFormat.test.ts 【测试用例清单】 1. test_date_format_zh_cn：中文日期格式（2026年4月1日） 2. test_date_format_en_us：英文日期格式（April 1, 2026） 3. test_number_format_zh：中文数字格式（千分位） 4. test_currency_format_cny：人民币格式（¥1,234.56） 5. test_currency_format_usd：美元格式（$1,234.56） 6. test_relative_time_format：相对时间格式（3分钟前/3 min ago） | M17: 6个本地化格式测试通过，覆盖日期、数字、货币和相对时间
A18: V23-I18-017 | B18: 本地化格式 - 实现 | C18: Green实现 | D18: 国际化与本地化 | E18: P0 | F18: 前端 | G18: 3 | H18: 2026-W26 | I18: 2026-W27 | J18: V23-I18-016 | K18: 未开始 | L18: 【目标】实现本地化格式化工具，支持日期、数字、货币的国际化显示。 【运行命令】npm test -- --grep 'locale format' 【实现步骤】 1. 创建src/i18n/utils/localeFormat.ts 2. 基于Intl.DateTimeFormat实现日期格式化 3. 基于Intl.NumberFormat实现数字和货币格式化 4. 实现相对时间格式化（刚刚/N分钟前/N小时前） 5. 创建useLocaleFormat hook 6. 在UI组件中集成格式化工具 【源文件路径】src/i18n/utils/localeFormat.ts 【测试文件路径】src/i18n/__tests__/localeFormat.test.ts | M18: 本地化格式实现完成，日期、数字、货币格式化正确
A19: V23-I18-018 | B19: 本地化格式 - 验收 | C19: Acceptance验收 | D19: 国际化与本地化 | E19: P0 | F19: 前端 | G19: 1 | H19: 2026-W26 | I19: 2026-W27 | J19: V23-I18-017 | K19: 未开始 | L19: 【目标】验收本地化格式化的正确性和完整性。 【验收检查项】 1. 中文日期显示正确（年月日格式） 2. 英文日期显示正确（Month Day, Year格式） 3. 数字千分位分隔正确 4. 人民币和美元货币符号正确 5. 相对时间显示符合语言习惯 【运行命令】npm run test:e2e -- --grep 'locale format' | M19: 本地化格式验收通过，所有格式化输出符合中英文习惯
A20: V23-PAY-001 | B20: Stripe Checkout集成 - 测试 | C20: Red测试 | D20: 支付与订阅 | E20: P0 | F20: 全栈 | G20: 3 | H20: 2026-W26 | I20: 2026-W27 | K20: 未开始 | L20: 【目标】编写Stripe Checkout集成的测试用例，验证支付流程正确性。 【运行命令】npm test -- --grep 'Stripe Checkout' 【测试文件路径】src/payment/__tests__/stripeCheckout.test.ts 【测试用例清单】 1. test_create_checkout_session：创建Checkout Session成功 2. test_checkout_session_contains_correct_price：Session包含正确价格 3. test_checkout_session_contains_metadata：Session包含用户metadata 4. test_checkout_webhook_signature_verification：Webhook签名验证 5. test_handle_successful_payment：处理成功支付回调 6. test_handle_failed_payment：处理失败支付回调 | M20: 6个Stripe Checkout测试通过，覆盖Session创建、签名验证和支付回调
A21: V23-PAY-002 | B21: Stripe Checkout集成 - 实现 | C21: Green实现 | D21: 支付与订阅 | E21: P0 | F21: 全栈 | G21: 6 | H21: 2026-W26 | I21: 2026-W27 | J21: V23-PAY-001 | K21: 未开始 | L21: 【目标】实现Stripe Checkout集成，搭建完整的支付流程。 【运行命令】npm test -- --grep 'Stripe Checkout' 【实现步骤】 1. 安装stripe SDK：npm install stripe @stripe/stripe-js 2. 创建src/payment/stripe/client.ts客户端配置 3. 创建src/payment/stripe/checkout.ts Checkout Session管理 4. 实现POST /api/payments/create-checkout-session接口 5. 实现POST /api/payments/webhook Stripe Webhook处理 6. 配置Stripe环境变量和密钥管理 【源文件路径】src/payment/stripe/checkout.ts, src/payment/api/createCheckout.ts 【测试文件路径】src/payment/__tests__/stripeCheckout.test.ts | M21: Stripe Checkout集成完成，支付流程端到端可用
A22: V23-PAY-003 | B22: Stripe Checkout集成 - 重构 | C22: Refactor重构 | D22: 支付与订阅 | E22: P0 | F22: 全栈 | G22: 3 | H22: 2026-W26 | I22: 2026-W27 | J22: V23-PAY-002 | K22: 未开始 | L22: 【目标】重构Stripe Checkout代码，增强安全性和可维护性。 【运行命令】npm test -- --grep 'Stripe Checkout' 【实现步骤】 1. 提取StripeService统一服务层 2. 实现支付状态机管理（pending/succeeded/failed/canceled） 3. 添加支付请求限流和防重复提交 4. 实现Stripe密钥轮换机制 5. 添加支付流程的详细日志和监控埋点 【源文件路径】src/payment/services/StripeService.ts 【测试文件路径】src/payment/__tests__/stripeCheckout.test.ts | M22: Stripe Checkout重构完成，安全性和可维护性增强
A23: V23-PAY-004 | B23: Stripe Checkout集成 - 验收 | C23: Acceptance验收 | D23: 支付与订阅 | E23: P0 | F23: 全栈 | G23: 2 | H23: 2026-W26 | I23: 2026-W27 | J23: V23-PAY-003 | K23: 未开始 | L23: 【目标】验收Stripe Checkout集成的完整支付流程。 【验收检查项】 1. 创建Checkout Session成功跳转Stripe支付页 2. 支付成功后正确处理回调 3. 支付失败后正确处理错误 4. Webhook签名验证安全可靠 5. 支付状态正确更新到数据库 6. 测试模式和正式模式切换正常 【运行命令】npm run test:e2e -- --grep 'stripe checkout' | M23: Stripe Checkout验收通过，支付流程完整可靠
A24: V23-PAY-005 | B24: Stripe Billing订阅管理 - 测试 | C24: Red测试 | D24: 支付与订阅 | E24: P0 | F24: 全栈 | G24: 3 | H24: 2026-W26 | I24: 2026-W27 | K24: 未开始 | L24: 【目标】编写Stripe Billing订阅管理的测试用例。 【运行命令】npm test -- --grep 'Stripe Billing' 【测试文件路径】src/payment/__tests__/stripeBilling.test.ts 【测试用例清单】 1. test_create_subscription：创建订阅成功 2. test_cancel_subscription：取消订阅成功 3. test_upgrade_subscription：升级订阅计划成功 4. test_downgrade_subscription：降级订阅计划成功 5. test_handle_subscription_webhook：处理订阅事件Webhook 6. test_subscription_status_sync：订阅状态同步正确 | M24: 6个Stripe Billing测试通过，覆盖创建、取消、升降级和状态同步
A25: V23-PAY-006 | B25: Stripe Billing订阅管理 - 实现 | C25: Green实现 | D25: 支付与订阅 | E25: P0 | F25: 全栈 | G25: 6 | H25: 2026-W26 | I25: 2026-W27 | J25: V23-PAY-005 | K25: 未开始 | L25: 【目标】实现Stripe Billing订阅管理，支持订阅的完整生命周期。 【运行命令】npm test -- --grep 'Stripe Billing' 【实现步骤】 1. 在Stripe Dashboard创建产品和价格 2. 创建src/payment/stripe/billing.ts订阅管理 3. 实现POST /api/subscriptions/create创建订阅 4. 实现POST /api/subscriptions/cancel取消订阅 5. 实现POST /api/subscriptions/update变更订阅 6. 实现订阅事件Webhook处理（customer.subscription.*） 【源文件路径】src/payment/stripe/billing.ts, src/payment/api/subscriptions.ts 【测试文件路径】src/payment/__tests__/stripeBilling.test.ts | M25: Stripe Billing订阅管理实现完成，支持创建、取消、升降级
A26: V23-PAY-007 | B26: Stripe Billing订阅管理 - 重构 | C26: Refactor重构 | D26: 支付与订阅 | E26: P0 | F26: 全栈 | G26: 3 | H26: 2026-W26 | I26: 2026-W27 | J26: V23-PAY-006 | K26: 未开始 | L26: 【目标】重构Stripe Billing代码，优化订阅管理逻辑。 【运行命令】npm test -- --grep 'Stripe Billing' 【实现步骤】 1. 提取SubscriptionManager服务类 2. 实现订阅变更的proration计算和展示 3. 添加订阅状态变更通知（邮件/站内信） 4. 实现订阅过期前的自动提醒 5. 优化Webhook处理的幂等性 【源文件路径】src/payment/services/SubscriptionManager.ts 【测试文件路径】src/payment/__tests__/stripeBilling.test.ts | M26: Stripe Billing重构完成，订阅管理逻辑优化
A27: V23-PAY-008 | B27: Stripe Billing订阅管理 - 验收 | C27: Acceptance验收 | D27: 支付与订阅 | E27: P0 | F27: 全栈 | G27: 2 | H27: 2026-W26 | I27: 2026-W27 | J27: V23-PAY-007 | K27: 未开始 | L27: 【目标】验收Stripe Billing订阅管理的完整功能。 【验收检查项】 1. 新用户创建订阅成功 2. 取消订阅后状态正确更新 3. 升级订阅proration金额正确 4. 降级订阅在周期结束后生效 5. Webhook事件处理幂等 6. 订阅状态与Stripe Dashboard一致 【运行命令】npm run test:e2e -- --grep 'stripe billing' | M27: Stripe Billing订阅管理验收通过，订阅生命周期管理完整
A28: V23-PAY-009 | B28: 四级订阅计划实现 - 测试 | C28: Red测试 | D28: 支付与订阅 | E28: P0 | F28: 全栈 | G28: 3 | H28: 2026-W26 | I28: 2026-W27 | K28: 未开始 | L28: 【目标】编写四级订阅计划（Free/Basic/Pro/Enterprise）的测试用例。 【运行命令】npm test -- --grep 'subscription plans' 【测试文件路径】src/payment/__tests__/subscriptionPlans.test.ts 【测试用例清单】 1. test_free_plan_limits：Free计划限额正确 2. test_basic_plan_features：Basic计划功能可用 3. test_pro_plan_features：Pro计划功能可用 4. test_enterprise_plan_features：Enterprise计划功能可用 5. test_plan_feature_gating：功能门控正确 6. test_plan_upgrade_path：升级路径正确 | M28: 6个订阅计划测试通过，覆盖四级计划的功能和限额
A29: V23-PAY-010 | B29: 四级订阅计划实现 - 实现 | C29: Green实现 | D29: 支付与订阅 | E29: P0 | F29: 全栈 | G29: 6 | H29: 2026-W26 | I29: 2026-W27 | J29: V23-PAY-009 | K29: 未开始 | L29: 【目标】实现四级订阅计划，配置各计划的功能和限额。 【运行命令】npm test -- --grep 'subscription plans' 【实现步骤】 1. 定义计划配置：Free(免费)/Basic($9.99)/Pro($29.99)/Enterprise(定制) 2. 创建src/payment/plans/planConfig.ts计划配置 3. 实现src/payment/plans/FeatureGate.ts功能门控 4. 实现useSubscription hook获取当前计划信息 5. 实现useFeatureAccess hook检查功能访问权限 6. 在UI中集成计划选择和功能门控 【源文件路径】src/payment/plans/planConfig.ts, src/payment/plans/FeatureGate.ts 【测试文件路径】src/payment/__tests__/subscriptionPlans.test.ts | M29: 四级订阅计划实现完成，功能门控正确
A30: V23-PAY-011 | B30: 四级订阅计划实现 - 重构 | C30: Refactor重构 | D30: 支付与订阅 | E30: P0 | F30: 全栈 | G30: 3 | H30: 2026-W26 | I30: 2026-W27 | J30: V23-PAY-010 | K30: 未开始 | L30: 【目标】重构订阅计划代码，增强灵活性和可扩展性。 【运行命令】npm test -- --grep 'subscription plans' 【实现步骤】 1. 实现计划配置的JSON Schema验证 2. 创建PlanManager统一管理计划逻辑 3. 实现功能门控的缓存优化 4. 添加计划变更的审计日志 5. 支持自定义计划配置（Enterprise） 【源文件路径】src/payment/services/PlanManager.ts 【测试文件路径】src/payment/__tests__/subscriptionPlans.test.ts | M30: 订阅计划重构完成，配置灵活可扩展
A31: V23-PAY-012 | B31: 四级订阅计划实现 - 验收 | C31: Acceptance验收 | D31: 支付与订阅 | E31: P0 | F31: 全栈 | G31: 2 | H31: 2026-W26 | I31: 2026-W27 | J31: V23-PAY-011 | K31: 未开始 | L31: 【目标】验收四级订阅计划的功能和限额正确性。 【验收检查项】 1. Free计划限额正确（如每月1000字） 2. Basic计划功能正确解锁 3. Pro计划高级功能可用 4. Enterprise计划全部功能开放 5. 功能门控在各页面正确生效 6. 计划切换后功能即时更新 【运行命令】npm run test:e2e -- --grep 'subscription plans' | M31: 四级订阅计划验收通过，功能和限额配置正确
A32: V23-PAY-013 | B32: 用量计量与计费 - 测试 | C32: Red测试 | D32: 支付与订阅 | E32: P0 | F32: 后端 | G32: 3 | H32: 2026-W26 | I32: 2026-W27 | K32: 未开始 | L32: 【目标】编写用量计量与计费系统的测试用例。 【运行命令】npm test -- --grep 'usage metering' 【测试文件路径】src/payment/__tests__/usageMetering.test.ts 【测试用例清单】 1. test_record_usage_event：记录用量事件成功 2. test_aggregate_monthly_usage：月度用量聚合正确 3. test_check_usage_limit：限额检查正确 4. test_calculate_overage_fee：超额费用计算正确 5. test_usage_reset_on_billing_cycle：计费周期重置用量 6. test_concurrent_usage_handling：并发用量处理正确 | M32: 6个用量计量测试通过，覆盖记录、聚合、限额和计费
A33: V23-PAY-014 | B33: 用量计量与计费 - 实现 | C33: Green实现 | D33: 支付与订阅 | E33: P0 | F33: 后端 | G33: 6 | H33: 2026-W26 | I33: 2026-W27 | J33: V23-PAY-013 | K33: 未开始 | L33: 【目标】实现用量计量与计费系统，跟踪用户资源使用情况。 【运行命令】npm test -- --grep 'usage metering' 【实现步骤】 1. 创建src/payment/metering/UsageTracker.ts用量追踪 2. 定义计量维度：AI字数、存储空间、API调用次数 3. 实现Redis原子计数器记录实时用量 4. 创建src/payment/metering/BillingCalculator.ts费用计算 5. 实现超额用量自动计费 6. 实现计费周期自动重置 【源文件路径】src/payment/metering/UsageTracker.ts, src/payment/metering/BillingCalculator.ts 【测试文件路径】src/payment/__tests__/usageMetering.test.ts | M33: 用量计量与计费实现完成，支持多维度计量和超额计费
A34: V23-PAY-015 | B34: 用量计量与计费 - 重构 | C34: Refactor重构 | D34: 支付与订阅 | E34: P0 | F34: 后端 | G34: 3 | H34: 2026-W26 | I34: 2026-W27 | J34: V23-PAY-014 | K34: 未开始 | L34: 【目标】重构用量计量代码，优化性能和准确性。 【运行命令】npm test -- --grep 'usage metering' 【实现步骤】 1. 实现用量数据的批量写入优化 2. 添加用量数据的一致性校验 3. 实现用量异常检测和告警 4. 优化Redis缓存策略减少数据库写入 5. 添加用量历史数据归档 【源文件路径】src/payment/metering/UsageAggregator.ts 【测试文件路径】src/payment/__tests__/usageMetering.test.ts | M34: 用量计量重构完成，性能和准确性优化
A35: V23-PAY-016 | B35: 用量计量与计费 - 验收 | C35: Acceptance验收 | D35: 支付与订阅 | E35: P0 | F35: 后端 | G35: 2 | H35: 2026-W26 | I35: 2026-W27 | J35: V23-PAY-015 | K35: 未开始 | L35: 【目标】验收用量计量与计费系统的准确性。 【验收检查项】 1. 用量事件记录准确无丢失 2. 月度用量聚合数据正确 3. 限额检查实时生效 4. 超额费用计算准确 5. 计费周期重置正确 6. 并发场景下数据一致 【运行命令】npm run test:e2e -- --grep 'usage metering' | M35: 用量计量与计费验收通过，数据准确可靠
A36: V23-PAY-017 | B36: 优惠策略与退款 - 测试 | C36: Red测试 | D36: 支付与订阅 | E36: P0 | F36: 全栈 | G36: 2 | H36: 2026-W26 | I36: 2026-W27 | K36: 未开始 | L36: 【目标】编写优惠策略与退款的测试用例。 【运行命令】npm test -- --grep 'coupon refund' 【测试文件路径】src/payment/__tests__/couponRefund.test.ts 【测试用例清单】 1. test_apply_coupon_code：应用优惠码成功 2. test_coupon_percentage_discount：百分比折扣计算正确 3. test_coupon_fixed_discount：固定金额折扣计算正确 4. test_coupon_expiration：过期优惠码拒绝 5. test_process_refund：处理退款成功 6. test_partial_refund：部分退款金额正确 | M36: 6个优惠策略与退款测试通过，覆盖折扣和退款场景
A37: V23-PAY-018 | B37: 优惠策略与退款 - 实现 | C37: Green实现 | D37: 支付与订阅 | E37: P0 | F37: 全栈 | G37: 5 | H37: 2026-W26 | I37: 2026-W27 | J37: V23-PAY-017 | K37: 未开始 | L37: 【目标】实现优惠策略和退款功能。 【运行命令】npm test -- --grep 'coupon refund' 【实现步骤】 1. 创建src/payment/coupons/CouponService.ts优惠服务 2. 实现优惠码的创建、验证和使用 3. 支持百分比折扣和固定金额折扣 4. 实现优惠码使用次数限制和过期时间 5. 创建src/payment/refunds/RefundService.ts退款服务 6. 实现全额退款和部分退款 【源文件路径】src/payment/coupons/CouponService.ts, src/payment/refunds/RefundService.ts 【测试文件路径】src/payment/__tests__/couponRefund.test.ts | M37: 优惠策略与退款实现完成，支持折扣码和退款
A38: V23-PAY-019 | B38: 优惠策略与退款 - 验收 | C38: Acceptance验收 | D38: 支付与订阅 | E38: P0 | F38: 全栈 | G38: 2 | H38: 2026-W26 | I38: 2026-W27 | J38: V23-PAY-018 | K38: 未开始 | L38: 【目标】验收优惠策略和退款功能的正确性。 【验收检查项】 1. 有效优惠码正确应用折扣 2. 过期优惠码被拒绝 3. 百分比和固定折扣计算正确 4. 全额退款成功处理 5. 部分退款金额正确 6. 退款后订阅状态正确更新 【运行命令】npm run test:e2e -- --grep 'coupon refund' | M38: 优惠策略与退款验收通过，折扣和退款功能正确
A39: V23-PAY-020 | B39: Stripe Webhook处理 - 测试 | C39: Red测试 | D39: 支付与订阅 | E39: P0 | F39: 后端 | G39: 2 | H39: 2026-W26 | I39: 2026-W27 | K39: 未开始 | L39: 【目标】编写Stripe Webhook处理的测试用例。 【运行命令】npm test -- --grep 'stripe webhook' 【测试文件路径】src/payment/__tests__/stripeWebhook.test.ts 【测试用例清单】 1. test_verify_webhook_signature：Webhook签名验证通过 2. test_handle_payment_intent_succeeded：处理支付成功事件 3. test_handle_invoice_paid：处理发票支付事件 4. test_handle_customer_subscription_deleted：处理订阅取消事件 5. test_replay_webhook_idempotent：Webhook重放幂等处理 6. test_invalid_signature_rejected：无效签名被拒绝 | M39: 6个Stripe Webhook测试通过，覆盖签名验证和事件处理
A40: V23-PAY-021 | B40: Stripe Webhook处理 - 实现与验收 | C40: Green实现 | D40: 支付与订阅 | E40: P0 | F40: 后端 | G40: 5 | H40: 2026-W26 | I40: 2026-W27 | J40: V23-PAY-020 | K40: 未开始 | L40: 【目标】实现Stripe Webhook处理，确保所有支付事件正确处理。 【运行命令】npm test -- --grep 'stripe webhook' 【实现步骤】 1. 创建src/payment/webhook/WebhookHandler.ts 2. 实现签名验证中间件 3. 处理payment_intent.succeeded事件 4. 处理invoice.paid和invoice.payment_failed事件 5. 处理customer.subscription.*系列事件 6. 实现Webhook处理日志和重试机制 7. 添加Webhook端点健康检查 【验收检查项】 1. 所有支付事件正确处理 2. Webhook签名验证安全 3. 重放请求幂等处理 4. 处理失败自动重试 5. 日志完整可追踪 【源文件路径】src/payment/webhook/WebhookHandler.ts 【测试文件路径】src/payment/__tests__/stripeWebhook.test.ts | M40: Stripe Webhook处理实现并验收通过，事件处理完整可靠
A41: V23-DEP-001 | B41: AWS多区域部署 - 测试 | C41: Red测试 | D41: 全球部署 | E41: P0 | F41: DevOps | G41: 3 | H41: 2026-W26 | I41: 2026-W27 | K41: 未开始 | L41: 【目标】编写AWS多区域部署的基础设施测试。 【运行命令】cd infra && pytest tests/test_multi_region.py -v 【测试文件路径】infra/tests/test_multi_region.py 【测试用例清单】 1. test_vpc_created_in_target_region：目标区域VPC创建成功 2. test_ecs_cluster_deployed：ECS集群在多区域部署成功 3. test_ecr_image_replicated：Docker镜像跨区域复制成功 4. test_route53_health_check：Route53健康检查配置正确 5. test_iam_role_cross_region：跨区域IAM角色权限正确 | M41: 5个AWS多区域部署测试通过，覆盖VPC、ECS、镜像复制和健康检查
A42: V23-DEP-002 | B42: AWS多区域部署 - 实现 | C42: Green实现 | D42: 全球部署 | E42: P0 | F42: DevOps | G42: 8 | H42: 2026-W26 | I42: 2026-W27 | J42: V23-DEP-001 | K42: 未开始 | L42: 【目标】实现AWS多区域部署，在us-east-1、eu-west-1、ap-northeast-1三区域部署服务。 【运行命令】cd infra && terraform plan && terraform apply 【实现步骤】 1. 创建infra/aws/multi-region/main.tf多区域Terraform配置 2. 在三个区域创建VPC、子网和安全组 3. 配置ECS Fargate集群和任务定义 4. 设置ECR跨区域镜像复制 5. 配置Route53多区域健康检查 6. 实现CI/CD流水线的多区域部署步骤 【源文件路径】infra/aws/multi-region/main.tf, infra/aws/multi-region/variables.tf 【测试文件路径】infra/tests/test_multi_region.py | M42: AWS多区域部署实现完成，三个区域服务可用
A43: V23-DEP-003 | B43: AWS多区域部署 - 验收 | C43: Acceptance验收 | D43: 全球部署 | E43: P0 | F43: DevOps | G43: 3 | H43: 2026-W26 | I43: 2026-W27 | J43: V23-DEP-002 | K43: 未开始 | L43: 【目标】验收AWS多区域部署的可用性和连通性。 【验收检查项】 1. 三个区域服务均可访问 2. 区域间延迟小于200ms 3. 单区域故障时自动切换 4. 镜像同步延迟小于5分钟 5. 安全组规则正确 【运行命令】cd infra && pytest tests/test_multi_region.py -v && ./scripts/verify-deployment.sh | M43: AWS多区域部署验收通过，三区域服务可用，故障切换正常
A44: V23-DEP-004 | B44: CloudFront CDN配置 - 测试 | C44: Red测试 | D44: 全球部署 | E44: P0 | F44: DevOps | G44: 2 | H44: 2026-W26 | I44: 2026-W27 | K44: 未开始 | L44: 【目标】编写CloudFront CDN配置的测试用例。 【运行命令】cd infra && pytest tests/test_cloudfront.py -v 【测试文件路径】infra/tests/test_cloudfront.py 【测试用例清单】 1. test_cloudfront_distribution_created：CDN分发创建成功 2. test_origin_configured：源站配置正确 3. test_cache_behavior_static：静态资源缓存策略正确 4. test_cache_behavior_api：API缓存策略正确 5. test_ssl_certificate_attached：SSL证书附加成功 6. test_custom_domain_mapping：自定义域名映射正确 | M44: 6个CloudFront CDN测试通过，覆盖分发、缓存、SSL和域名
A45: V23-DEP-005 | B45: CloudFront CDN配置 - 实现 | C45: Green实现 | D45: 全球部署 | E45: P0 | F45: DevOps | G45: 6 | H45: 2026-W26 | I45: 2026-W27 | J45: V23-DEP-004 | K45: 未开始 | L45: 【目标】实现CloudFront CDN配置，加速全球静态资源和API访问。 【运行命令】cd infra && terraform plan && terraform apply 【实现步骤】 1. 创建infra/aws/cloudfront/main.tf CDN配置 2. 配置S3源站用于静态资源 3. 配置ALB源站用于API请求 4. 设置缓存行为：静态资源长缓存，API短缓存 5. 配置自定义错误页面 6. 附加ACM SSL证书 7. 配置自定义域名CNAME映射 【源文件路径】infra/aws/cloudfront/main.tf 【测试文件路径】infra/tests/test_cloudfront.py | M45: CloudFront CDN配置完成，静态资源和API加速生效
A46: V23-DEP-006 | B46: CloudFront CDN配置 - 验收 | C46: Acceptance验收 | D46: 全球部署 | E46: P0 | F46: DevOps | G46: 2 | H46: 2026-W26 | I46: 2026-W27 | J46: V23-DEP-005 | K46: 未开始 | L46: 【目标】验收CloudFront CDN配置的正确性和性能。 【验收检查项】 1. 静态资源通过CDN分发，缓存命中率>90% 2. API请求正确路由到源站 3. HTTPS访问正常，SSL证书有效 4. 自定义域名解析正确 5. 全球各区域访问延迟降低>50% 【运行命令】cd infra && pytest tests/test_cloudfront.py -v && ./scripts/verify-cdn.sh | M46: CloudFront CDN验收通过，全球加速效果显著
A47: V23-DEP-007 | B47: Cloudflare DNS延迟路由 - 测试 | C47: Red测试 | D47: 全球部署 | E47: P0 | F47: DevOps | G47: 2 | H47: 2026-W26 | I47: 2026-W27 | K47: 未开始 | L47: 【目标】编写Cloudflare DNS延迟路由的测试用例。 【运行命令】cd infra && pytest tests/test_cloudflare.py -v 【测试文件路径】infra/tests/test_cloudflare.py 【测试用例清单】 1. test_dns_record_created：DNS记录创建成功 2. test_latency_based_routing：延迟路由配置正确 3. test_geo_dns_resolution：地理位置DNS解析正确 4. test_health_check_probes：健康检查探测正常 5. test_failover_routing：故障转移路由正确 | M47: 5个Cloudflare DNS测试通过，覆盖延迟路由和故障转移
A48: V23-DEP-008 | B48: Cloudflare DNS延迟路由 - 实现 | C48: Green实现 | D48: 全球部署 | E48: P0 | F48: DevOps | G48: 5 | H48: 2026-W26 | I48: 2026-W27 | J48: V23-DEP-007 | K48: 未开始 | L48: 【目标】实现Cloudflare DNS延迟路由，将用户引导到最近的区域。 【运行命令】cd infra && python scripts/setup_cloudflare.py 【实现步骤】 1. 创建infra/cloudflare/dns.tf DNS配置 2. 配置三个区域的A记录指向各区域ALB 3. 启用Cloudflare延迟路由 4. 配置地理位置路由（亚洲/欧洲/美洲） 5. 设置健康检查探测各区域端点 6. 配置故障转移优先级 【源文件路径】infra/cloudflare/dns.tf, infra/cloudflare/variables.tf 【测试文件路径】infra/tests/test_cloudflare.py | M48: Cloudflare DNS延迟路由实现完成，用户自动引导到最近区域
A49: V23-DEP-009 | B49: Cloudflare DNS延迟路由 - 验收 | C49: Acceptance验收 | D49: 全球部署 | E49: P0 | F49: DevOps | G49: 2 | H49: 2026-W26 | I49: 2026-W27 | J49: V23-DEP-008 | K49: 未开始 | L49: 【目标】验收Cloudflare DNS延迟路由的效果。 【验收检查项】 1. 亚洲用户解析到ap-northeast-1 2. 欧洲用户解析到eu-west-1 3. 美洲用户解析到us-east-1 4. 单区域故障时自动切换到健康区域 5. DNS解析延迟小于50ms 【运行命令】cd infra && pytest tests/test_cloudflare.py -v && ./scripts/verify-dns.sh | M49: Cloudflare DNS延迟路由验收通过，地理路由和故障转移正确
A50: V23-DEP-010 | B50: 多区域数据库 - 测试 | C50: Red测试 | D50: 全球部署 | E50: P0 | F50: 后端 | G50: 3 | H50: 2026-W26 | I50: 2026-W27 | K50: 未开始 | L50: 【目标】编写多区域数据库的测试用例。 【运行命令】npm test -- --grep 'multi-region database' 【测试文件路径】src/db/__tests__/multiRegionDb.test.ts 【测试用例清单】 1. test_primary_replica_sync：主从数据库同步正确 2. test_read_from_local_replica：从本地副本读取数据 3. test_write_to_primary：写入操作路由到主库 4. test_cross_region_replication_lag：跨区域复制延迟可接受 5. test_failover_to_replica：主库故障时切换到副本 | M50: 5个多区域数据库测试通过，覆盖同步、读写分离和故障切换
A51: V23-DEP-011 | B51: 多区域数据库 - 实现 | C51: Green实现 | D51: 全球部署 | E51: P0 | F51: 后端 | G51: 8 | H51: 2026-W26 | I51: 2026-W27 | J51: V23-DEP-010 | K51: 未开始 | L51: 【目标】实现多区域数据库，支持跨区域数据同步和读写分离。 【运行命令】npm test -- --grep 'multi-region database' 【实现步骤】 1. 配置Aurora Global Database，主区域us-east-1 2. 添加eu-west-1和ap-northeast-1为副本区域 3. 实现数据库连接池的路由逻辑 4. 写操作路由到主库，读操作路由到本地副本 5. 配置复制延迟监控和告警 6. 实现主库故障时的自动切换 【源文件路径】src/db/MultiRegionDataSource.ts, infra/aws/rds/global-db.tf 【测试文件路径】src/db/__tests__/multiRegionDb.test.ts | M51: 多区域数据库实现完成，读写分离和跨区域同步正常
A52: V23-DEP-012 | B52: 多区域数据库 - 验收 | C52: Acceptance验收 | D52: 全球部署 | E52: P0 | F52: 后端 | G52: 3 | H52: 2026-W26 | I52: 2026-W27 | J52: V23-DEP-011 | K52: 未开始 | L52: 【目标】验收多区域数据库的正确性和性能。 【验收检查项】 1. 主从数据同步延迟小于1秒 2. 读操作从本地副本执行 3. 写操作路由到主库 4. 主库故障时30秒内切换到副本 5. 数据一致性保证 【运行命令】npm run test:e2e -- --grep 'multi-region database' | M52: 多区域数据库验收通过，同步延迟和故障切换达标
A53: V23-DEP-013 | B53: 全球负载均衡 - 测试 | C53: Red测试 | D53: 全球部署 | E53: P0 | F53: DevOps | G53: 2 | H53: 2026-W26 | I53: 2026-W27 | K53: 未开始 | L53: 【目标】编写全球负载均衡的测试用例。 【运行命令】cd infra && pytest tests/test_load_balancer.py -v 【测试文件路径】infra/tests/test_load_balancer.py 【测试用例清单】 1. test_alb_created_in_each_region：各区域ALB创建成功 2. test_target_group_health_check：目标组健康检查通过 3. test_traffic_distribution：流量分配比例正确 4. test_sticky_sessions：会话保持配置正确 5. test_connection_draining：连接排空配置正确 | M53: 5个全球负载均衡测试通过，覆盖ALB、健康检查和流量分配
A54: V23-DEP-014 | B54: 全球负载均衡 - 实现 | C54: Green实现 | D54: 全球部署 | E54: P0 | F54: DevOps | G54: 6 | H54: 2026-W26 | I54: 2026-W27 | J54: V23-DEP-013 | K54: 未开始 | L54: 【目标】实现全球负载均衡，确保流量在各区域均匀分配。 【运行命令】cd infra && terraform plan && terraform apply 【实现步骤】 1. 创建各区域Application Load Balancer 2. 配置目标组和健康检查 3. 设置基于权重的流量分配策略 4. 配置会话保持（Sticky Session） 5. 实现连接排空（Connection Draining） 6. 配置请求速率限制和WAF规则 【源文件路径】infra/aws/loadbalancer/main.tf 【测试文件路径】infra/tests/test_load_balancer.py | M54: 全球负载均衡实现完成，流量分配和健康检查正常
A55: V23-DEP-015 | B55: 全球负载均衡 - 验收 | C55: Acceptance验收 | D55: 全球部署 | E55: P0 | F55: DevOps | G55: 2 | H55: 2026-W26 | I55: 2026-W27 | J55: V23-DEP-014 | K55: 未开始 | L55: 【目标】验收全球负载均衡的效果。 【验收检查项】 1. 各区域ALB健康检查通过 2. 流量按权重正确分配 3. 会话保持生效 4. 后端实例故障时自动摘除 5. 连接排空期间无请求丢失 【运行命令】cd infra && pytest tests/test_load_balancer.py -v && ./scripts/verify-lb.sh | M55: 全球负载均衡验收通过，流量分配和故障处理正确
A56: V23-COM-001 | B56: GDPR数据导出API - 测试 | C56: Red测试 | D56: 合规与法律 | E56: P0 | F56: 后端 | G56: 3 | H56: 2026-W26 | I56: 2026-W27 | K56: 未开始 | L56: 【目标】编写GDPR数据导出API的测试用例。 【运行命令】npm test -- --grep 'GDPR export' 【测试文件路径】src/compliance/__tests__/gdprExport.test.ts 【测试用例清单】 1. test_export_request_creates_job：数据导出请求创建导出任务 2. test_export_includes_all_user_data：导出包含所有用户数据 3. test_export_format_is_json：导出格式为标准JSON 4. test_export_email_notification：导出完成后发送邮件通知 5. test_export_link_expires_after_7_days：导出链接7天后过期 6. test_export_rate_limiting：导出请求限流正确 | M56: 6个GDPR数据导出测试通过，覆盖导出流程、格式和通知
A57: V23-COM-002 | B57: GDPR数据导出API - 实现 | C57: Green实现 | D57: 合规与法律 | E57: P0 | F57: 后端 | G57: 6 | H57: 2026-W26 | I57: 2026-W27 | J57: V23-COM-001 | K57: 未开始 | L57: 【目标】实现GDPR数据导出API，支持用户数据可携带权。 【运行命令】npm test -- --grep 'GDPR export' 【实现步骤】 1. 创建src/compliance/gdpr/DataExportService.ts 2. 实现POST /api/gdpr/export请求数据导出 3. 收集用户所有数据：个人信息、作品、设置、支付记录 4. 生成标准JSON格式导出文件 5. 上传到S3并生成临时下载链接 6. 发送包含下载链接的邮件通知 7. 实现7天过期自动清理 【源文件路径】src/compliance/gdpr/DataExportService.ts 【测试文件路径】src/compliance/__tests__/gdprExport.test.ts | M57: GDPR数据导出API实现完成，支持完整数据导出
A58: V23-COM-003 | B58: GDPR数据导出API - 验收 | C58: Acceptance验收 | D58: 合规与法律 | E58: P0 | F58: 后端 | G58: 2 | H58: 2026-W26 | I58: 2026-W27 | J58: V23-COM-002 | K58: 未开始 | L58: 【目标】验收GDPR数据导出API的合规性。 【验收检查项】 1. 导出数据包含所有用户相关数据 2. 导出格式符合GDPR标准 3. 导出链接7天后自动失效 4. 邮件通知及时发送 5. 导出请求限流生效 6. 敏感数据脱敏处理 【运行命令】npm run test:e2e -- --grep 'gdpr export' | M58: GDPR数据导出API验收通过，符合GDPR合规要求
A59: V23-COM-004 | B59: GDPR数据删除API - 测试 | C59: Red测试 | D59: 合规与法律 | E59: P0 | F59: 后端 | G59: 3 | H59: 2026-W26 | I59: 2026-W27 | K59: 未开始 | L59: 【目标】编写GDPR数据删除API的测试用例。 【运行命令】npm test -- --grep 'GDPR delete' 【测试文件路径】src/compliance/__tests__/gdprDelete.test.ts 【测试用例清单】 1. test_delete_request_creates_ticket：删除请求创建工单 2. test_delete_removes_all_user_data：删除清除所有用户数据 3. test_delete_cascades_to_related_data：级联删除关联数据 4. test_delete_confirmation_email：删除后发送确认邮件 5. test_delete_grace_period：30天宽限期内可撤销 6. test_delete_audit_log：删除操作记录审计日志 | M59: 6个GDPR数据删除测试通过，覆盖删除流程、级联和审计
A60: V23-COM-005 | B60: GDPR数据删除API - 实现 | C60: Green实现 | D60: 合规与法律 | E60: P0 | F60: 后端 | G60: 6 | H60: 2026-W26 | I60: 2026-W27 | J60: V23-COM-004 | K60: 未开始 | L60: 【目标】实现GDPR数据删除API，支持用户被遗忘权。 【运行命令】npm test -- --grep 'GDPR delete' 【实现步骤】 1. 创建src/compliance/gdpr/DataDeleteService.ts 2. 实现POST /api/gdpr/delete请求数据删除 3. 实现30天宽限期机制，期间可撤销 4. 确认删除后级联清除所有关联数据 5. 清除Redis缓存中的用户数据 6. 记录完整的审计日志 7. 发送删除确认邮件 【源文件路径】src/compliance/gdpr/DataDeleteService.ts 【测试文件路径】src/compliance/__tests__/gdprDelete.test.ts | M60: GDPR数据删除API实现完成，支持被遗忘权
A61: V23-COM-006 | B61: GDPR数据删除API - 验收 | C61: Acceptance验收 | D61: 合规与法律 | E61: P0 | F61: 后端 | G61: 2 | H61: 2026-W26 | I61: 2026-W27 | J61: V23-COM-005 | K61: 未开始 | L61: 【目标】验收GDPR数据删除API的合规性。 【验收检查项】 1. 删除后所有用户数据不可恢复 2. 关联数据（作品、评论、支付记录）全部清除 3. 30天宽限期机制正常 4. 审计日志完整记录删除操作 5. 缓存数据同步清除 6. 确认邮件及时发送 【运行命令】npm run test:e2e -- --grep 'gdpr delete' | M61: GDPR数据删除API验收通过，符合GDPR被遗忘权要求
A62: V23-COM-007 | B62: Cookie Consent管理 - 测试 | C62: Red测试 | D62: 合规与法律 | E62: P0 | F62: 前端 | G62: 2 | H62: 2026-W26 | I62: 2026-W27 | K62: 未开始 | L62: 【目标】编写Cookie Consent管理的测试用例。 【运行命令】npm test -- --grep 'cookie consent' 【测试文件路径】src/compliance/__tests__/cookieConsent.test.tsx 【测试用例清单】 1. test_consent_banner_shows_on_first_visit：首次访问显示Cookie横幅 2. test_accept_all_cookies：接受全部Cookie后横幅消失 3. test_reject_optional_cookies：拒绝可选Cookie后仅设置必要Cookie 4. test_consent_preferences_saved：偏好设置保存到localStorage 5. test_consent_banner_not_shown_after_accept：接受后不再显示横幅 6. test_manage_consent_settings：可修改已保存的偏好设置 | M62: 6个Cookie Consent测试通过，覆盖横幅显示、接受/拒绝和偏好管理
A63: V23-COM-008 | B63: Cookie Consent管理 - 实现 | C63: Green实现 | D63: 合规与法律 | E63: P0 | F63: 前端 | G63: 4 | H63: 2026-W26 | I63: 2026-W27 | J63: V23-COM-007 | K63: 未开始 | L63: 【目标】实现Cookie Consent管理，符合GDPR Cookie要求。 【运行命令】npm test -- --grep 'cookie consent' 【实现步骤】 1. 创建src/compliance/cookies/CookieConsentBanner.tsx 2. 实现Cookie分类：必要/分析/营销/功能 3. 创建useCookieConsent hook管理Cookie偏好 4. 实现偏好设置持久化到localStorage 5. 根据偏好控制第三方Cookie的设置 6. 创建Cookie偏好管理面板 【源文件路径】src/compliance/cookies/CookieConsentBanner.tsx, src/compliance/cookies/useCookieConsent.ts 【测试文件路径】src/compliance/__tests__/cookieConsent.test.tsx | M63: Cookie Consent管理实现完成，符合GDPR要求
A64: V23-COM-009 | B64: Cookie Consent管理 - 验收 | C64: Acceptance验收 | D64: 合规与法律 | E64: P0 | F64: 前端 | G64: 2 | H64: 2026-W26 | I64: 2026-W27 | J64: V23-COM-008 | K64: 未开始 | L64: 【目标】验收Cookie Consent管理的合规性。 【验收检查项】 1. 首次访问显示Cookie同意横幅 2. 接受/拒绝操作正确设置Cookie 3. 偏好设置持久化保存 4. 拒绝可选Cookie后不设置对应Cookie 5. 可随时修改偏好设置 6. 横幅UI符合GDPR设计规范 【运行命令】npm run test:e2e -- --grep 'cookie consent' | M64: Cookie Consent管理验收通过，符合GDPR Cookie合规要求
A65: V23-COM-010 | B65: 年龄验证流程 - 测试 | C65: Red测试 | D65: 合规与法律 | E65: P0 | F65: 全栈 | G65: 2 | H65: 2026-W26 | I65: 2026-W27 | K65: 未开始 | L65: 【目标】编写年龄验证流程的测试用例。 【运行命令】npm test -- --grep 'age verification' 【测试文件路径】src/compliance/__tests__/ageVerification.test.tsx 【测试用例清单】 1. test_age_gate_shows_on_signup：注册时显示年龄验证 2. test_under_13_rejected：13岁以下用户被拒绝 3. test_over_13_accepted：13岁及以上用户通过验证 4. test_age_verification_bypass_prevented：无法绕过年龄验证 5. test_age_recorded_in_user_profile：年龄验证结果记录到用户档案 | M65: 5个年龄验证测试通过，覆盖年龄门槛和绕过防护
A66: V23-COM-011 | B66: 年龄验证流程 - 实现 | C66: Green实现 | D66: 合规与法律 | E66: P0 | F66: 全栈 | G66: 4 | H66: 2026-W26 | I66: 2026-W27 | J66: V23-COM-010 | K66: 未开始 | L66: 【目标】实现年龄验证流程，确保符合COPPA等法规。 【运行命令】npm test -- --grep 'age verification' 【实现步骤】 1. 创建src/compliance/age/AgeVerificationGate.tsx 2. 实现出生日期输入和年龄计算 3. 添加13岁年龄门槛检查 4. 拒绝未通过验证的用户注册 5. 将验证结果记录到用户档案 6. 在注册流程中集成年龄验证步骤 【源文件路径】src/compliance/age/AgeVerificationGate.tsx 【测试文件路径】src/compliance/__tests__/ageVerification.test.tsx | M66: 年龄验证流程实现完成，符合COPPA要求
A67: V23-COM-012 | B67: 年龄验证流程 - 验收 | C67: Acceptance验收 | D67: 合规与法律 | E67: P0 | F67: 全栈 | G67: 2 | H67: 2026-W26 | I67: 2026-W27 | J67: V23-COM-011 | K67: 未开始 | L67: 【目标】验收年龄验证流程的合规性。 【验收检查项】 1. 注册流程包含年龄验证步骤 2. 13岁以下用户无法完成注册 3. 13岁及以上用户正常通过 4. 无法通过修改参数绕过验证 5. 验证结果正确记录 【运行命令】npm run test:e2e -- --grep 'age verification' | M67: 年龄验证流程验收通过，符合COPPA合规要求
A68: V23-COM-013 | B68: AI内容声明标签 - 测试 | C68: Red测试 | D68: 合规与法律 | E68: P0 | F68: 前端 | G68: 2 | H68: 2026-W26 | I68: 2026-W27 | K68: 未开始 | L68: 【目标】编写AI内容声明标签的测试用例。 【运行命令】npm test -- --grep 'AI disclosure' 【测试文件路径】src/compliance/__tests__/aiDisclosure.test.tsx 【测试用例清单】 1. test_ai_label_shows_on_ai_content：AI生成内容显示声明标签 2. test_ai_label_not_shows_on_manual_content：手动创作内容不显示标签 3. test_ai_label_includes_model_info：标签包含模型信息 4. test_ai_label_in_export：导出内容包含AI声明 5. test_ai_label_accessible：标签符合无障碍标准 | M68: 5个AI内容声明标签测试通过，覆盖显示、信息和导出
A69: V23-COM-014 | B69: AI内容声明标签 - 实现 | C69: Green实现 | D69: 合规与法律 | E69: P0 | F69: 前端 | G69: 4 | H69: 2026-W26 | I69: 2026-W27 | J69: V23-COM-013 | K69: 未开始 | L69: 【目标】实现AI内容声明标签，符合AI内容透明度法规。 【运行命令】npm test -- --grep 'AI disclosure' 【实现步骤】 1. 创建src/compliance/ai/AIDisclosureLabel.tsx组件 2. 在内容元数据中标记AI生成比例 3. 根据AI参与度显示不同级别的声明标签 4. 标签包含使用的AI模型信息 5. 在内容导出时包含AI声明 6. 确保标签符合无障碍访问标准 【源文件路径】src/compliance/ai/AIDisclosureLabel.tsx 【测试文件路径】src/compliance/__tests__/aiDisclosure.test.tsx | M69: AI内容声明标签实现完成，符合透明度要求
A70: V23-COM-015 | B70: AI内容声明标签 - 验收 | C70: Acceptance验收 | D70: 合规与法律 | E70: P0 | F70: 前端 | G70: 2 | H70: 2026-W26 | I70: 2026-W27 | J70: V23-COM-014 | K70: 未开始 | L70: 【目标】验收AI内容声明标签的合规性。 【验收检查项】 1. AI生成内容正确显示声明标签 2. 手动创作内容不显示标签 3. 标签信息完整（模型、比例） 4. 导出内容包含AI声明 5. 标签UI清晰可见 6. 符合EU AI Act等法规要求 【运行命令】npm run test:e2e -- --grep 'ai disclosure' | M70: AI内容声明标签验收通过，符合AI透明度法规
A71: V23-MON-001 | B71: Sentry错误追踪 - 测试 | C71: Red测试 | D71: 监控与可观测性 | E71: P1 | F71: 全栈 | G71: 2 | H71: 2026-W28 | I71: 2026-W29 | K71: 未开始 | L71: 【目标】编写Sentry错误追踪集成的测试用例。 【运行命令】npm test -- --grep 'Sentry integration' 【测试文件路径】src/monitoring/__tests__/sentry.test.ts 【测试用例清单】 1. test_sentry_initialized_with_correct_dsn：Sentry使用正确DSN初始化 2. test_error_captured_and_reported：错误被捕获并上报 3. test_breadcrumb_recorded：面包屑信息正确记录 4. test_user_context_attached：用户上下文正确附加 5. test_source_map_uploaded：Source Map正确上传 | M71: 5个Sentry测试通过，覆盖初始化、错误捕获和上下文
A72: V23-MON-002 | B72: Sentry错误追踪 - 实现 | C72: Green实现 | D72: 监控与可观测性 | E72: P1 | F72: 全栈 | G72: 4 | H72: 2026-W28 | I72: 2026-W29 | J72: V23-MON-001 | K72: 未开始 | L72: 【目标】实现Sentry错误追踪集成，实现全栈错误监控。 【运行命令】npm test -- --grep 'Sentry integration' 【实现步骤】 1. 安装@sentry/react和@sentry/node 2. 创建src/monitoring/sentry/init.ts初始化配置 3. 配置前端React ErrorBoundary集成 4. 配置后端Express中间件集成 5. 实现用户上下文附加（用户ID、语言、订阅计划） 6. 配置Source Map上传到Sentry 7. 设置告警规则和通知渠道 【源文件路径】src/monitoring/sentry/init.ts 【测试文件路径】src/monitoring/__tests__/sentry.test.ts | M72: Sentry错误追踪实现完成，前后端错误监控生效
A73: V23-MON-003 | B73: Sentry错误追踪 - 验收 | C73: Acceptance验收 | D73: 监控与可观测性 | E73: P1 | F73: 全栈 | G73: 2 | H73: 2026-W28 | I73: 2026-W29 | J73: V23-MON-002 | K73: 未开始 | L73: 【目标】验收Sentry错误追踪的完整性和可用性。 【验收检查项】 1. 前端错误自动上报到Sentry 2. 后端错误自动上报到Sentry 3. 错误包含完整的堆栈和上下文 4. Source Map正确解析，错误可定位到源码 5. 告警通知及时发送 【运行命令】npm run test:e2e -- --grep 'sentry' && ./scripts/verify-sentry.sh | M73: Sentry错误追踪验收通过，全栈错误监控可用
A74: V23-MON-004 | B74: Datadog APM - 测试 | C74: Red测试 | D74: 监控与可观测性 | E74: P1 | F74: 全栈 | G74: 2 | H74: 2026-W28 | I74: 2026-W29 | K74: 未开始 | L74: 【目标】编写Datadog APM集成的测试用例。 【运行命令】npm test -- --grep 'Datadog APM' 【测试文件路径】src/monitoring/__tests__/datadog.test.ts 【测试用例清单】 1. test_datadog_agent_connected：Datadog Agent连接成功 2. test_traces_generated_for_api_calls：API调用生成trace 3. test_custom_spans_created：自定义span正确创建 4. test_service_map_generated：服务地图正确生成 5. test_performance_metrics_collected：性能指标正确采集 | M74: 5个Datadog APM测试通过，覆盖连接、trace和指标
A75: V23-MON-005 | B75: Datadog APM - 实现 | C75: Green实现 | D75: 监控与可观测性 | E75: P1 | F75: 全栈 | G75: 5 | H75: 2026-W28 | I75: 2026-W29 | J75: V23-MON-004 | K75: 未开始 | L75: 【目标】实现Datadog APM集成，实现应用性能监控。 【运行命令】npm test -- --grep 'Datadog APM' 【实现步骤】 1. 部署Datadog Agent到各区域ECS集群 2. 安装dd-trace SDK：npm install dd-trace 3. 创建src/monitoring/datadog/init.ts初始化配置 4. 为关键API端点添加自定义span 5. 配置服务名称和环境标签 6. 设置性能基线和告警规则 【源文件路径】src/monitoring/datadog/init.ts 【测试文件路径】src/monitoring/__tests__/datadog.test.ts | M75: Datadog APM实现完成，应用性能监控生效
A76: V23-MON-006 | B76: Datadog APM - 验收 | C76: Acceptance验收 | D76: 监控与可观测性 | E76: P1 | F76: 全栈 | G76: 2 | H76: 2026-W28 | I76: 2026-W29 | J76: V23-MON-005 | K76: 未开始 | L76: 【目标】验收Datadog APM的监控效果。 【验收检查项】 1. API请求trace完整可见 2. 服务依赖关系正确展示 3. 慢请求自动标记 4. 性能指标实时更新 5. 告警规则正确触发 【运行命令】npm run test:e2e -- --grep 'datadog' && ./scripts/verify-datadog.sh | M76: Datadog APM验收通过，性能监控和告警正常
A77: V23-MON-007 | B77: CloudWatch日志 - 测试 | C77: Red测试 | D77: 监控与可观测性 | E77: P1 | F77: DevOps | G77: 2 | H77: 2026-W28 | I77: 2026-W29 | K77: 未开始 | L77: 【目标】编写CloudWatch日志配置的测试用例。 【运行命令】cd infra && pytest tests/test_cloudwatch.py -v 【测试文件路径】infra/tests/test_cloudwatch.py 【测试用例清单】 1. test_log_group_created：日志组创建成功 2. test_log_stream_created：日志流创建成功 3. test_log_retention_configured：日志保留期配置正确 4. test_log_metric_filter：日志指标过滤器正确 5. test_cross_region_log_aggregation：跨区域日志聚合正确 | M77: 5个CloudWatch日志测试通过，覆盖日志组和过滤器
A78: V23-MON-008 | B78: CloudWatch日志 - 实现 | C78: Green实现 | D78: 监控与可观测性 | E78: P1 | F78: DevOps | G78: 4 | H78: 2026-W28 | I78: 2026-W29 | J78: V23-MON-007 | K78: 未开始 | L78: 【目标】实现CloudWatch日志配置，实现集中式日志管理。 【运行命令】cd infra && terraform plan && terraform apply 【实现步骤】 1. 创建infra/aws/cloudwatch/logs.tf日志配置 2. 为每个服务创建独立的日志组 3. 配置日志保留期（90天热存储，365天冷存储） 4. 创建日志指标过滤器（ERROR、WARN级别） 5. 配置跨区域日志聚合到中央区域 6. 设置日志订阅到S3长期归档 【源文件路径】infra/aws/cloudwatch/logs.tf 【测试文件路径】infra/tests/test_cloudwatch.py | M78: CloudWatch日志配置完成，集中式日志管理生效
A79: V23-MON-009 | B79: CloudWatch日志 - 验收 | C79: Acceptance验收 | D79: 监控与可观测性 | E79: P1 | F79: DevOps | G79: 2 | H79: 2026-W28 | I79: 2026-W29 | J79: V23-MON-008 | K79: 未开始 | L79: 【目标】验收CloudWatch日志配置的完整性。 【验收检查项】 1. 各服务日志正确发送到对应日志组 2. 日志保留期配置正确 3. 日志指标过滤器正确触发 4. 跨区域日志聚合正常 5. 日志查询和检索功能可用 【运行命令】cd infra && pytest tests/test_cloudwatch.py -v && ./scripts/verify-logs.sh | M79: CloudWatch日志验收通过，日志管理配置正确
A80: V23-MON-010 | B80: PagerDuty告警 - 测试 | C80: Red测试 | D80: 监控与可观测性 | E80: P1 | F80: DevOps | G80: 2 | H80: 2026-W28 | I80: 2026-W29 | K80: 未开始 | L80: 【目标】编写PagerDuty告警集成的测试用例。 【运行命令】cd infra && pytest tests/test_pagerduty.py -v 【测试文件路径】infra/tests/test_pagerduty.py 【测试用例清单】 1. test_pagerduty_service_created：PagerDuty服务创建成功 2. test_alert_triggered_on_error：错误时触发告警 3. test_alert_escalation_policy：告警升级策略正确 4. test_alert_acknowledged：告警确认流程正确 5. test_alert_auto_resolve：告警自动解决 | M80: 5个PagerDuty告警测试通过，覆盖触发、升级和解决
A81: V23-MON-011 | B81: PagerDuty告警 - 实现 | C81: Green实现 | D81: 监控与可观测性 | E81: P1 | F81: DevOps | G81: 4 | H81: 2026-W28 | I81: 2026-W29 | J81: V23-MON-010 | K81: 未开始 | L81: 【目标】实现PagerDuty告警集成，建立完善的告警体系。 【运行命令】cd infra && python scripts/setup_pagerduty.py 【实现步骤】 1. 创建PagerDuty服务和集成 2. 配置告警升级策略（L1→L2→L3→经理） 3. 创建CloudWatch告警到PagerDuty的集成 4. 配置Sentry错误告警到PagerDuty 5. 设置Datadog APM告警到PagerDuty 6. 定义告警分类和优先级 【源文件路径】infra/monitoring/pagerduty/config.tf 【测试文件路径】infra/tests/test_pagerduty.py | M81: PagerDuty告警集成完成，告警体系建立
A82: V23-MON-012 | B82: PagerDuty告警 - 验收 | C82: Acceptance验收 | D82: 监控与可观测性 | E82: P1 | F82: DevOps | G82: 2 | H82: 2026-W28 | I82: 2026-W29 | J82: V23-MON-011 | K82: 未开始 | L82: 【目标】验收PagerDuty告警体系的完整性。 【验收检查项】 1. 错误告警正确触发PagerDuty 2. 告警升级策略按时执行 3. 告警确认和解决流程正常 4. 多渠道通知（邮件/短信/Push） 5. 告警历史可查询 【运行命令】cd infra && pytest tests/test_pagerduty.py -v && ./scripts/verify-pagerduty.sh | M82: PagerDuty告警验收通过，告警体系完整可用
A83: V23-INT-001 | B83: 多语言UI切换测试 - 测试 | C83: Red测试 | D83: 全球版集成测试 | E83: P0 | F83: 测试 | G83: 2 | H83: 2026-W26 | I83: 2026-W27 | K83: 未开始 | L83: 【目标】编写多语言UI切换的E2E测试用例。 【运行命令】npm run test:e2e -- --grep 'multilingual UI switch' 【测试文件路径】e2e/tests/multilingualUISwitch.test.ts 【测试用例清单】 1. test_switch_from_zh_to_en_complete：中文切换英文，所有页面文本更新 2. test_switch_from_en_to_zh_complete：英文切换中文，所有页面文本更新 3. test_language_persist_after_page_navigation：页面导航后语言保持 4. test_language_persist_after_browser_refresh：浏览器刷新后语言保持 5. test_no_mixed_language_display：无中英文混合显示 6. test_rtl_not_applied_for_zh_en：中英文不应用RTL布局 | M83: 6个多语言UI切换E2E测试通过，覆盖切换、持久化和一致性
A84: V23-INT-002 | B84: 多语言UI切换测试 - 实现 | C84: Green实现 | D84: 全球版集成测试 | E84: P0 | F84: 测试 | G84: 4 | H84: 2026-W26 | I84: 2026-W27 | J84: V23-INT-001 | K84: 未开始 | L84: 【目标】实现多语言UI切换的E2E测试自动化。 【运行命令】npm run test:e2e -- --grep 'multilingual UI switch' 【实现步骤】 1. 配置Playwright多语言测试环境 2. 编写语言切换的Page Object 3. 实现各页面的文本断言（Sidebar/Editor/Settings） 4. 实现语言持久化的测试场景 5. 添加截图对比验证UI布局 6. 集成到CI/CD流水线 【源文件路径】e2e/pages/LanguageSwitchPage.ts, e2e/tests/multilingualUISwitch.test.ts 【测试文件路径】e2e/tests/multilingualUISwitch.test.ts | M84: 多语言UI切换E2E测试实现完成，自动化运行正常
A85: V23-INT-003 | B85: 多语言UI切换测试 - 验收 | C85: Acceptance验收 | D85: 全球版集成测试 | E85: P0 | F85: 测试 | G85: 2 | H85: 2026-W26 | I85: 2026-W27 | J85: V23-INT-002 | K85: 未开始 | L85: 【目标】验收多语言UI切换测试的覆盖率和可靠性。 【验收检查项】 1. E2E测试覆盖所有主要页面 2. 中英文切换无遗漏文本 3. 语言持久化验证通过 4. 测试在CI中稳定运行 5. 截图对比无回归 【运行命令】npm run test:e2e -- --grep 'multilingual' | M85: 多语言UI切换测试验收通过，覆盖率和稳定性达标
A86: V23-INT-004 | B86: Stripe支付流程E2E - 测试 | C86: Red测试 | D86: 全球版集成测试 | E86: P0 | F86: 测试 | G86: 3 | H86: 2026-W26 | I86: 2026-W27 | K86: 未开始 | L86: 【目标】编写Stripe支付流程的E2E测试用例。 【运行命令】npm run test:e2e -- --grep 'Stripe payment E2E' 【测试文件路径】e2e/tests/stripePaymentE2E.test.ts 【测试用例清单】 1. test_complete_payment_flow：完整支付流程（选择计划→支付→确认） 2. test_payment_with_test_card：使用Stripe测试卡完成支付 3. test_payment_failure_handling：支付失败错误处理正确 4. test_subscription_activation_after_payment：支付后订阅激活 5. test_upgrade_subscription_flow：升级订阅流程正确 6. test_cancel_subscription_flow：取消订阅流程正确 | M86: 6个Stripe支付E2E测试通过，覆盖完整支付生命周期
A87: V23-INT-005 | B87: Stripe支付流程E2E - 实现 | C87: Green实现 | D87: 全球版集成测试 | E87: P0 | F87: 测试 | G87: 5 | H87: 2026-W26 | I87: 2026-W27 | J87: V23-INT-004 | K87: 未开始 | L87: 【目标】实现Stripe支付流程的E2E测试自动化。 【运行命令】npm run test:e2e -- --grep 'Stripe payment E2E' 【实现步骤】 1. 配置Stripe测试环境（测试密钥和Webhook） 2. 创建PaymentPage Object封装支付页面操作 3. 实现完整支付流程测试（选择计划→Checkout→回调） 4. 使用Stripe测试卡模拟各种支付场景 5. 实现订阅管理测试（升级/降级/取消） 6. 集成到CI/CD流水线 【源文件路径】e2e/pages/PaymentPage.ts, e2e/tests/stripePaymentE2E.test.ts 【测试文件路径】e2e/tests/stripePaymentE2E.test.ts | M87: Stripe支付E2E测试实现完成，覆盖完整支付流程
A88: V23-INT-006 | B88: Stripe支付流程E2E - 验收 | C88: Acceptance验收 | D88: 全球版集成测试 | E88: P0 | F88: 测试 | G88: 2 | H88: 2026-W26 | I88: 2026-W27 | J88: V23-INT-005 | K88: 未开始 | L88: 【目标】验收Stripe支付E2E测试的覆盖率和可靠性。 【验收检查项】 1. 支付流程E2E测试全部通过 2. 覆盖成功/失败/取消等场景 3. 订阅管理测试覆盖升级/降级/取消 4. 测试在CI中稳定运行 5. 测试数据自动清理 【运行命令】npm run test:e2e -- --grep 'stripe payment' | M88: Stripe支付E2E测试验收通过，覆盖率和稳定性达标
A89: V23-INT-007 | B89: GDPR合规测试 - 测试 | C89: Red测试 | D89: 全球版集成测试 | E89: P0 | F89: 测试 | G89: 2 | H89: 2026-W26 | I89: 2026-W27 | K89: 未开始 | L89: 【目标】编写GDPR合规的E2E测试用例。 【运行命令】npm run test:e2e -- --grep 'GDPR compliance' 【测试文件路径】e2e/tests/gdprCompliance.test.ts 【测试用例清单】 1. test_data_export_request_and_download：数据导出请求和下载完整流程 2. test_data_deletion_request_and_confirmation：数据删除请求和确认流程 3. test_cookie_consent_flow：Cookie同意流程完整 4. test_age_verification_flow：年龄验证流程完整 5. test_privacy_policy_accessible：隐私政策页面可访问 | M89: 5个GDPR合规E2E测试通过，覆盖导出、删除、Cookie和年龄验证
A90: V23-INT-008 | B90: GDPR合规测试 - 实现 | C90: Green实现 | D90: 全球版集成测试 | E90: P0 | F90: 测试 | G90: 4 | H90: 2026-W26 | I90: 2026-W27 | J90: V23-INT-007 | K90: 未开始 | L90: 【目标】实现GDPR合规的E2E测试自动化。 【运行命令】npm run test:e2e -- --grep 'GDPR compliance' 【实现步骤】 1. 创建GDPR测试工具类（用户数据创建/清理） 2. 实现数据导出E2E测试（请求→等待→下载→验证） 3. 实现数据删除E2E测试（请求→宽限期→确认→验证） 4. 实现Cookie Consent E2E测试 5. 实现年龄验证E2E测试 6. 集成到CI/CD流水线 【源文件路径】e2e/tests/gdprCompliance.test.ts, e2e/utils/GDPRTestHelper.ts 【测试文件路径】e2e/tests/gdprCompliance.test.ts | M90: GDPR合规E2E测试实现完成，覆盖所有合规场景
A91: V23-INT-009 | B91: GDPR合规测试 - 验收 | C91: Acceptance验收 | D91: 全球版集成测试 | E91: P0 | F91: 测试 | G91: 2 | H91: 2026-W26 | I91: 2026-W27 | J91: V23-INT-008 | K91: 未开始 | L91: 【目标】验收GDPR合规测试的覆盖率和合规性。 【验收检查项】 1. 数据导出测试验证导出完整性 2. 数据删除测试验证数据彻底清除 3. Cookie Consent测试验证合规性 4. 年龄验证测试验证COPPA合规 5. 测试在CI中稳定运行 【运行命令】npm run test:e2e -- --grep 'gdpr compliance' | M91: GDPR合规测试验收通过，覆盖所有合规要求
A92: V23-INT-010 | B92: 全球延迟测试 - 测试 | C92: Red测试 | D92: 全球版集成测试 | E92: P0 | F92: DevOps | G92: 2 | H92: 2026-W26 | I92: 2026-W27 | K92: 未开始 | L92: 【目标】编写全球延迟测试的测试用例。 【运行命令】cd infra && pytest tests/test_global_latency.py -v 【测试文件路径】infra/tests/test_global_latency.py 【测试用例清单】 1. test_api_latency_us_east_1：us-east-1 API延迟<100ms 2. test_api_latency_eu_west_1：eu-west-1 API延迟<200ms 3. test_api_latency_ap_northeast_1：ap-northeast-1 API延迟<200ms 4. test_static_asset_cdn_latency：CDN静态资源延迟<50ms 5. test_dns_resolution_latency：DNS解析延迟<50ms | M92: 5个全球延迟测试通过，覆盖各区域API和CDN延迟
A93: V23-INT-011 | B93: 全球延迟测试 - 实现 | C93: Green实现 | D93: 全球版集成测试 | E93: P0 | F93: DevOps | G93: 4 | H93: 2026-W26 | I93: 2026-W27 | J93: V23-INT-010 | K93: 未开始 | L93: 【目标】实现全球延迟测试自动化，持续监控各区域性能。 【运行命令】cd infra && pytest tests/test_global_latency.py -v 【实现步骤】 1. 创建infra/tests/global_latency_test.py延迟测试脚本 2. 配置各区域测试端点 3. 实现API延迟测试（从各区域发起请求） 4. 实现CDN延迟测试（全球各节点） 5. 实现DNS解析延迟测试 6. 生成延迟报告并设置阈值告警 7. 集成到CI/CD和定时任务 【源文件路径】infra/tests/global_latency_test.py, infra/scripts/latency_report.py 【测试文件路径】infra/tests/test_global_latency.py | M93: 全球延迟测试实现完成，持续监控各区域性能
A94: V23-INT-012 | B94: 全球延迟测试 - 验收 | C94: Acceptance验收 | D94: 全球版集成测试 | E94: P0 | F94: DevOps | G94: 2 | H94: 2026-W26 | I94: 2026-W27 | J94: V23-INT-011 | K94: 未开始 | L94: 【目标】验收全球延迟测试的覆盖率和准确性。 【验收检查项】 1. 三个区域API延迟均达标 2. CDN延迟全球范围内<100ms 3. DNS解析延迟<50ms 4. 延迟报告自动生成 5. 超阈值告警正确触发 【运行命令】cd infra && pytest tests/test_global_latency.py -v && ./scripts/run-latency-test.sh | M94: 全球延迟测试验收通过，各区域性能达标
